Workbook

Sheet Summary
F1: Updated on | G1: 46218
A2: Engg VP | B2: Engg Director | C2: Component | D2: Count of Sub-component
A3: Justin Hou | B3: Koyeli Dasgupta | C3: L&D | D3: 1 | F3: Confluence
A4: Keith Wiseman | B4: Vaibhav Saini | C4: APC | D4: 3 | F4: https://tekion.atlassian.net/wiki/spaces/TW/pages/4454875476/JIRA+Component+Sub-Component+Cleanup
C5: ApplicationPlatforms | D5: 10
B6: Bobby Alexander | C6: OnboardingPlatforms | D6: 9
C7: ZEBRA | D7: 3
A8: Kunal Bhattacharya | B8: Kapileshwar Punna | C8: Security | D8: 5
A9: Marc Stillman | B9: Gaurav Sharma | C9: VOC | D9: 1
A10: Raghu Edalur | B10: Jawahar Prasad | C10: ORBIT | D10: 7
C11: T1Platform | D11: 3
B12: Parul Jain | C12: HorizontalPlatforms | D12: 12
B13: Raghu Edalur | C13: Architecture | D13: 1
A14: Santosh Golecha | B14: Aditya Kolli | C14: AEPlatform | D14: 12
C15: AMC | D15: 1
B16: Ankur Agarwal | C16: DR_Honda | D16: 16
C17: DR_Hyundai | D17: 4
C18: Fleet_Honda | D18: 10
C19: IOT | D19: 4
B20: Manoj Kansal | C20: DR_GM | D20: 37
B21: Santosh Golecha | C21: AECIntegration | D21: 3
C22: DR_Ford | D22: 3
A23: Sanyam Agrawal | B23: Ambuj Mehra | C23: PayTek | D23: 3
B24: Anirudh Agarwal | C24: Parts | D24: 18
B25: Fahad Tasleem | C25: Accounting | D25: 8
C26: Cashiering | D26: 1
C27: eSign_Platform | D27: 1
C28: Payroll | D28: 4
B29: Prashant Gupta, Vraj Solanki | C29: Service | D29: 15
A30: Satish Sallakonda | B30: Anvesh Aileni | C30: Analytics | D30: 5
B31: Bob Wagoner | C31: Data_Services | D31: 5
B32: Prakash Mohan | C32: ARCIntegration | D32: 4
B33: Satish Sallakonda | C33: AI_Core | D33: 12
C34: APEX | D34: 10
B35: Ajay Rao | C35: DataPlatform | D35: 9
B36: Satyajeet Singh | C36: AIE_Core | D36: 12
C37: AIE_Platform | D37: 10
A38: Srin Tangirala | B38: Arul Jothi | C38: DataEngg | D38: 3
B39: Srin Tangirala | C39: Professional_Services | D39: 1
A40: Teza Mukkavilli | B40: Ramesh Sarabu | C40: TOC_Horizontal | D40: 7
B41: Vijay Kumar | C41: IT_Team | D41: 1
C42: TOC | D42: 22
A43: Ved Singh | B43: Arun Gangadhar | C43: Campaign | D43: 1
C44: CRM | D44: 13
B45: Damodara Reddy | C45: FnI | D45: 8
C46: Galaxy | D46: 6
C47: TDP | D47: 1
B48: Karan Jeet Singh | C48: Retail | D48: 7
B49: Ketan Dikshit | C49: AIBDC | D49: 6
C50: Communication | D50: 5
C51: DigitalRetailing | D51: 5
A52: Viraj Patel | B52: Saurabh Goyal | C52: Infra | D52: 3
C53: PerformanceEngg | D53: 1
A54: (blank) | B54: (blank) | C54: (blank)
A55: Turker Coskun | B55: Prakash Mohan | C55: ARCIntegration | D55: 9
C56: SIPlatform | D56: 4
A57: Sowmya Shivalli Malliah | B57: (blank) | C57: People_Team | D57: 1
A58: Grand Total | D58: 366

Sheet Unique Components
A1: Component
A2: CRM | B2: Ved Singh
A3: Core | B3: Uma Shanker
A4: RuleEngine | B4: Uma Shanker
A5: Campaign | B5: Ved Singh
A6: Bootstrapping | B6: Uma Shanker
A7: ARCIntegration | B7: Satish
A8: CMS | B8: Satish
A9: Galaxy | B9: Ved Singh
A10: Retail | B10: Ved Singh
A11: ML | B11: Satish
A12: Accounting | B12: Sanyam
A13: Payroll | B13: Sanyam
... A20: Platform | B20: Uma Shanker
A21: PerformanceEngg
A22: APC | B22: Uma Shanker
A23: DataPlatform | B23: Satish
A24: AECPlatform | B24: Ved Singh
A25: Analytics | B25: Satish
A26: Insights
A27: TAP | B27: Teza
A28: DataEngg
A29: Infra | B29: Viraj
A30: IOT/Hardware
A31: DR_GM
A32: DR_Ford
A33: AECIntegration
A34: L&D
A35: DR_Honda
A36: DealerLaunchAutomation
A37: FnI
A38: Architecture
A39: AIBDC
A40: DR_Hyundai
A41: MLPlatform
... A45: HR_Team

Sheet Projects
A1: Unique Projects | B1: JIRA Key | C1: Phase | D1: Capacity per Release | F1: Phase | G1: Starts
A2: Accounting & Payroll | B2: ACCT | C2: GA | F2: Pilot v1 | G2: July sprint
A3: AEC Platform | B3: AECP | C3: GA | F3: Pilot v2 | G3: Aug sprint
A4: Data & Analytics | B4: DATA | C4: GA | F4: GA | G4: Oct sprint
A5: APC | B5: APC | C5: GA
A6: Integration | B6: INT | C6: GA
A7: CRM | B7: CRM | C7: Pilot v1 | D7: 560
A8: PayTek | B8: PYTK | C8: Pilot v1 | D8: 170
A9: Core | B9: CORE | C9: GA
A10: Migration & Conversion | B10: MICV | C10: GA
A11: FnI | B11: FNI | C11: Pilot v1 | D11: 216
A12: Galaxy | B12: GAL | C12: Pilot v1 | D12: 120
A13: Mobile | B13: MOB | C13: GA
A14: Parts | B14: PART | C14: GA
A15: Platform | B15: PLTF | C15: GA
A16: Retail | B16: RETL | C16: Pilot v2
A17: Service | B17: SERV | C17: GA
A18: Hyundai | B18: HYUN | C18: Pilot v2
A19: AIBDC | B19: AIB | C19: Pilot v1
A20: Reliability | B20: RELB | C20: Pilot v2
A26: Component | B26: Engg Director / Leader | C26: Project | D26: Key | E26: Remarks
A27: Accounting | B27: Fahad Tasleem | C27: Accounting & Payroll | D27: ACCT
A28: AECIntegration | B28: Santosh Golecha | E28: To be discussed later
A29: AECPlatform | B29: Jawahar Prasad | C29: AEC Platform | D29: AECP
A30: Analytics | B30: Venkateswarlu Yerramalli | C30: Data & Analytics | D30: DATA
A31: APC | B31: Vaibhav Saini | C31: APC | D31: APC
A32: ARCIntegration | B32: Prakash Mohan | C32: Integration | D32: INT
A33: Campaign | B33: Abhishek Agarwala | C33: CRM | D33: CRM | E33: Merged under CRM
A34: Cashiering | B34: Prashant Gupta | C34: PayTek | D34: PYTK | E34: Needs discussion as Engg team reports to Prashant Gupta
A35: CMS | B35: Satish Sallakonda | C35: Data & Analytics | D35: DATA
A36: Core | B36: Surya Narayanan | C36: Core | D36: CORE
A37: CRM | B37: Abhishek Agarwala | C37: CRM | D37: CRM
A38: DataEngg | B38: Arul Jothi | C38: Migration & Conversion | D38: MICV
A39: DataPlatform | B39: Raghu Ram Vengalil | C39: Data & Analytics | D39: DATA
A40: DealerLaunchAutomation | B40: Surya Narayanan | E40: To be discussed later
A41: DR_Ford | B41: Santosh Golecha | E41: To be discussed later
A42: DR_GM | B42: Santosh Golecha | E42: To be discussed later
A43: DR_Honda | B43: Santosh Golecha | E43: To be discussed later
A44: eSign_Platform | B44: Prashant Gupta | C44: FnI | D44: FNI | E44: Needs discussion as Engg team reports to Prashant Gupta
A45: FnI | B45: Abhishek Agarwala | C45: FnI | D45: FNI
A46: Galaxy | B46: Damodara Reddy | C46: Galaxy | D46: GAL
A47: Infra | B47: Saurabh Goyal | C47: Reliability | D47: RELB
A48: Insights | B48: Raghu Ram Vengalil | C48: Data & Analytics | D48: DATA
A49: IOT/Hardware | B49: Robert Manoharan
A50: L&D | B50: Justin Hou
A51: ML | B51: Nitika Gupta | C51: Data & Analytics | D51: DATA
A52: MobilePlatform | B52: Prashant Gupta | C52: Mobile | D52: MOB | E52: Needs discussion
A53: Bootstrapping | B53: Surya Narayanan | E53: DOS project?? Needs discussion
A54: Parts | B54: Anirudh Agrawal | C54: Parts | D54: PART
A55: Payroll | B55: Fahad Tasleem | C55: Accounting & Payroll | D55: ACCT
A56: PayTek | B56: Ved Surtani | C56: PayTek | D56: PYTK
A57: PerformanceEngg | B57: Parul Jain | E57: To be merged with Infra? VOC?
A58: Platform | B58: Parul Jain | C58: Platform | D58: PLTF
A59: Retail | B59: Abhishek Agarwala | C59: Retail | D59: RETL
A60: RuleEngine | B60: Surya Narayanan | C60: Core | D60: CORE
A61: Service | B61: Prashant Gupta | C61: Service | D61: SERV
A62: TAP | B62: Vijay Kumar | E62: Works on TAP
A63: DR_Hyundai | B63: Santosh Golecha | C63: Hyundai | D63: HYUN
A64: MLPlatform | B64: Raghu Ram Vengalil | C64: Data & Analytics | D64: DATA
A65: AIBDC | B65: Ved Singh | C65: AIBDC | D65: AIB
A66: VOC | B66: Gaurav Sharma | E66: Needs discussion
B68: Merged with Other Component
B69: New project not needed

Sheet JIRA
A1: Component JIRA mapping | J1: Sub-component JIRA mapping
A3: Project | B3: Issue type | C3: Required | D3: Create Screen | E3: View Screen | F3: Edit Screen | G3: Mandatory | H3: Remarks | J3: Project | K3: Issue type | L3: Required | M3: Create Screen | N3: View Screen | O3: Edit Screen | P3: Mandatory | Q3: Remarks
A4: ENG | B4: Story | C4: Y | D4: Y | E4: Y | F4: Y | G4: Y | J4: ENG | K4: Story | L4: Y | M4: Y | N4: Y | O4: Y | P4: Y
A5: ENG | B5: Bug | C5: Y | D5: Y | E5: Y | F5: Y | G5: Y | J5: ENG | K5: Bug | L5: Y | M5: Y | N5: Y | O5: Y | P5: N | Q5: Transition
A6: ENG | B6: Epic | C6: Y | D6: Y | E6: Y | F6: Y | G6: Y | J6: ENG | K6: Epic | L6: Y | M6: Y | N6: Y | O6: Y | P6: N
A7: ENG | B7: Feature | C7: Y | D7: Y | E7: Y | F7: Y | G7: Y | J7: ENG | K7: Feature | L7: N | M7: N | N7: N | O7: N | P7: N
A8: ENG | B8: HFR | C8: Y | D8: Y | E8: Y | F8: Y | G8: Y | J8: ENG | K8: HFR | L8: N | M8: N | N8: N | O8: N | P8: N
A9: ENG | B9: TAP Ticket | C9: Y | D9: Y | E9: Y | F9: Y | G9: Y | J9: ENG | K9: TAP Ticket | L9: Y | M9: Y | N9: Y | O9: Y | P9: N | Q9: Transition
A10: ENG | B10: Task | C10: Y | D10: Y | E10: Y | F10: Y | G10: N | H10: TBD | J10: ENG | K10: Task | L10: Y | M10: Y | N10: Y | O10: Y | P10: N | Q10: TBD
A11: ENG | B11: Sub-task | C11: Y | D11: Y | E11: Y | F11: Y | G11: N | H11: TBD | J11: ENG | K11: Sub-task | L11: Y | M11: Y | N11: Y | O11: Y | P11: N | Q11: TBD
A12: ENG | B12: TCC Incident | C12: Y | D12: Y | E12: Y | F12: Y | G12: N | H12: Transition | J12: ENG | K12: TCC Incident | L12: Y | M12: Y | N12: Y | O12: Y | P12: N | Q12: Transition
A13: PM | B13: Epic | C13: Y | D13: Y | E13: Y | F13: Y | G13: Y | J13: PM | K13: Epic | L13: Y | M13: Y | N13: Y | O13: Y | P13: N
A14: PM | B14: Feature | C14: Y | D14: Y | E14: Y | F14: Y | G14: Y | J14: PM | K14: Feature | L14: N | M14: N | N14: N | O14: N | P14: N
A15: PM | B15: Initiative | C15: N | D15: N | E15: N | F15: N | G15: N | J15: PM | K15: Initiative | L15: N | M15: N | N15: N | O15: N | P15: N
A16: PM | B16: SCR | C16: Y | D16: Y | E16: Y | F16: N | G16: Y | J16: PM | K16: SCR | L16: N | M16: N | N16: N | O16: N | P16: N

Sheet Component Masterlist v2
A1: Component | B1: Sub-component | C1: Sub-Component Owner - EM | D1: Sr. Engg Manager | E1: Engg Director | F1: Sr. Engg Director | G1: Engg VP | H1: PM | I1: Manager, PM | J1: Sr. Manager, PM | K1: Product Director | L1: Sr. Product Director | M1: Product VP | N1: SDET | O1: Scrum Team | P1: PDLC Project Key | Q1: TPM Assigned | R1: Old Sub-component Name
A2: CRM | B2: CRM-Lead_Assignment | C2: Nitesh Khadanga | E2: Arun Gangadhar | G2: Ved Singh | H2: Shivam Arora | I2: Subhash Mohan | K2: Rashmi Prakash | L2: Gaurav Gupta | M2: Satyavrat Mudgil | N2: Komala | O2: {=IFERROR( INDEX('Scrum Teams'!B$2:B$1010, MATCH(1, (B2='Scrum Teams'!F$2:F$1010) + (B2='Scrum Teams'!G$2:G$1010) + (B2='Scrum Teams'!H$2:H$1010) + (B2='Scrum Teams'!I$2:I$1010) + (B2='Scrum Teams'!J$2:J$1010) + (B2='Scrum Teams'!K$2:K$1010) + (B2='Scrum Teams'!L$2:L$1010) + (B2='Scrum Teams'!M$2:M$1010) + (B2='Scrum Teams'!N$2:N$1010) + (B2='Scrum Teams'!O$2:O$1010) + (B2='Scrum Teams'!P$2:P$1010) + (B2='Scrum Teams'!Q$2:Q$1010), 0) ), "Not found" )} -> Wolverine | P2: CRM | Q2: Srividya Mandalapu
A3: CRM | B3: CRM-Leads | C3: Nitesh Khadanga | E3: Arun Gangadhar | G3: Ved Singh | H3: Jitendra Rahangdale | I3: Subhash Mohan | K3: Rashmi Prakash | L3: Gaurav Gupta | M3: Satyavrat Mudgil | N3: Komala | O3: {=IFERROR( INDEX('Scrum Teams'!B$2:B$1010, MATCH(1, (B3='Scrum Teams'!F$2:F$1010) + (B3='Scrum Teams'!G$2:G$1010) + (B3='Scrum Teams'!H$2:H$1010) + (B3='Scrum Teams'!I$2:I$1010) + (B3='Scrum Teams'!J$2:J$1010) + (B3='Scrum Teams'!K$2:K$1010) + (B3='Scrum Teams'!L$2:L$1010) + (B3='Scrum Teams'!M$2:M$1010) + (B3='Scrum Teams'!N$2:N$1010) + (B3='Scrum Teams'!O$2:O$1010) + (B3='Scrum Teams'!P$2:P$1010) + (B3='Scrum Teams'!Q$2:Q$1010), 0) ), "Not found" )} -> Wolverine | P3: CRM | Q3: Srividya Mandalapu
A4: CRM | B4: CRM-Migration | C4: Mani T | E4: Arun Gangadhar | G4: Ved Singh | H4: Subhash Mohan | K4: Rashmi Prakash | L4: Gaurav Gupta | M4: Satyavrat Mudgil | N4: Komala | O4: {=IFERROR( INDEX('Scrum Teams'!B$2:B$1010, MATCH(1, (B4='Scrum Teams'!F$2:F$1010) + (B4='Scrum Teams'!G$2:G$1010) + (B4='Scrum Teams'!H$2:H$1010) + (B4='Scrum Teams'!I$2:I$1010) + (B4='Scrum Teams'!J$2:J$1010) + (B4='Scrum Teams'!K$2:K$1010) + (B4='Scrum Teams'!L$2:L$1010) + (B4='Scrum Teams'!M$2:M$1010) + (B4='Scrum Teams'!N$2:N$1010) + (B4='Scrum Teams'!O$2:O$1010) + (B4='Scrum Teams'!P$2:P$1010) + (B4='Scrum Teams'!Q$2:Q$1010), 0) ), "Not found" )} -> Gambit | P4: CRM | Q4: Srividya Mandalapu
A5: CRM | B5: CRM-Mobile | C5: Mani T | E5: Arun Gangadhar | G5: Ved Singh | H5: Shivam Arora | I5: Subhash Mohan | K5: Rashmi Prakash | L5: Gaurav Gupta | M5: Satyavrat Mudgil | N5: Komala | O5: {=IFERROR( INDEX('Scrum Teams'!B$2:B$1010, MATCH(1, (B5='Scrum Teams'!F$2:F$1010) + (B5='Scrum Teams'!G$2:G$1010) + (B5='Scrum Teams'!H$2:H$1010) + (B5='Scrum Teams'!I$2:I$1010) + (B5='Scrum Teams'!J$2:J$1010) + (B5='Scrum Teams'!K$2:K$1010) + (B5='Scrum Teams'!L$2:L$1010) + (B5='Scrum Teams'!M$2:M$1010) + (B5='Scrum Teams'!N$2:N$1010) + (B5='Scrum Teams'!O$2:O$1010) + (B5='Scrum Teams'!P$2:P$1010) + (B5='Scrum Teams'!Q$2:Q$1010), 0) ), "Not found" )} -> Mystique | P5: CRM | Q5: Srividya Mandalapu
A6: CRM | B6: CRM-Task | C6: Jyothi Vejju | E6: Arun Gangadhar | G6: Ved Singh | H6: Jitendra Rahangdale | I6: Subhash Mohan | K6: Rashmi Prakash | L6: Gaurav Gupta | M6: Satyavrat Mudgil | N6: Komala | O6: {=IFERROR( INDEX('Scrum Teams'!B$2:B$1010, MATCH(1, (B6='Scrum Teams'!F$2:F$1010) + (B6='Scrum Teams'!G$2:G$1010) + (B6='Scrum Teams'!H$2:H$1010) + (B6='Scrum Teams'!I$2:I$1010) + (B6='Scrum Teams'!J$2:J$1010) + (B6='Scrum Teams'!K$2:K$1010) + (B6='Scrum Teams'!L$2:L$1010) + (B6='Scrum Teams'!M$2:M$1010) + (B6='Scrum Teams'!N$2:N$1010) + (B6='Scrum Teams'!O$2:O$1010) + (B6='Scrum Teams'!P$2:P$1010) + (B6='Scrum Teams'!Q$2:Q$1010), 0) ), "Not found" )} -> Storm | P6: CRM | Q6: Srividya Mandalapu
A7: CRM | B7: CRM-Appointment | C7: Jyothi Vejju | E7: Arun Gangadhar | G7: Ved Singh | H7: Jitendra Rahangdale | I7: Subhash Mohan | K7: Rashmi Prakash | L7: Gaurav Gupta | M7: Satyavrat Mudgil | N7: Komala | O7: {=IFERROR( INDEX('Scrum Teams'!B$2:B$1010, MATCH(1, (B7='Scrum Teams'!F$2:F$1010) + (B7='Scrum Teams'!G$2:G$1010) + (B7='Scrum Teams'!H$2:H$1010) + (B7='Scrum Teams'!I$2:I$1010) + (B7='Scrum Teams'!J$2:J$1010) + (B7='Scrum Teams'!K$2:K$1010) + (B7='Scrum Teams'!L$2:L$1010) + (B7='Scrum Teams'!M$2:M$1010) + (B7='Scrum Teams'!N$2:N$1010) + (B7='Scrum Teams'!O$2:O$1010) + (B7='Scrum Teams'!P$2:P$1010) + (B7='Scrum Teams'!Q$2:Q$1010), 0) ), "Not found" )} -> Storm | P7: CRM | Q7: Srividya Mandalapu
A8: CRM | B8: CRM-Reports | C8: Nawaz Baba | E8: Arun Gangadhar | G8: Ved Singh | H8: Jitendra Rahangdale | I8: Subhash Mohan | K8: Rashmi Prakash | L8: Gaurav Gupta | M8: Satyavrat Mudgil | N8: Komala | O8: {=IFERROR( INDEX('Scrum Teams'!B$2:B$1010, MATCH(1, (B8='Scrum Teams'!F$2:F$1010) + (B8='Scrum Teams'!G$2:G$1010) + (B8='Scrum Teams'!H$2:H$1010) + (B8='Scrum Teams'!I$2:I$1010) + (B8='Scrum Teams'!J$2:J$1010) + (B8='Scrum Teams'!K$2:K$1010) + (B8='Scrum Teams'!L$2:L$1010) + (B8='Scrum Teams'!M$2:M$1010) + (B8='Scrum Teams'!N$2:N$1010) + (B8='Scrum Teams'!O$2:O$1010) + (B8='Scrum Teams'!P$2:P$1010) + (B8='Scrum Teams'!Q$2:Q$1010), 0) ), "Not found" )} -> Bishop | P8: CRM | Q8: Srividya Mandalapu
A9: CRM | B9: CRM-Dashboards | C9: Nawaz Baba | E9: Arun Gangadhar | G9: Ved Singh | H9: Jitendra Rahangdale | I9: Subhash Mohan | K9: Rashmi Prakash | L9: Gaurav Gupta | M9: Satyavrat Mudgil | N9: Komala | O9: {=IFERROR( INDEX('Scrum Teams'!B$2:B$1010, MATCH(1, (B9='Scrum Teams'!F$2:F$1010) + (B9='Scrum Teams'!G$2:G$1010) + (B9='Scrum Teams'!H$2:H$1010) + (B9='Scrum Teams'!I$2:I$1010) + (B9='Scrum Teams'!J$2:J$1010) + (B9='Scrum Teams'!K$2:K$1010) + (B9='Scrum Teams'!L$2:L$1010) + (B9='Scrum Teams'!M$2:M$1010) + (B9='Scrum Teams'!N$2:N$1010) + (B9='Scrum Teams'!O$2:O$1010) + (B9='Scrum Teams'!P$2:P$1010) + (B9='Scrum Teams'!Q$2:Q$1010), 0) ), "Not found" )} -> Bishop | P9: CRM | Q9: Srividya Mandalapu
A10: CRM | B10: CRM-AI | C10: Mani T | E10: Arun Gangadhar | G10: Ved Singh | H10: Shivam Arora | I10: Subhash Mohan | K10: Rashmi Prakash | L10: Gaurav Gupta | M10: Satyavrat Mudgil | N10: Komala | O10: {=IFERROR( INDEX('Scrum Teams'!B$2:B$1010, MATCH(1, (B10='Scrum Teams'!F$2:F$1010) + (B10='Scrum Teams'!G$2:G$1010) + (B10='Scrum Teams'!H$2:H$1010) + (B10='Scrum Teams'!I$2:I$1010) + (B10='Scrum Teams'!J$2:J$1010) + (B10='Scrum Teams'!K$2:K$1010) + (B10='Scrum Teams'!L$2:L$1010) + (B10='Scrum Teams'!M$2:M$1010) + (B10='Scrum Teams'!N$2:N$1010) + (B10='Scrum Teams'!O$2:O$1010) + (B10='Scrum Teams'!P$2:P$1010) + (B10='Scrum Teams'!Q$2:Q$1010), 0) ), "Not found" )} -> Mystique | P10: CRM | Q10: Srividya Mandalapu
A11: CRM | B11: CRM-Retail_Mobile | C11: Mani T | E11: Arun Gangadhar | G11: Ved Singh | H11: Palash Sanjay Kotgirwar | I11: Hardik Paharia | J11: Hardik Paharia | K11: Gaurav Gupta | L11: Gaurav Gupta | M11: Satyavrat Mudgil | N11: Komala | O11: {=IFERROR( INDEX('Scrum Teams'!B$2:B$1010, MATCH(1, (B11='Scrum Teams'!F$2:F$1010) + (B11='Scrum Teams'!G$2:G$1010) + (B11='Scrum Teams'!H$2:H$1010) + (B11='Scrum Teams'!I$2:I$1010) + (B11='Scrum Teams'!J$2:J$1010) + (B11='Scrum Teams'!K$2:K$1010) + (B11='Scrum Teams'!L$2:L$1010) + (B11='Scrum Teams'!M$2:M$1010) + (B11='Scrum Teams'!N$2:N$1010) + (B11='Scrum Teams'!O$2:O$1010) + (B11='Scrum Teams'!P$2:P$1010) + (B11='Scrum Teams'!Q$2:Q$1010), 0) ), "Not found" )} -> Mystique | P11: CRM | Q11: Srividya Mandalapu
A12: CRM | B12: CRM-Sales_AI | C12: Mani T | E12: Arun Gangadhar | G12: Ved Singh | H12: Preetiranjan Pradhan | K12: Rashmi Prakash | L12: Gaurav Gupta | M12: Satyavrat Mudgil | N12: Komala | O12: {=IFERROR( INDEX('Scrum Teams'!B$2:B$1010, MATCH(1, (B12='Scrum Teams'!F$2:F$1010) + (B12='Scrum Teams'!G$2:G$1010) + (B12='Scrum Teams'!H$2:H$1010) + (B12='Scrum Teams'!I$2:I$1010) + (B12='Scrum Teams'!J$2:J$1010) + (B12='Scrum Teams'!K$2:K$1010) + (B12='Scrum Teams'!L$2:L$1010) + (B12='Scrum Teams'!M$2:M$1010) + (B12='Scrum Teams'!N$2:N$1010) + (B12='Scrum Teams'!O$2:O$1010) + (B12='Scrum Teams'!P$2:P$1010) + (B12='Scrum Teams'!Q$2:Q$1010), 0) ), "Not found" )} -> Mystique | P12: CRM | Q12: Srividya Mandalapu
A13: CRM | B13: CRM-Pro | C13: Mani T | E13: Arun Gangadhar | G13: Ved Singh | H13: Preetiranjan Pradhan | K13: Rashmi Prakash | L13: Gaurav Gupta | M13: Satyavrat Mudgil | N13: Komala | O13: {=IFERROR( INDEX('Scrum Teams'!B$2:B$1010, MATCH(1, (B13='Scrum Teams'!F$2:F$1010) + (B13='Scrum Teams'!G$2:G$1010) + (B13='Scrum Teams'!H$2:H$1010) + (B13='Scrum Teams'!I$2:I$1010) + (B13='Scrum Teams'!J$2:J$1010) + (B13='Scrum Teams'!K$2:K$1010) + (B13='Scrum Teams'!L$2:L$1010) + (B13='Scrum Teams'!M$2:M$1010) + (B13='Scrum Teams'!N$2:N$1010) + (B13='Scrum Teams'!O$2:O$1010) + (B13='Scrum Teams'!P$2:P$1010) + (B13='Scrum Teams'!Q$2:Q$1010), 0) ), "Not found" )} -> Mystique | P13: CRM | Q13: Srividya Mandalapu
A14: CRM | B14: CRM-Compliance | C14: Jyothi Vejju | E14: Arun Gangadhar | G14: Ved Singh | H14: Piyush Kumar | I14: Avin Jain | K14: Ashish Kalya | M14: Shiva Somasundaram | N14: Komala | O14: {=IFERROR( INDEX('Scrum Teams'!B$2:B$1010, MATCH(1, (B14='Scrum Teams'!F$2:F$1010) + (B14='Scrum Teams'!G$2:G$1010) + (B14='Scrum Teams'!H$2:H$1010) + (B14='Scrum Teams'!I$2:I$1010) + (B14='Scrum Teams'!J$2:J$1010) + (B14='Scrum Teams'!K$2:K$1010) + (B14='Scrum Teams'!L$2:L$1010) + (B14='Scrum Teams'!M$2:M$1010) + (B14='Scrum Teams'!N$2:N$1010) + (B14='Scrum Teams'!O$2:O$1010) + (B14='Scrum Teams'!P$2:P$1010) + (B14='Scrum Teams'!Q$2:Q$1010), 0) ), "Not found" )} -> Storm | P14: CRM | Q14: Srividya Mandalapu | R14: CRM-Communication_Preferences
A15: CRM | B15: CRM-CDM | C15: Siddharth Gaur | E15: Arun Gangadhar | G15: Ved Singh | P15: CRM | Q15: Srividya Mandalapu
A16: CRM | B16: CRM-CMS | C16: Siddharth Gaur | E16: Arun Gangadhar | G16: Ved Singh | P16: CRM | Q16: Srividya Mandalapu
A17: Campaign | B17: Campaign-Core | C17: Nawaz Baba | E17: Arun Gangadhar | G17: Ved Singh | H17: Uday Jumle | K17: Rashmi Prakash | L17: Gaurav Gupta | M17: Satyavrat Mudgil | N17: Komala | O17: {=IFERROR( INDEX('Scrum Teams'!B$2:B$1010, MATCH(1, (B17='Scrum Teams'!F$2:F$1010) + (B17='Scrum Teams'!G$2:G$1010) + (B17='Scrum Teams'!H$2:H$1010) + (B17='Scrum Teams'!I$2:I$1010) + (B17='Scrum Teams'!J$2:J$1010) + (B17='Scrum Teams'!K$2:K$1010) + (B17='Scrum Teams'!L$2:L$1010) + (B17='Scrum Teams'!M$2:M$1010) + (B17='Scrum Teams'!N$2:N$1010) + (B17='Scrum Teams'!O$2:O$1010) + (B17='Scrum Teams'!P$2:P$1010) + (B17='Scrum Teams'!Q$2:Q$1010), 0) ), "Not found" )} -> Bishop | P17: CRM | Q17: Srividya Mandalapu
A18: Communication | B18: Communication-Calling | C18: Vikash kumar | E18: Ketan Dikshit | G18: Ved Singh | H18: Jutla Manaswini | I18: Avin Jain | K18: Ashish Kalya | M18: Shiva Somasundaram | O18: {=IFERROR( INDEX('Scrum Teams'!B$2:B$1010, MATCH(1, (B18='Scrum Teams'!F$2:F$1010) + (B18='Scrum Teams'!G$2:G$1010) + (B18='Scrum Teams'!H$2:H$1010) + (B18='Scrum Teams'!I$2:I$1010) + (B18='Scrum Teams'!J$2:J$1010) + (B18='Scrum Teams'!K$2:K$1010) + (B18='Scrum Teams'!L$2:L$1010) + (B18='Scrum Teams'!M$2:M$1010) + (B18='Scrum Teams'!N$2:N$1010) + (B18='Scrum Teams'!O$2:O$1010) + (B18='Scrum Teams'!P$2:P$1010) + (B18='Scrum Teams'!Q$2:Q$1010), 0) ), "Not found" )} -> Not found | P18: COMM | Q18: Srividya Mandalapu | R18: CRM-Communication
A19: Communication | B19: Communication-Texting | E19: Ketan Dikshit | G19: Ved Singh | H19: Piyush Kumar | I19: Avin Jain | K19: Ashish Kalya | M19: Shiva Somasundaram | O19: {=IFERROR( INDEX('Scrum Teams'!B$2:B$1010, MATCH(1, (B19='Scrum Teams'!F$2:F$1010) + (B19='Scrum Teams'!G$2:G$1010) + (B19='Scrum Teams'!H$2:H$1010) + (B19='Scrum Teams'!I$2:I$1010) + (B19='Scrum Teams'!J$2:J$1010) + (B19='Scrum Teams'!K$2:K$1010) + (B19='Scrum Teams'!L$2:L$1010) + (B19='Scrum Teams'!M$2:M$1010) + (B19='Scrum Teams'!N$2:N$1010) + (B19='Scrum Teams'!O$2:O$1010) + (B19='Scrum Teams'!P$2:P$1010) + (B19='Scrum Teams'!Q$2:Q$1010), 0) ), "Not found" )} -> Not found | P19: COMM | Q19: Srividya Mandalapu
A20: Communication | B20: Communication-Email | E20: Ketan Dikshit | G20: Ved Singh | H20: Abhinav Wagadre | K20: Ashish Kalya | M20: Shiva Somasundaram | O20: {=IFERROR( INDEX('Scrum Teams'!B$2:B$1010, MATCH(1, (B20='Scrum Teams'!F$2:F$1010) + (B20='Scrum Teams'!G$2:G$1010) + (B20='Scrum Teams'!H$2:H$1010) + (B20='Scrum Teams'!I$2:I$1010) + (B20='Scrum Teams'!J$2:J$1010) + (B20='Scrum Teams'!K$2:K$1010) + (B20='Scrum Teams'!L$2:L$1010) + (B20='Scrum Teams'!M$2:M$1010) + (B20='Scrum Teams'!N$2:N$1010) + (B20='Scrum Teams'!O$2:O$1010) + (B20='Scrum Teams'!P$2:P$1010) + (B20='Scrum Teams'!Q$2:Q$1010), 0) ), "Not found" )} -> Not found | P20: COMM | Q20: Srividya Mandalapu
A21: Communication | B21: Communication-Live_Chat | E21: Ketan Dikshit | G21: Ved Singh | H21: Abhinav Wagadre | K21: Ashish Kalya | M21: Shiva Somasundaram | O21: {=IFERROR( INDEX('Scrum Teams'!B$2:B$1010, MATCH(1, (B21='Scrum Teams'!F$2:F$1010) + (B21='Scrum Teams'!G$2:G$1010) + (B21='Scrum Teams'!H$2:H$1010) + (B21='Scrum Teams'!I$2:I$1010) + (B21='Scrum Teams'!J$2:J$1010) + (B21='Scrum Teams'!K$2:K$1010) + (B21='Scrum Teams'!L$2:L$1010) + (B21='Scrum Teams'!M$2:M$1010) + (B21='Scrum Teams'!N$2:N$1010) + (B21='Scrum Teams'!O$2:O$1010) + (B21='Scrum Teams'!P$2:P$1010) + (B21='Scrum Teams'!Q$2:Q$1010), 0) ), "Not found" )} -> Not found | P21: COMM | Q21: Srividya Mandalapu
A22: Communication | B22: Communication-Unified_Platform | C22: Vikash kumar | E22: Ketan Dikshit | G22: Ved Singh | H22: Jutla Manaswini | I22: Avin Jain | K22: Ashish Kalya | M22: Shiva Somasundaram | O22: {=IFERROR( INDEX('Scrum Teams'!B$2:B$1010, MATCH(1, (B22='Scrum Teams'!F$2:F$1010) + (B22='Scrum Teams'!G$2:G$1010) + (B22='Scrum Teams'!H$2:H$1010) + (B22='Scrum Teams'!I$2:I$1010) + (B22='Scrum Teams'!J$2:J$1010) + (B22='Scrum Teams'!K$2:K$1010) + (B22='Scrum Teams'!L$2:L$1010) + (B22='Scrum Teams'!M$2:M$1010) + (B22='Scrum Teams'!N$2:N$1010) + (B22='Scrum Teams'!O$2:O$1010) + (B22='Scrum Teams'!P$2:P$1010) + (B22='Scrum Teams'!Q$2:Q$1010), 0) ), "Not found" )} -> Not found | P22: COMM | Q22: Srividya Mandalapu | R22: Communication-Platform
A23: ApplicationPlatforms | B23: AP-Compliance | C23: Venkatesh naik | E23: Vaibhav Saini | F23: Surya Narayanan | G23: Keith Wiseman | H23: Lohit Reddy | I23: Vamsee Krishna Mullapudi | J23: Vamsee Krishna Mullapudi | K23: Vijayakumar B | M23: Shiva Somasundaram | N23: Shashi Kumar | O23: {=IFERROR( INDEX('Scrum Teams'!B$2:B$1010, MATCH(1, (B23='Scrum Teams'!F$2:F$1010) + (B23='Scrum Teams'!G$2:G$1010) + (B23='Scrum Teams'!H$2:H$1010) + (B23='Scrum Teams'!I$2:I$1010) + (B23='Scrum Teams'!J$2:J$1010) + (B23='Scrum Teams'!K$2:K$1010) + (B23='Scrum Teams'!L$2:L$1010) + (B23='Scrum Teams'!M$2:M$1010) + (B23='Scrum Teams'!N$2:N$1010) + (B23='Scrum Teams'!O$2:O$1010) + (B23='Scrum Teams'!P$2:P$1010) + (B23='Scrum Teams'!Q$2:Q$1010), 0) ), "Not found" )} -> Compliance | P23: APLT | Q23: Rahul Rathore | R23: Core-Compliance
A24: ApplicationPlatforms | B24: AP-Printers_ Scanners | C24: Priyansu Singh | E24: Vaibhav Saini | F24: Surya Narayanan | G24: Keith Wiseman | H24: Lohit Reddy | I24: Vamsee Krishna Mullapudi | J24: Vamsee Krishna Mullapudi | K24: Vijayakumar B | M24: Shiva Somasundaram | N24: Shashi Kumar | O24: {=IFERROR( INDEX('Scrum Teams'!B$2:B$1010, MATCH(1, (B24='Scrum Teams'!F$2:F$1010) + (B24='Scrum Teams'!G$2:G$1010) + (B24='Scrum Teams'!H$2:H$1010) + (B24='Scrum Teams'!I$2:I$1010) + (B24='Scrum Teams'!J$2:J$1010) + (B24='Scrum Teams'!K$2:K$1010) + (B24='Scrum Teams'!L$2:L$1010) + (B24='Scrum Teams'!M$2:M$1010) + (B24='Scrum Teams'!N$2:N$1010) + (B24='Scrum Teams'!O$2:O$1010) + (B24='Scrum Teams'!P$2:P$1010) + (B24='Scrum Teams'!Q$2:Q$1010), 0) ), "Not found" )} -> Not found | P24: APLT | Q24: Rahul Rathore | R24: Core-PrinterScanner
A25: ApplicationPlatforms | B25: AP-Enterprise | C25: Aditya Pandey | E25: Vaibhav Saini | F25: Surya Narayanan | G25: Keith Wiseman | H25: Sudeep Kapadia | K25: Vijayakumar B | M25: Shiva Somasundaram | N25: Shashi Kumar | O25: {=IFERROR( INDEX('Scrum Teams'!B$2:B$1010, MATCH(1, (B25='Scrum Teams'!F$2:F$1010) + (B25='Scrum Teams'!G$2:G$1010) + (B25='Scrum Teams'!H$2:H$1010) + (B25='Scrum Teams'!I$2:I$1010) + (B25='Scrum Teams'!J$2:J$1010) + (B25='Scrum Teams'!K$2:K$1010) + (B25='Scrum Teams'!L$2:L$1010) + (B25='Scrum Teams'!M$2:M$1010) + (B25='Scrum Teams'!N$2:N$1010) + (B25='Scrum Teams'!O$2:O$1010) + (B25='Scrum Teams'!P$2:P$1010) + (B25='Scrum Teams'!Q$2:Q$1010), 0) ), "Not found" )} -> Enterprise | P25: APLT | Q25: Rahul Rathore | R25: Core-Foundation
A26: ApplicationPlatforms | B26: AP-Config_Studio | C26: Priyansu Singh | E26: Vaibhav Saini | F26: Surya Narayanan | G26: Keith Wiseman | H26: Anshika Chaturvedi | I26: Vamsee Krishna Mullapudi | J26: Vamsee Krishna Mullapudi | K26: Vijayakumar B | M26: Shiva Somasundaram | N26: Shashi Kumar | O26: {=IFERROR( INDEX('Scrum Teams'!B$2:B$1010, MATCH(1, (B26='Scrum Teams'!F$2:F$1010) + (B26='Scrum Teams'!G$2:G$1010) + (B26='Scrum Teams'!H$2:H$1010) + (B26='Scrum Teams'!I$2:I$1010) + (B26='Scrum Teams'!J$2:J$1010) + (B26='Scrum Teams'!K$2:K$1010) + (B26='Scrum Teams'!L$2:L$1010) + (B26='Scrum Teams'!M$2:M$1010) + (B26='Scrum Teams'!N$2:N$1010) + (B26='Scrum Teams'!O$2:O$1010) + (B26='Scrum Teams'!P$2:P$1010) + (B26='Scrum Teams'!Q$2:Q$1010), 0) ), "Not found" )} -> Configuration Studio | P26: APLT | Q26: Rahul Rathore | R26: Core-DealerConfigurations
A27: ApplicationPlatforms | B27: AP-Workflow_Engine | C27: Priyansu Singh | E27: Vaibhav Saini | F27: Surya Narayanan | G27: Keith Wiseman | H27: Jaideep Gangwar | I27: Subhash Mohan | K27: Rashmi Prakash | L27: Gaurav Gupta | M27: Satyavrat Mudgil | N27: Shashi Kumar | O27: {=IFERROR( INDEX('Scrum Teams'!B$2:B$1010, MATCH(1, (B27='Scrum Teams'!F$2:F$1010) + (B27='Scrum Teams'!G$2:G$1010) + (B27='Scrum Teams'!H$2:H$1010) + (B27='Scrum Teams'!I$2:I$1010) + (B27='Scrum Teams'!J$2:J$1010) + (B27='Scrum Teams'!K$2:K$1010) + (B27='Scrum Teams'!L$2:L$1010) + (B27='Scrum Teams'!M$2:M$1010) + (B27='Scrum Teams'!N$2:N$1010) + (B27='Scrum Teams'!O$2:O$1010) + (B27='Scrum Teams'!P$2:P$1010) + (B27='Scrum Teams'!Q$2:Q$1010), 0) ), "Not found" )} -> Workflow Engine | P27: APLT | Q27: Rahul Rathore | R27: Core-RuleEngine
A28: ApplicationPlatforms | B28: AP-Identity_Mgt | C28: Venkatesh naik | E28: Vaibhav Saini | F28: Surya Narayanan | G28: Keith Wiseman | H28: Jayashri Soundararajan | I28: Vamsee Krishna Mullapudi | J28: Vamsee Krishna Mullapudi | K28: Vijayakumar B | M28: Shiva Somasundaram | N28: Shashi Kumar | O28: {=IFERROR( INDEX('Scrum Teams'!B$2:B$1010, MATCH(1, (B28='Scrum Teams'!F$2:F$1010) + (B28='Scrum Teams'!G$2:G$1010) + (B28='Scrum Teams'!H$2:H$1010) + (B28='Scrum Teams'!I$2:I$1010) + (B28='Scrum Teams'!J$2:J$1010) + (B28='Scrum Teams'!K$2:K$1010) + (B28='Scrum Teams'!L$2:L$1010) + (B28='Scrum Teams'!M$2:M$1010) + (B28='Scrum Teams'!N$2:N$1010) + (B28='Scrum Teams'!O$2:O$1010) + (B28='Scrum Teams'!P$2:P$1010) + (B28='Scrum Teams'!Q$2:Q$1010), 0) ), "Not found" )} -> Identity Management | P28: APLT | Q28: Rahul Rathore | R28: Core-IdentityManagement
A29: ApplicationPlatforms | B29: AP-Audit_Approval | C29: Aditya Pandey | E29: Vaibhav Saini | F29: Surya Narayanan | G29: Keith Wiseman | H29: Sudeep Kapadia | K29: Vijayakumar B | M29: Shiva Somasundaram | N29: Shashi Kumar | O29: {=IFERROR( INDEX('Scrum Teams'!B$2:B$1010, MATCH(1, (B29='Scrum Teams'!F$2:F$1010) + (B29='Scrum Teams'!G$2:G$1010) + (B29='Scrum Teams'!H$2:H$1010) + (B29='Scrum Teams'!I$2:I$1010) + (B29='Scrum Teams'!J$2:J$1010) + (B29='Scrum Teams'!K$2:K$1010) + (B29='Scrum Teams'!L$2:L$1010) + (B29='Scrum Teams'!M$2:M$1010) + (B29='Scrum Teams'!N$2:N$1010) + (B29='Scrum Teams'!O$2:O$1010) + (B29='Scrum Teams'!P$2:P$1010) + (B29='Scrum Teams'!Q$2:Q$1010), 0) ), "Not found" )} -> Audit & Approval | P29: APLT | Q29: Rahul Rathore
A30: ZEBRA | B30: ZEBRA-Bootstrapping | C30: Shivam Goyal | E30: Bobby Alexander | F30: Surya Narayanan | G30: Keith Wiseman | H30: No PM Coverage | I30: No PM Coverage | J30: No PM Coverage | K30: No PM Coverage | L30: No PM Coverage | M30: Shiva Somasundaram | O30: {=IFERROR( INDEX('Scrum Teams'!B$2:B$1010, MATCH(1, (B30='Scrum Teams'!F$2:F$1010) + (B30='Scrum Teams'!G$2:G$1010) + (B30='Scrum Teams'!H$2:H$1010) + (B30='Scrum Teams'!I$2:I$1010) + (B30='Scrum Teams'!J$2:J$1010) + (B30='Scrum Teams'!K$2:K$1010) + (B30='Scrum Teams'!L$2:L$1010) + (B30='Scrum Teams'!M$2:M$1010) + (B30='Scrum Teams'!N$2:N$1010) + (B30='Scrum Teams'!O$2:O$1010) + (B30='Scrum Teams'!P$2:P$1010) + (B30='Scrum Teams'!Q$2:Q$1010), 0) ), "Not found" )} -> Zebra | P30: ZEB | Q30: Rahul Rathore
A31: ZEBRA | B31: ZEBRA-GoLiveSupport | C31: Shivam Goyal | E31: Bobby Alexander | F31: Surya Narayanan | G31: Keith Wiseman | H31: No PM Coverage | I31: No PM Coverage | J31: No PM Coverage | K31: No PM Coverage | L31: No PM Coverage | M31: Shiva Somasundaram | O31: {=IFERROR( INDEX('Scrum Teams'!B$2:B$1010, MATCH(1, (B31='Scrum Teams'!F$2:F$1010) + (B31='Scrum Teams'!G$2:G$1010) + (B31='Scrum Teams'!H$2:H$1010) + (B31='Scrum Teams'!I$2:I$1010) + (B31='Scrum Teams'!J$2:J$1010) + (B31='Scrum Teams'!K$2:K$1010) + (B31='Scrum Teams'!L$2:L$1010) + (B31='Scrum Teams'!M$2:M$1010) + (B31='Scrum Teams'!N$2:N$1010) + (B31='Scrum Teams'!O$2:O$1010) + (B31='Scrum Teams'!P$2:P$1010) + (B31='Scrum Teams'!Q$2:Q$1010), 0) ), "Not found" )} -> Zebra | P31: ZEB | Q31: Rahul Rathore
A32: ZEBRA | B32: ZEBRA-InternalTools | C32: Shivam Goyal | E32: Bobby Alexander | F32: Surya Narayanan | G32: Keith Wiseman | H32: No PM Coverage | I32: No PM Coverage | J32: No PM Coverage | K32: No PM Coverage | L32: No PM Coverage | M32: Shiva Somasundaram | O32: {=IFERROR( INDEX('Scrum Teams'!B$2:B$1010, MATCH(1, (B32='Scrum Teams'!F$2:F$1010) + (B32='Scrum Teams'!G$2:G$1010) + (B32='Scrum Teams'!H$2:H$1010) + (B32='Scrum Teams'!I$2:I$1010) + (B32='Scrum Teams'!J$2:J$1010) + (B32='Scrum Teams'!K$2:K$1010) + (B32='Scrum Teams'!L$2:L$1010) + (B32='Scrum Teams'!M$2:M$1010) + (B32='Scrum Teams'!N$2:N$1010) + (B32='Scrum Teams'!O$2:O$1010) + (B32='Scrum Teams'!P$2:P$1010) + (B32='Scrum Teams'!Q$2:Q$1010), 0) ), "Not found" )} -> Not found | P32: ZEB | Q32: Rahul Rathore | R32: Core-InternalTools
A33: ARCIntegration | B33: ARCIntegration-Accounting | C33: Raghavendra Pai | E33: Prakash Mohan | F33: Prakash Mohan | G33: Turker Coskun | H33: Bismah Kiani | I33: Hanuth Singh | J33: Hanuth Singh | M33: Satyavrat Mudgil | N33: Abhinandan Srinivas | O33: {=IFERROR( INDEX('Scrum Teams'!B$2:B$1010, MATCH(1, (B33='Scrum Teams'!F$2:F$1010) + (B33='Scrum Teams'!G$2:G$1010) + (B33='Scrum Teams'!H$2:H$1010) + (B33='Scrum Teams'!I$2:I$1010) + (B33='Scrum Teams'!J$2:J$1010) + (B33='Scrum Teams'!K$2:K$1010) + (B33='Scrum Teams'!L$2:L$1010) + (B33='Scrum Teams'!M$2:M$1010) + (B33='Scrum Teams'!N$2:N$1010) + (B33='Scrum Teams'!O$2:O$1010) + (B33='Scrum Teams'!P$2:P$1010) + (B33='Scrum Teams'!Q$2:Q$1010), 0) ), "Not found" )} -> Credit & FNI Integrations | P33: INTG | Q33: Nishanth Nag
A34: ARCIntegration | B34: ARCIntegration-Core | C34: Raghavendra Pai | E34: Prakash Mohan | F34: Prakash Mohan | G34: Turker Coskun | H34: No PM Coverage | K34: Tom Jude Ammanthurutil | M34: Turker Coskun | N34: Abhinandan Srinivas | O34: {=IFERROR( INDEX('Scrum Teams'!B$2:B$1010, MATCH(1, (B34='Scrum Teams'!F$2:F$1010) + (B34='Scrum Teams'!G$2:G$1010) + (B34='Scrum Teams'!H$2:H$1010) + (B34='Scrum Teams'!I$2:I$1010) + (B34='Scrum Teams'!J$2:J$1010) + (B34='Scrum Teams'!K$2:K$1010) + (B34='Scrum Teams'!L$2:L$1010) + (B34='Scrum Teams'!M$2:M$1010) + (B34='Scrum Teams'!N$2:N$1010) + (B34='Scrum Teams'!O$2:O$1010) + (B34='Scrum Teams'!P$2:P$1010) + (B34='Scrum Teams'!Q$2:Q$1010), 0) ), "Not found" )} -> Credit & FNI Integrations | P34: INTG | Q34: Nishanth Nag
A35: ARCIntegration | B35: ARCIntegration-CreditApp&eContracting | C35: Raghavendra Pai | E35: Prakash Mohan | F35: Prakash Mohan | G35: Turker Coskun | H35: Mudra Surana | I35: Saurabh Birla | J35: Saurabh Birla | K35: Irfan Presswala | L35: Irfan Presswala | M35: Satyavrat Mudgil | N35: Abhinandan Srinivas | O35: {=IFERROR( INDEX('Scrum Teams'!B$2:B$1010, MATCH(1, (B35='Scrum Teams'!F$2:F$1010) + (B35='Scrum Teams'!G$2:G$1010) + (B35='Scrum Teams'!H$2:H$1010) + (B35='Scrum Teams'!I$2:I$1010) + (B35='Scrum Teams'!J$2:J$1010) + (B35='Scrum Teams'!K$2:K$1010) + (B35='Scrum Teams'!L$2:L$1010) + (B35='Scrum Teams'!M$2:M$1010) + (B35='Scrum Teams'!N$2:N$1010) + (B35='Scrum Teams'!O$2:O$1010) + (B35='Scrum Teams'!P$2:P$1010) + (B35='Scrum Teams'!Q$2:Q$1010), 0) ), "Not found" )} -> Credit & FNI Integrations | P35: INTG | Q35: Nishanth Nag
A36: ARCIntegration | B36: ARCIntegration-CRM | C36: Raghavendra Pai | E36: Prakash Mohan | F36: Prakash Mohan | G36: Turker Coskun | H36: Siddharth Bountra | K36: Tom Jude Ammanthurutil | M36: Turker Coskun | N36: Abhinandan Srinivas | O36: {=IFERROR( INDEX('Scrum Teams'!B$2:B$1010, MATCH(1, (B36='Scrum Teams'!F$2:F$1010) + (B36='Scrum Teams'!G$2:G$1010) + (B36='Scrum Teams'!H$2:H$1010) + (B36='Scrum Teams'!I$2:I$1010) + (B36='Scrum Teams'!J$2:J$1010) + (B36='Scrum Teams'!K$2:K$1010) + (B36='Scrum Teams'!L$2:L$1010) + (B36='Scrum Teams'!M$2:M$1010) + (B36='Scrum Teams'!N$2:N$1010) + (B36='Scrum Teams'!O$2:O$1010) + (B36='Scrum Teams'!P$2:P$1010) + (B36='Scrum Teams'!Q$2:Q$1010), 0) ), "Not found" )} -> Retail Integration 2 | P36: INTG | Q36: Nishanth Nag
A37: ARCIntegration | B37: ARCIntegration-DRS | C37: Raghavendra Pai | E37: Prakash Mohan | F37: Prakash Mohan | G37: Turker Coskun | H37: Ankush Kedia | K37: Suraj Jain | L37: Gaurav Gupta | M37: Satyavrat Mudgil | N37: Abhinandan Srinivas | O37: {=IFERROR( INDEX('Scrum Teams'!B$2:B$1010, MATCH(1, (B37='Scrum Teams'!F$2:F$1010) + (B37='Scrum Teams'!G$2:G$1010) + (B37='Scrum Teams'!H$2:H$1010) + (B37='Scrum Teams'!I$2:I$1010) + (B37='Scrum Teams'!J$2:J$1010) + (B37='Scrum Teams'!K$2:K$1010) + (B37='Scrum Teams'!L$2:L$1010) + (B37='Scrum Teams'!M$2:M$1010) + (B37='Scrum Teams'!N$2:N$1010) + (B37='Scrum Teams'!O$2:O$1010) + (B37='Scrum Teams'!P$2:P$1010) + (B37='Scrum Teams'!Q$2:Q$1010), 0) ), "Not found" )} -> Retail Integration 2 | P37: INTG | Q37: Nishanth Nag
A38: ARCIntegration | B38: ARCIntegration-F&I | C38: Raghavendra Pai | E38: Prakash Mohan | F38: Prakash Mohan | G38: Turker Coskun | H38: Prakhar Gaur | I38: Saurabh Birla | J38: Saurabh Birla | K38: Irfan Presswala | L38: Irfan Presswala | M38: Satyavrat Mudgil | N38: Abhinandan Srinivas | O38: {=IFERROR( INDEX('Scrum Teams'!B$2:B$1010, MATCH(1, (B38='Scrum Teams'!F$2:F$1010) + (B38='Scrum Teams'!G$2:G$1010) + (B38='Scrum Teams'!H$2:H$1010) + (B38='Scrum Teams'!I$2:I$1010) + (B38='Scrum Teams'!J$2:J$1010) + (B38='Scrum Teams'!K$2:K$1010) + (B38='Scrum Teams'!L$2:L$1010) + (B38='Scrum Teams'!M$2:M$1010) + (B38='Scrum Teams'!N$2:N$1010) + (B38='Scrum Teams'!O$2:O$1010) + (B38='Scrum Teams'!P$2:P$1010) + (B38='Scrum Teams'!Q$2:Q$1010), 0) ), "Not found" )} -> Credit & FNI Integrations | P38: INTG | Q38: Nishanth Nag
A39: ARCIntegration | B39: ARCIntegration-Parts | C39: D M Raj Karthick | D39: D M Raj Karthick | E39: Prakash Mohan | F39: Prakash Mohan | G39: Turker Coskun | H39: Uday Wadhera | I39: Arjun Rajeev | K39: Tom Jude Ammanthurutil | M39: Turker Coskun | N39: Abhinandan Srinivas | O39: {=IFERROR( INDEX('Scrum Teams'!B$2:B$1010, MATCH(1, (B39='Scrum Teams'!F$2:F$1010) + (B39='Scrum Teams'!G$2:G$1010) + (B39='Scrum Teams'!H$2:H$1010) + (B39='Scrum Teams'!I$2:I$1010) + (B39='Scrum Teams'!J$2:J$1010) + (B39='Scrum Teams'!K$2:K$1010) + (B39='Scrum Teams'!L$2:L$1010) + (B39='Scrum Teams'!M$2:M$1010) + (B39='Scrum Teams'!N$2:N$1010) + (B39='Scrum Teams'!O$2:O$1010) + (B39='Scrum Teams'!P$2:P$1010) + (B39='Scrum Teams'!Q$2:Q$1010), 0) ), "Not found" )} -> FixedOps Integration 3 | P39: INTG | Q39: Nishanth Nag
A40: ARCIntegration | B40: ARCIntegration-Platform | C40: D M Raj Karthick | D40: D M Raj Karthick | E40: Prakash Mohan | F40: Prakash Mohan | G40: Turker Coskun | H40: Advait Anand | I40: Dhanapal Mohanaswamy | K40: Tom Jude Ammanthurutil | M40: Turker Coskun | N40: Abhinandan Srinivas | O40: {=IFERROR( INDEX('Scrum Teams'!B$2:B$1010, MATCH(1, (B40='Scrum Teams'!F$2:F$1010) + (B40='Scrum Teams'!G$2:G$1010) + (B40='Scrum Teams'!H$2:H$1010) + (B40='Scrum Teams'!I$2:I$1010) + (B40='Scrum Teams'!J$2:J$1010) + (B40='Scrum Teams'!K$2:K$1010) + (B40='Scrum Teams'!L$2:L$1010) + (B40='Scrum Teams'!M$2:M$1010) + (B40='Scrum Teams'!N$2:N$1010) + (B40='Scrum Teams'!O$2:O$1010) + (B40='Scrum Teams'!P$2:P$1010) + (B40='Scrum Teams'!Q$2:Q$1010), 0) ), "Not found" )} -> Platform Integrations | P40: INTG | Q40: Nishanth Nag
A41: ARCIntegration | B41: ARCIntegration-Retail | C41: Raghavendra Pai | E41: Prakash Mohan | F41: Prakash Mohan | G41: Turker Coskun | H41: Diksha Jain | I41: Siddharth Bountra | J41: Siddharth Bountra | K41: Tom Jude Ammanthurutil | M41: Turker Coskun | N41: Abhinandan Srinivas | O41: {=IFERROR( INDEX('Scrum Teams'!B$2:B$1010, MATCH(1, (B41='Scrum Teams'!F$2:F$1010) + (B41='Scrum Teams'!G$2:G$1010) + (B41='Scrum Teams'!H$2:H$1010) + (B41='Scrum Teams'!I$2:I$1010) + (B41='Scrum Teams'!J$2:J$1010) + (B41='Scrum Teams'!K$2:K$1010) + (B41='Scrum Teams'!L$2:L$1010) + (B41='Scrum Teams'!M$2:M$1010) + (B41='Scrum Teams'!N$2:N$1010) + (B41='Scrum Teams'!O$2:O$1010) + (B41='Scrum Teams'!P$2:P$1010) + (B41='Scrum Teams'!Q$2:Q$1010), 0) ), "Not found" )} -> Retail Integration 1 | P41: INTG | Q41: Nishanth Nag
A42: ARCIntegration | B42: ARCIntegration-Service | C42: D M Raj Karthick | D42: D M Raj Karthick | E42: Prakash Mohan | F42: Prakash Mohan | G42: Turker Coskun | H42: Arjun Rajeev | K42: Tom Jude Ammanthurutil | M42: Turker Coskun | N42: Abhinandan Srinivas | O42: {=IFERROR( INDEX('Scrum Teams'!B$2:B$1010, MATCH(1, (B42='Scrum Teams'!F$2:F$1010) + (B42='Scrum Teams'!G$2:G$1010) + (B42='Scrum Teams'!H$2:H$1010) + (B42='Scrum Teams'!I$2:I$1010) + (B42='Scrum Teams'!J$2:J$1010) + (B42='Scrum Teams'!K$2:K$1010) + (B42='Scrum Teams'!L$2:L$1010) + (B42='Scrum Teams'!M$2:M$1010) + (B42='Scrum Teams'!N$2:N$1010) + (B42='Scrum Teams'!O$2:O$1010) + (B42='Scrum Teams'!P$2:P$1010) + (B42='Scrum Teams'!Q$2:Q$1010), 0) ), "Not found" )} -> FixedOps Integration 1 | P42: INTG | Q42: Nishanth Nag
A43: ARCIntegration | B43: ARCIntegration-VinDecoding | C43: D M Raj Karthick | D43: D M Raj Karthick | E43: Prakash Mohan | F43: Prakash Mohan | G43: Turker Coskun | H43: No PM Coverage | K43: Tom Jude Ammanthurutil | M43: Turker Coskun | N43: Abhinandan Srinivas | O43: {=IFERROR( INDEX('Scrum Teams'!B$2:B$1010, MATCH(1, (B43='Scrum Teams'!F$2:F$1010) + (B43='Scrum Teams'!G$2:G$1010) + (B43='Scrum Teams'!H$2:H$1010) + (B43='Scrum Teams'!I$2:I$1010) + (B43='Scrum Teams'!J$2:J$1010) + (B43='Scrum Teams'!K$2:K$1010) + (B43='Scrum Teams'!L$2:L$1010) + (B43='Scrum Teams'!M$2:M$1010) + (B43='Scrum Teams'!N$2:N$1010) + (B43='Scrum Teams'!O$2:O$1010) + (B43='Scrum Teams'!P$2:P$1010) + (B43='Scrum Teams'!Q$2:Q$1010), 0) ), "Not found" )} -> Not found | P43: INTG | Q43: Nishanth Nag
A44: ARCIntegration | B44: ARCIntegration-Payroll&Cashiering | C44: Raghavendra Pai | E44: Prakash Mohan | F44: Prakash Mohan | G44: Turker Coskun | H44: Glenn Joseph | I44: Sundar Rajagopalan | M44: Satyavrat Mudgil | N44: Abhinandan Srinivas | O44: {=IFERROR( INDEX('Scrum Teams'!B$2:B$1010, MATCH(1, (B44='Scrum Teams'!F$2:F$1010) + (B44='Scrum Teams'!G$2:G$1010) + (B44='Scrum Teams'!H$2:H$1010) + (B44='Scrum Teams'!I$2:I$1010) + (B44='Scrum Teams'!J$2:J$1010) + (B44='Scrum Teams'!K$2:K$1010) + (B44='Scrum Teams'!L$2:L$1010) + (B44='Scrum Teams'!M$2:M$1010) + (B44='Scrum Teams'!N$2:N$1010) + (B44='Scrum Teams'!O$2:O$1010) + (B44='Scrum Teams'!P$2:P$1010) + (B44='Scrum Teams'!Q$2:Q$1010), 0) ), "Not found" )} -> Credit & FNI Integrations | P44: INTG | Q44: Nishanth Nag
A45: ARCIntegration | B45: ARCIntegration-Comms | C45: Raghavendra Pai | E45: Prakash Mohan | F45: Prakash Mohan | G45: Turker Coskun | H45: Piyush Kumar | I45: Avin Jain | K45: Ashish Kalya | M45: Shiva Somasundaram | O45: {=IFERROR( INDEX('Scrum Teams'!B$2:B$1010, MATCH(1, (B45='Scrum Teams'!F$2:F$1010) + (B45='Scrum Teams'!G$2:G$1010) + (B45='Scrum Teams'!H$2:H$1010) + (B45='Scrum Teams'!I$2:I$1010) + (B45='Scrum Teams'!J$2:J$1010) + (B45='Scrum Teams'!K$2:K$1010) + (B45='Scrum Teams'!L$2:L$1010) + (B45='Scrum Teams'!M$2:M$1010) + (B45='Scrum Teams'!N$2:N$1010) + (B45='Scrum Teams'!O$2:O$1010) + (B45='Scrum Teams'!P$2:P$1010) + (B45='Scrum Teams'!Q$2:Q$1010), 0) ), "Not found" )} -> Retail Integration 2 | P45: INTG | Q45: Nishanth Nag
A46: Galaxy | B46: Galaxy-Core | C46: Sunil Garg | E46: Damodara Reddy | G46: Ved Singh | H46: Prashant Khulbe | I46: Hardik Patel | J46: Hardik Patel | K46: Irfan Presswala | L46: Irfan Presswala | M46: Satyavrat Mudgil | O46: {=IFERROR( INDEX('Scrum Teams'!B$2:B$1010, MATCH(1, (B46='Scrum Teams'!F$2:F$1010) + (B46='Scrum Teams'!G$2:G$1010) + (B46='Scrum Teams'!H$2:H$1010) + (B46='Scrum Teams'!I$2:I$1010) + (B46='Scrum Teams'!J$2:J$1010) + (B46='Scrum Teams'!K$2:K$1010) + (B46='Scrum Teams'!L$2:L$1010) + (B46='Scrum Teams'!M$2:M$1010) + (B46='Scrum Teams'!N$2:N$1010) + (B46='Scrum Teams'!O$2:O$1010) + (B46='Scrum Teams'!P$2:P$1010) + (B46='Scrum Teams'!Q$2:Q$1010), 0) ), "Not found" )} -> Kaveri | P46: GAL | Q46: Srividya Mandalapu
A47: Galaxy | B47: Galaxy-CMS_Decoder | C47: Sunil Garg | E47: Damodara Reddy | G47: Ved Singh | H47: Sudhanshu Madhur | I47: Prashant Khulbe | J47: Hardik Patel | K47: Irfan Presswala | L47: Irfan Presswala | M47: Satyavrat Mudgil | O47: {=IFERROR( INDEX('Scrum Teams'!B$2:B$1010, MATCH(1, (B47='Scrum Teams'!F$2:F$1010) + (B47='Scrum Teams'!G$2:G$1010) + (B47='Scrum Teams'!H$2:H$1010) + (B47='Scrum Teams'!I$2:I$1010) + (B47='Scrum Teams'!J$2:J$1010) + (B47='Scrum Teams'!K$2:K$1010) + (B47='Scrum Teams'!L$2:L$1010) + (B47='Scrum Teams'!M$2:M$1010) + (B47='Scrum Teams'!N$2:N$1010) + (B47='Scrum Teams'!O$2:O$1010) + (B47='Scrum Teams'!P$2:P$1010) + (B47='Scrum Teams'!Q$2:Q$1010), 0) ), "Not found" )} -> Kaveri | P47: GAL | Q47: Srividya Mandalapu
A48: Galaxy | B48: Galaxy-US | C48: Sunil Garg | E48: Damodara Reddy | G48: Ved Singh | H48: Prashant Khulbe | I48: Hardik Patel | J48: Hardik Patel | K48: Irfan Presswala | L48: Irfan Presswala | M48: Satyavrat Mudgil | O48: {=IFERROR( INDEX('Scrum Teams'!B$2:B$1010, MATCH(1, (B48='Scrum Teams'!F$2:F$1010) + (B48='Scrum Teams'!G$2:G$1010) + (B48='Scrum Teams'!H$2:H$1010) + (B48='Scrum Teams'!I$2:I$1010) + (B48='Scrum Teams'!J$2:J$1010) + (B48='Scrum Teams'!K$2:K$1010) + (B48='Scrum Teams'!L$2:L$1010) + (B48='Scrum Teams'!M$2:M$1010) + (B48='Scrum Teams'!N$2:N$1010) + (B48='Scrum Teams'!O$2:O$1010) + (B48='Scrum Teams'!P$2:P$1010) + (B48='Scrum Teams'!Q$2:Q$1010), 0) ), "Not found" )} -> Kaveri | P48: GAL | Q48: Srividya Mandalapu
A49: Galaxy | B49: Galaxy-Canada | C49: Sunil Garg | E49: Damodara Reddy | G49: Ved Singh | H49: Prashant Khulbe | I49: Hardik Patel | J49: Hardik Patel | K49: Irfan Presswala | L49: Irfan Presswala | M49: Satyavrat Mudgil | O49: {=IFERROR( INDEX('Scrum Teams'!B$2:B$1010, MATCH(1, (B49='Scrum Teams'!F$2:F$1010) + (B49='Scrum Teams'!G$2:G$1010) + (B49='Scrum Teams'!H$2:H$1010) + (B49='Scrum Teams'!I$2:I$1010) + (B49='Scrum Teams'!J$2:J$1010) + (B49='Scrum Teams'!K$2:K$1010) + (B49='Scrum Teams'!L$2:L$1010) + (B49='Scrum Teams'!M$2:M$1010) + (B49='Scrum Teams'!N$2:N$1010) + (B49='Scrum Teams'!O$2:O$1010) + (B49='Scrum Teams'!P$2:P$1010) + (B49='Scrum Teams'!Q$2:Q$1010), 0) ), "Not found" )} -> Kaveri | P49: GAL | Q49: Srividya Mandalapu
A50: Galaxy | B50: Galaxy-UK | C50: Sunil Garg | E50: Damodara Reddy | G50: Ved Singh | H50: Prashant Khulbe | I50: Hardik Patel | J50: Hardik Patel | K50: Irfan Presswala | L50: Irfan Presswala | M50: Satyavrat Mudgil | O50: {=IFERROR( INDEX('Scrum Teams'!B$2:B$1010, MATCH(1, (B50='Scrum Teams'!F$2:F$1010) + (B50='Scrum Teams'!G$2:G$1010) + (B50='Scrum Teams'!H$2:H$1010) + (B50='Scrum Teams'!I$2:I$1010) + (B50='Scrum Teams'!J$2:J$1010) + (B50='Scrum Teams'!K$2:K$1010) + (B50='Scrum Teams'!L$2:L$1010) + (B50='Scrum Teams'!M$2:M$1010) + (B50='Scrum Teams'!N$2:N$1010) + (B50='Scrum Teams'!O$2:O$1010) + (B50='Scrum Teams'!P$2:P$1010) + (B50='Scrum Teams'!Q$2:Q$1010), 0) ), "Not found" )} -> Kaveri | P50: GAL | Q50: Srividya Mandalapu
A51: Galaxy | B51: Galaxy-TDP_Modernisation | C51: Abhijeet Singh | E51: Damodara Reddy | G51: Ved Singh | H51: Sudhanshu Madhur | I51: Prashant Khulbe | J51: Hardik Patel | K51: Irfan Presswala | L51: Irfan Presswala | M51: Satyavrat Mudgil | O51: {=IFERROR( INDEX('Scrum Teams'!B$2:B$1010, MATCH(1, (B51='Scrum Teams'!F$2:F$1010) + (B51='Scrum Teams'!G$2:G$1010) + (B51='Scrum Teams'!H$2:H$1010) + (B51='Scrum Teams'!I$2:I$1010) + (B51='Scrum Teams'!J$2:J$1010) + (B51='Scrum Teams'!K$2:K$1010) + (B51='Scrum Teams'!L$2:L$1010) + (B51='Scrum Teams'!M$2:M$1010) + (B51='Scrum Teams'!N$2:N$1010) + (B51='Scrum Teams'!O$2:O$1010) + (B51='Scrum Teams'!P$2:P$1010) + (B51='Scrum Teams'!Q$2:Q$1010), 0) ), "Not found" )} -> Kaveri | P51: GAL | Q51: Srividya Mandalapu
A52: TDP | B52: TDP-Business | C52: Jerson Maglasang | E52: Damodara Reddy | G52: Ved Singh | H52: Diksha Jain | I52: Siddharth Bountra | J52: Siddharth Bountra | K52: Tom Jude Ammanthurutil | M52: Turker Coskun | O52: {=IFERROR( INDEX('Scrum Teams'!B$2:B$1010, MATCH(1, (B52='Scrum Teams'!F$2:F$1010) + (B52='Scrum Teams'!G$2:G$1010) + (B52='Scrum Teams'!H$2:H$1010) + (B52='Scrum Teams'!I$2:I$1010) + (B52='Scrum Teams'!J$2:J$1010) + (B52='Scrum Teams'!K$2:K$1010) + (B52='Scrum Teams'!L$2:L$1010) + (B52='Scrum Teams'!M$2:M$1010) + (B52='Scrum Teams'!N$2:N$1010) + (B52='Scrum Teams'!O$2:O$1010) + (B52='Scrum Teams'!P$2:P$1010) + (B52='Scrum Teams'!Q$2:Q$1010), 0) ), "Not found" )} -> Not found | Q52: Srividya Mandalapu
A53: Retail | B53: Retail-Desking | C53: Patel Abhijit Sunil | E53: Karan Jeet Singh | G53: Ved Singh | H53: Naman Jain | I53: Hardik Paharia | J53: Hardik Paharia | K53: Gaurav Gupta | L53: Gaurav Gupta | M53: Satyavrat Mudgil | N53: Lokesh Suresh | O53: {=IFERROR( INDEX('Scrum Teams'!B$2:B$1010, MATCH(1, (B53='Scrum Teams'!F$2:F$1010) + (B53='Scrum Teams'!G$2:G$1010) + (B53='Scrum Teams'!H$2:H$1010) + (B53='Scrum Teams'!I$2:I$1010) + (B53='Scrum Teams'!J$2:J$1010) + (B53='Scrum Teams'!K$2:K$1010) + (B53='Scrum Teams'!L$2:L$1010) + (B53='Scrum Teams'!M$2:M$1010) + (B53='Scrum Teams'!N$2:N$1010) + (B53='Scrum Teams'!O$2:O$1010) + (B53='Scrum Teams'!P$2:P$1010) + (B53='Scrum Teams'!Q$2:Q$1010), 0) ), "Not found" )} -> Desking | P53: RETL | Q53: Srividya Mandalapu
A54: Retail | B54: Retail-Deals | C54: Harish Nanjundaiah | E54: Karan Jeet Singh | G54: Ved Singh | H54: Avinash Kumar | I54: Nilesh Rana | J54: Hardik Paharia | K54: Gaurav Gupta | L54: Gaurav Gupta | M54: Satyavrat Mudgil | N54: Lokesh Suresh | O54: {=IFERROR( INDEX('Scrum Teams'!B$2:B$1010, MATCH(1, (B54='Scrum Teams'!F$2:F$1010) + (B54='Scrum Teams'!G$2:G$1010) + (B54='Scrum Teams'!H$2:H$1010) + (B54='Scrum Teams'!I$2:I$1010) + (B54='Scrum Teams'!J$2:J$1010) + (B54='Scrum Teams'!K$2:K$1010) + (B54='Scrum Teams'!L$2:L$1010) + (B54='Scrum Teams'!M$2:M$1010) + (B54='Scrum Teams'!N$2:N$1010) + (B54='Scrum Teams'!O$2:O$1010) + (B54='Scrum Teams'!P$2:P$1010) + (B54='Scrum Teams'!Q$2:Q$1010), 0) ), "Not found" )} -> Deals | P54: RETL | Q54: Srividya Mandalapu
A55: Retail | B55: Retail-Vehicle_Inventory | C55: Bogadapati Rupesh | E55: Karan Jeet Singh | G55: Ved Singh | H55: Akash Upadhyay | I55: Hardik Paharia | J55: Hardik Paharia | K55: Gaurav Gupta | L55: Gaurav Gupta | M55: Satyavrat Mudgil | N55: Lokesh Suresh | O55: {=IFERROR( INDEX('Scrum Teams'!B$2:B$1010, MATCH(1, (B55='Scrum Teams'!F$2:F$1010) + (B55='Scrum Teams'!G$2:G$1010) + (B55='Scrum Teams'!H$2:H$1010) + (B55='Scrum Teams'!I$2:I$1010) + (B55='Scrum Teams'!J$2:J$1010) + (B55='Scrum Teams'!K$2:K$1010) + (B55='Scrum Teams'!L$2:L$1010) + (B55='Scrum Teams'!M$2:M$1010) + (B55='Scrum Teams'!N$2:N$1010) + (B55='Scrum Teams'!O$2:O$1010) + (B55='Scrum Teams'!P$2:P$1010) + (B55='Scrum Teams'!Q$2:Q$1010), 0) ), "Not found" )} -> VI | P55: RETL | Q55: Srividya Mandalapu
A56: Retail | B56: Retail-Pricing | C56: Patel Abhijit Sunil | E56: Karan Jeet Singh | G56: Ved Singh | H56: Rakesh Reddy Nallagangula | I56: Rishabh Dwivedi | J56: Hardik Paharia | K56: Gaurav Gupta | L56: Gaurav Gupta | M56: Satyavrat Mudgil | N56: Lokesh Suresh | O56: {=IFERROR( INDEX('Scrum Teams'!B$2:B$1010, MATCH(1, (B56='Scrum Teams'!F$2:F$1010) + (B56='Scrum Teams'!G$2:G$1010) + (B56='Scrum Teams'!H$2:H$1010) + (B56='Scrum Teams'!I$2:I$1010) + (B56='Scrum Teams'!J$2:J$1010) + (B56='Scrum Teams'!K$2:K$1010) + (B56='Scrum Teams'!L$2:L$1010) + (B56='Scrum Teams'!M$2:M$1010) + (B56='Scrum Teams'!N$2:N$1010) + (B56='Scrum Teams'!O$2:O$1010) + (B56='Scrum Teams'!P$2:P$1010) + (B56='Scrum Teams'!Q$2:Q$1010), 0) ), "Not found" )} -> Pricing | P56: RETL | Q56: Srividya Mandalapu
A57: Retail | B57: Retail-IMS | C57: Samanwita De | E57: Karan Jeet Singh | G57: Ved Singh | H57: Hinal Kumar Mistry | I57: Hardik Paharia | J57: Hardik Paharia | K57: Gaurav Gupta | L57: Gaurav Gupta | M57: Satyavrat Mudgil | N57: Lokesh Suresh | O57: {=IFERROR( INDEX('Scrum Teams'!B$2:B$1010, MATCH(1, (B57='Scrum Teams'!F$2:F$1010) + (B57='Scrum Teams'!G$2:G$1010) + (B57='Scrum Teams'!H$2:H$1010) + (B57='Scrum Teams'!I$2:I$1010) + (B57='Scrum Teams'!J$2:J$1010) + (B57='Scrum Teams'!K$2:K$1010) + (B57='Scrum Teams'!L$2:L$1010) + (B57='Scrum Teams'!M$2:M$1010) + (B57='Scrum Teams'!N$2:N$1010) + (B57='Scrum Teams'!O$2:O$1010) + (B57='Scrum Teams'!P$2:P$1010) + (B57='Scrum Teams'!Q$2:Q$1010), 0) ), "Not found" )} -> IMS | P57: RETL | Q57: Srividya Mandalapu
A58: Retail | B58: Retail-Caviar | C58: Bogadapati Rupesh | E58: Karan Jeet Singh | G58: Ved Singh | H58: Ashish Rajput | I58: Hardik Paharia | J58: Hardik Paharia | K58: Gaurav Gupta | L58: Gaurav Gupta | M58: Satyavrat Mudgil | N58: Lokesh Suresh | O58: {=IFERROR( INDEX('Scrum Teams'!B$2:B$1010, MATCH(1, (B58='Scrum Teams'!F$2:F$1010) + (B58='Scrum Teams'!G$2:G$1010) + (B58='Scrum Teams'!H$2:H$1010) + (B58='Scrum Teams'!I$2:I$1010) + (B58='Scrum Teams'!J$2:J$1010) + (B58='Scrum Teams'!K$2:K$1010) + (B58='Scrum Teams'!L$2:L$1010) + (B58='Scrum Teams'!M$2:M$1010) + (B58='Scrum Teams'!N$2:N$1010) + (B58='Scrum Teams'!O$2:O$1010) + (B58='Scrum Teams'!P$2:P$1010) + (B58='Scrum Teams'!Q$2:Q$1010), 0) ), "Not found" )} -> CAVIAR | P58: RETL | Q58: Srividya Mandalapu
A59: Retail | B59: Retail-Mobile | C59: Bogadapati Rupesh | E59: Karan Jeet Singh | G59: Ved Singh | H59: Palash Sanjay Kotgirwar | I59: Hardik Paharia | J59: Hardik Paharia | K59: Gaurav Gupta | L59: Gaurav Gupta | M59: Satyavrat Mudgil | N59: Lokesh Suresh | O59: {=IFERROR( INDEX('Scrum Teams'!B$2:B$1010, MATCH(1, (B59='Scrum Teams'!F$2:F$1010) + (B59='Scrum Teams'!G$2:G$1010) + (B59='Scrum Teams'!H$2:H$1010) + (B59='Scrum Teams'!I$2:I$1010) + (B59='Scrum Teams'!J$2:J$1010) + (B59='Scrum Teams'!K$2:K$1010) + (B59='Scrum Teams'!L$2:L$1010) + (B59='Scrum Teams'!M$2:M$1010) + (B59='Scrum Teams'!N$2:N$1010) + (B59='Scrum Teams'!O$2:O$1010) + (B59='Scrum Teams'!P$2:P$1010) + (B59='Scrum Teams'!Q$2:Q$1010), 0) ), "Not found" )} -> VI | P59: RETL | Q59: Srividya Mandalapu
A60: Accounting | B60: Accounting-Core | C60: Ankita Bhandarkar | D60: Mudit Singhal | E60: Fahad Tasleem | G60: Sanyam Agrawal | H60: Saanya Singh | I60: Hanuth Singh | J60: Hanuth Singh | M60: Satyavrat Mudgil | O60: {=IFERROR( INDEX('Scrum Teams'!B$2:B$1010, MATCH(1, (B60='Scrum Teams'!F$2:F$1010) + (B60='Scrum Teams'!G$2:G$1010) + (B60='Scrum Teams'!H$2:H$1010) + (B60='Scrum Teams'!I$2:I$1010) + (B60='Scrum Teams'!J$2:J$1010) + (B60='Scrum Teams'!K$2:K$1010) + (B60='Scrum Teams'!L$2:L$1010) + (B60='Scrum Teams'!M$2:M$1010) + (B60='Scrum Teams'!N$2:N$1010) + (B60='Scrum Teams'!O$2:O$1010) + (B60='Scrum Teams'!P$2:P$1010) + (B60='Scrum Teams'!Q$2:Q$1010), 0) ), "Not found" )} -> Hydrogen | P60: ACCT | Q60: Akanksha Jadli
A61: Accounting | B61: Accounting-AP | C61: Spurthi Gouthareddy | E61: Fahad Tasleem | G61: Sanyam Agrawal | H61: Bismah Kiani | I61: Hanuth Singh | J61: Hanuth Singh | M61: Satyavrat Mudgil | N61: Jalu Ram | O61: {=IFERROR( INDEX('Scrum Teams'!B$2:B$1010, MATCH(1, (B61='Scrum Teams'!F$2:F$1010) + (B61='Scrum Teams'!G$2:G$1010) + (B61='Scrum Teams'!H$2:H$1010) + (B61='Scrum Teams'!I$2:I$1010) + (B61='Scrum Teams'!J$2:J$1010) + (B61='Scrum Teams'!K$2:K$1010) + (B61='Scrum Teams'!L$2:L$1010) + (B61='Scrum Teams'!M$2:M$1010) + (B61='Scrum Teams'!N$2:N$1010) + (B61='Scrum Teams'!O$2:O$1010) + (B61='Scrum Teams'!P$2:P$1010) + (B61='Scrum Teams'!Q$2:Q$1010), 0) ), "Not found" )} -> Gold | P61: ACCT | Q61: Akanksha Jadli
A62: Accounting | B62: Accounting-AR | C62: Charu Kulshrestha | E62: Fahad Tasleem | G62: Sanyam Agrawal | H62: Rohith Thommandru | I62: Hanuth Singh | J62: Hanuth Singh | M62: Satyavrat Mudgil | N62: Jalu Ram | O62: {=IFERROR( INDEX('Scrum Teams'!B$2:B$1010, MATCH(1, (B62='Scrum Teams'!F$2:F$1010) + (B62='Scrum Teams'!G$2:G$1010) + (B62='Scrum Teams'!H$2:H$1010) + (B62='Scrum Teams'!I$2:I$1010) + (B62='Scrum Teams'!J$2:J$1010) + (B62='Scrum Teams'!K$2:K$1010) + (B62='Scrum Teams'!L$2:L$1010) + (B62='Scrum Teams'!M$2:M$1010) + (B62='Scrum Teams'!N$2:N$1010) + (B62='Scrum Teams'!O$2:O$1010) + (B62='Scrum Teams'!P$2:P$1010) + (B62='Scrum Teams'!Q$2:Q$1010), 0) ), "Not found" )} -> Platinum | P62: ACCT | Q62: Akanksha Jadli
A63: Accounting | B63: Accounting-FS | C63: Ankita Bhandarkar | D63: Mudit Singhal | E63: Fahad Tasleem | G63: Sanyam Agrawal | H63: Calvin William Miranda | I63: Saanya Singh | J63: Hanuth Singh | M63: Satyavrat Mudgil | O63: {=IFERROR( INDEX('Scrum Teams'!B$2:B$1010, MATCH(1, (B63='Scrum Teams'!F$2:F$1010) + (B63='Scrum Teams'!G$2:G$1010) + (B63='Scrum Teams'!H$2:H$1010) + (B63='Scrum Teams'!I$2:I$1010) + (B63='Scrum Teams'!J$2:J$1010) + (B63='Scrum Teams'!K$2:K$1010) + (B63='Scrum Teams'!L$2:L$1010) + (B63='Scrum Teams'!M$2:M$1010) + (B63='Scrum Teams'!N$2:N$1010) + (B63='Scrum Teams'!O$2:O$1010) + (B63='Scrum Teams'!P$2:P$1010) + (B63='Scrum Teams'!Q$2:Q$1010), 0) ), "Not found" )} -> Helium | P63: ACCT | Q63: Akanksha Jadli
A64: Accounting | B64: Accounting-Core2 | C64: Mudit Singhal | D64: Mudit Singhal | E64: Fahad Tasleem | G64: Sanyam Agrawal | H64: Saanya Singh | I64: Hanuth Singh | J64: Hanuth Singh | M64: Satyavrat Mudgil | O64: {=IFERROR( INDEX('Scrum Teams'!B$2:B$1010, MATCH(1, (B64='Scrum Teams'!F$2:F$1010) + (B64='Scrum Teams'!G$2:G$1010) + (B64='Scrum Teams'!H$2:H$1010) + (B64='Scrum Teams'!I$2:I$1010) + (B64='Scrum Teams'!J$2:J$1010) + (B64='Scrum Teams'!K$2:K$1010) + (B64='Scrum Teams'!L$2:L$1010) + (B64='Scrum Teams'!M$2:M$1010) + (B64='Scrum Teams'!N$2:N$1010) + (B64='Scrum Teams'!O$2:O$1010) + (B64='Scrum Teams'!P$2:P$1010) + (B64='Scrum Teams'!Q$2:Q$1010), 0) ), "Not found" )} -> Helium | P64: ACCT | Q64: Akanksha Jadli
A65: Accounting | B65: Accounting-Platform | C65: Mudit Singhal | D65: Mudit Singhal | E65: Fahad Tasleem | G65: Sanyam Agrawal | H65: Saanya Singh | I65: Hanuth Singh | J65: Hanuth Singh | M65: Satyavrat Mudgil | O65: {=IFERROR( INDEX('Scrum Teams'!B$2:B$1010, MATCH(1, (B65='Scrum Teams'!F$2:F$1010) + (B65='Scrum Teams'!G$2:G$1010) + (B65='Scrum Teams'!H$2:H$1010) + (B65='Scrum Teams'!I$2:I$1010) + (B65='Scrum Teams'!J$2:J$1010) + (B65='Scrum Teams'!K$2:K$1010) + (B65='Scrum Teams'!L$2:L$1010) + (B65='Scrum Teams'!M$2:M$1010) + (B65='Scrum Teams'!N$2:N$1010) + (B65='Scrum Teams'!O$2:O$1010) + (B65='Scrum Teams'!P$2:P$1010) + (B65='Scrum Teams'!Q$2:Q$1010), 0) ), "Not found" )} -> Oxygen | P65: ACCT | Q65: Akanksha Jadli
A66: Accounting | B66: Accounting-AP-Payments | C66: Spurthi Gouthareddy | E66: Fahad Tasleem | G66: Sanyam Agrawal | H66: Bismah Kiani | I66: Hanuth Singh | J66: Hanuth Singh | M66: Satyavrat Mudgil | N66: Jalu Ram | O66: {=IFERROR( INDEX('Scrum Teams'!B$2:B$1010, MATCH(1, (B66='Scrum Teams'!F$2:F$1010) + (B66='Scrum Teams'!G$2:G$1010) + (B66='Scrum Teams'!H$2:H$1010) + (B66='Scrum Teams'!I$2:I$1010) + (B66='Scrum Teams'!J$2:J$1010) + (B66='Scrum Teams'!K$2:K$1010) + (B66='Scrum Teams'!L$2:L$1010) + (B66='Scrum Teams'!M$2:M$1010) + (B66='Scrum Teams'!N$2:N$1010) + (B66='Scrum Teams'!O$2:O$1010) + (B66='Scrum Teams'!P$2:P$1010) + (B66='Scrum Teams'!Q$2:Q$1010), 0) ), "Not found" )} -> Gold | P66: ACCT | Q66: Akanksha Jadli
A67: Accounting | B67: Accounting-VMS | C67: Spurthi Gouthareddy | E67: Fahad Tasleem | G67: Sanyam Agrawal | H67: Bismah Kiani | I67: Hanuth Singh | J67: Hanuth Singh | M67: Satyavrat Mudgil | N67: Abhishek Ghildiyal | O67: Aurum | P67: ACCT | Q67: Akanksha Jadli
A68: Payroll | B68: Payroll-V1 | C68: Suhail Jain | E68: Fahad Tasleem | G68: Sanyam Agrawal | H68: Preston Griffin | I68: Sundar Rajagopalan | M68: Satyavrat Mudgil | O68: {=IFERROR( INDEX('Scrum Teams'!B$2:B$1010, MATCH(1, (B68='Scrum Teams'!F$2:F$1010) + (B68='Scrum Teams'!G$2:G$1010) + (B68='Scrum Teams'!H$2:H$1010) + (B68='Scrum Teams'!I$2:I$1010) + (B68='Scrum Teams'!J$2:J$1010) + (B68='Scrum Teams'!K$2:K$1010) + (B68='Scrum Teams'!L$2:L$1010) + (B68='Scrum Teams'!M$2:M$1010) + (B68='Scrum Teams'!N$2:N$1010) + (B68='Scrum Teams'!O$2:O$1010) + (B68='Scrum Teams'!P$2:P$1010) + (B68='Scrum Teams'!Q$2:Q$1010), 0) ), "Not found" )} -> Earth | P68: PYRL | Q68: Akanksha Jadli
A69: Payroll | B69: Payroll-V2 | C69: Suhail Jain | E69: Fahad Tasleem | G69: Sanyam Agrawal | H69: Jeremy Atkin | I69: Sundar Rajagopalan | M69: Satyavrat Mudgil | O69: {=IFERROR( INDEX('Scrum Teams'!B$2:B$1010, MATCH(1, (B69='Scrum Teams'!F$2:F$1010) + (B69='Scrum Teams'!G$2:G$1010) + (B69='Scrum Teams'!H$2:H$1010) + (B69='Scrum Teams'!I$2:I$1010) + (B69='Scrum Teams'!J$2:J$1010) + (B69='Scrum Teams'!K$2:K$1010) + (B69='Scrum Teams'!L$2:L$1010) + (B69='Scrum Teams'!M$2:M$1010) + (B69='Scrum Teams'!N$2:N$1010) + (B69='Scrum Teams'!O$2:O$1010) + (B69='Scrum Teams'!P$2:P$1010) + (B69='Scrum Teams'!Q$2:Q$1010), 0) ), "Not found" )} -> Earth | P69: PYRL | Q69: Akanksha Jadli
A70: Payroll | B70: Payroll-EH_V1 | C70: Suhail Jain | E70: Fahad Tasleem | G70: Sanyam Agrawal | H70: Glen Joseph | I70: Sundar Rajagopalan | M70: Satyavrat Mudgil | O70: {=IFERROR( INDEX('Scrum Teams'!B$2:B$1010, MATCH(1, (B70='Scrum Teams'!F$2:F$1010) + (B70='Scrum Teams'!G$2:G$1010) + (B70='Scrum Teams'!H$2:H$1010) + (B70='Scrum Teams'!I$2:I$1010) + (B70='Scrum Teams'!J$2:J$1010) + (B70='Scrum Teams'!K$2:K$1010) + (B70='Scrum Teams'!L$2:L$1010) + (B70='Scrum Teams'!M$2:M$1010) + (B70='Scrum Teams'!N$2:N$1010) + (B70='Scrum Teams'!O$2:O$1010) + (B70='Scrum Teams'!P$2:P$1010) + (B70='Scrum Teams'!Q$2:Q$1010), 0) ), "Not found" )} -> Mars | P70: PYRL | Q70: Akanksha Jadli
A71: Payroll | B71: Payroll-EH_V2 | C71: Suhail Jain | E71: Fahad Tasleem | G71: Sanyam Agrawal | H71: Glen Joseph | I71: Sundar Rajagopalan | M71: Satyavrat Mudgil | O71: {=IFERROR( INDEX('Scrum Teams'!B$2:B$1010, MATCH(1, (B71='Scrum Teams'!F$2:F$1010) + (B71='Scrum Teams'!G$2:G$1010) + (B71='Scrum Teams'!H$2:H$1010) + (B71='Scrum Teams'!I$2:I$1010) + (B71='Scrum Teams'!J$2:J$1010) + (B71='Scrum Teams'!K$2:K$1010) + (B71='Scrum Teams'!L$2:L$1010) + (B71='Scrum Teams'!M$2:M$1010) + (B71='Scrum Teams'!N$2:N$1010) + (B71='Scrum Teams'!O$2:O$1010) + (B71='Scrum Teams'!P$2:P$1010) + (B71='Scrum Teams'!Q$2:Q$1010), 0) ), "Not found" )} -> Mars | P71: PYRL | Q71: Akanksha Jadli
A72: eSign_Platform | B72: eSign_Platform | C72: Suhail Jain | E72: Fahad Tasleem | G72: Sanyam Agrawal | H72: Sireesha Yakkali | I72: Hardik Patel | J72: Hardik Patel | K72: Irfan Presswala | L72: Irfan Presswala | M72: Satyavrat Mudgil | N72: Jagadish M | O72: {=IFERROR( INDEX('Scrum Teams'!B$2:B$1010, MATCH(1, (B72='Scrum Teams'!F$2:F$1010) + (B72='Scrum Teams'!G$2:G$1010) + (B72='Scrum Teams'!H$2:H$1010) + (B72='Scrum Teams'!I$2:I$1010) + (B72='Scrum Teams'!J$2:J$1010) + (B72='Scrum Teams'!K$2:K$1010) + (B72='Scrum Teams'!L$2:L$1010) + (B72='Scrum Teams'!M$2:M$1010) + (B72='Scrum Teams'!N$2:N$1010) + (B72='Scrum Teams'!O$2:O$1010) + (B72='Scrum Teams'!P$2:P$1010) + (B72='Scrum Teams'!Q$2:Q$1010), 0) ), "Not found" )} -> eSign_Platform | P72: ESGN | Q72: Akanksha Jadli
A73: Cashiering | B73: Cashiering | C73: Suhail Jain | E73: Fahad Tasleem | G73: Sanyam Agrawal | H73: Kumar Gaurav | I73: Babu Pasupathy | J73: Babu Pasupathy | M73: Satyavrat Mudgil | N73: Jagadish M | O73: {=IFERROR( INDEX('Scrum Teams'!B$2:B$1010, MATCH(1, (B73='Scrum Teams'!F$2:F$1010) + (B73='Scrum Teams'!G$2:G$1010) + (B73='Scrum Teams'!H$2:H$1010) + (B73='Scrum Teams'!I$2:I$1010) + (B73='Scrum Teams'!J$2:J$1010) + (B73='Scrum Teams'!K$2:K$1010) + (B73='Scrum Teams'!L$2:L$1010) + (B73='Scrum Teams'!M$2:M$1010) + (B73='Scrum Teams'!N$2:N$1010) + (B73='Scrum Teams'!O$2:O$1010) + (B73='Scrum Teams'!P$2:P$1010) + (B73='Scrum Teams'!Q$2:Q$1010), 0) ), "Not found" )} -> Cashiering | P73: CASH | Q73: Akanksha Jadli
A74: Service | B74: Service-RO_Core | C74: Prasad Nagraj | E74: Prashant Gupta, Vraj Solanki | G74: Sanyam Agrawal | H74: Darshan Dange | I74: Rishabh Dassani | K74: Alok Joshi | L74: Alok Joshi | M74: Satyavrat Mudgil | N74: Sangeetha Sharma | O74: {=IFERROR( INDEX('Scrum Teams'!B$2:B$1010, MATCH(1, (B74='Scrum Teams'!F$2:F$1010) + (B74='Scrum Teams'!G$2:G$1010) + (B74='Scrum Teams'!H$2:H$1010) + (B74='Scrum Teams'!I$2:I$1010) + (B74='Scrum Teams'!J$2:J$1010) + (B74='Scrum Teams'!K$2:K$1010) + (B74='Scrum Teams'!L$2:L$1010) + (B74='Scrum Teams'!M$2:M$1010) + (B74='Scrum Teams'!N$2:N$1010) + (B74='Scrum Teams'!O$2:O$1010) + (B74='Scrum Teams'!P$2:P$1010) + (B74='Scrum Teams'!Q$2:Q$1010), 0) ), "Not found" )} -> RO-Core | P74: SERV | Q74: Akanksha Jadli
A75: Service | B75: Service-RO_Web | C75: Prasad Nagraj | E75: Prashant Gupta, Vraj Solanki | G75: Sanyam Agrawal | H75: Darshan Dange | I75: Rishabh Dassani | K75: Alok Joshi | L75: Alok Joshi | M75: Satyavrat Mudgil | N75: Sangeetha Sharma | O75: {=IFERROR( INDEX('Scrum Teams'!B$2:B$1010, MATCH(1, (B75='Scrum Teams'!F$2:F$1010) + (B75='Scrum Teams'!G$2:G$1010) + (B75='Scrum Teams'!H$2:H$1010) + (B75='Scrum Teams'!I$2:I$1010) + (B75='Scrum Teams'!J$2:J$1010) + (B75='Scrum Teams'!K$2:K$1010) + (B75='Scrum Teams'!L$2:L$1010) + (B75='Scrum Teams'!M$2:M$1010) + (B75='Scrum Teams'!N$2:N$1010) + (B75='Scrum Teams'!O$2:O$1010) + (B75='Scrum Teams'!P$2:P$1010) + (B75='Scrum Teams'!Q$2:Q$1010), 0) ), "Not found" )} -> RO-Core | P75: SERV | Q75: Akanksha Jadli
A76: Service | B76: Service-Platform | C76: Syed Absar Ahmad | D76: Amit Parpiyani | E76: Prashant Gupta, Vraj Solanki | G76: Sanyam Agrawal | H76: Ayush Aditya | I76: Rishabh Dassani | K76: Alok Joshi | L76: Alok Joshi | M76: Satyavrat Mudgil | N76: Sangeetha Sharma | O76: {=IFERROR( INDEX('Scrum Teams'!B$2:B$1010, MATCH(1, (B76='Scrum Teams'!F$2:F$1010) + (B76='Scrum Teams'!G$2:G$1010) + (B76='Scrum Teams'!H$2:H$1010) + (B76='Scrum Teams'!I$2:I$1010) + (B76='Scrum Teams'!J$2:J$1010) + (B76='Scrum Teams'!K$2:K$1010) + (B76='Scrum Teams'!L$2:L$1010) + (B76='Scrum Teams'!M$2:M$1010) + (B76='Scrum Teams'!N$2:N$1010) + (B76='Scrum Teams'!O$2:O$1010) + (B76='Scrum Teams'!P$2:P$1010) + (B76='Scrum Teams'!Q$2:Q$1010), 0) ), "Not found" )} -> Platform | P76: SERV | Q76: Akanksha Jadli
A77: Service | B77: Service-Scheduling | C77: Raj Patel | D77: Raj Patel | E77: Prashant Gupta, Vraj Solanki | G77: Sanyam Agrawal | H77: Sivarprasad Danthuluri | I77: Rishabh Dassani | K77: Alok Joshi | L77: Alok Joshi | M77: Satyavrat Mudgil | N77: Sangeetha Sharma | O77: {=IFERROR( INDEX('Scrum Teams'!B$2:B$1010, MATCH(1, (B77='Scrum Teams'!F$2:F$1010) + (B77='Scrum Teams'!G$2:G$1010) + (B77='Scrum Teams'!H$2:H$1010) + (B77='Scrum Teams'!I$2:I$1010) + (B77='Scrum Teams'!J$2:J$1010) + (B77='Scrum Teams'!K$2:K$1010) + (B77='Scrum Teams'!L$2:L$1010) + (B77='Scrum Teams'!M$2:M$1010) + (B77='Scrum Teams'!N$2:N$1010) + (B77='Scrum Teams'!O$2:O$1010) + (B77='Scrum Teams'!P$2:P$1010) + (B77='Scrum Teams'!Q$2:Q$1010), 0) ), "Not found" )} -> Scheduling | P77: SERV | Q77: Akanksha Jadli
A78: Service | B78: Service-Reporting | C78: Raj Patel | D78: Raj Patel | E78: Prashant Gupta, Vraj Solanki | G78: Sanyam Agrawal | H78: Himani Gandhi | I78: Rishabh Dassani | K78: Alok Joshi | L78: Alok Joshi | M78: Satyavrat Mudgil | N78: Sangeetha Sharma | O78: {=IFERROR( INDEX('Scrum Teams'!B$2:B$1010, MATCH(1, (B78='Scrum Teams'!F$2:F$1010) + (B78='Scrum Teams'!G$2:G$1010) + (B78='Scrum Teams'!H$2:H$1010) + (B78='Scrum Teams'!I$2:I$1010) + (B78='Scrum Teams'!J$2:J$1010) + (B78='Scrum Teams'!K$2:K$1010) + (B78='Scrum Teams'!L$2:L$1010) + (B78='Scrum Teams'!M$2:M$1010) + (B78='Scrum Teams'!N$2:N$1010) + (B78='Scrum Teams'!O$2:O$1010) + (B78='Scrum Teams'!P$2:P$1010) + (B78='Scrum Teams'!Q$2:Q$1010), 0) ), "Not found" )} -> Scheduling | P78: SERV | Q78: Akanksha Jadli
A79: Service | B79: Service-Setups | C79: Amit Parpiyani | D79: Amit Parpiyani | E79: Prashant Gupta, Vraj Solanki | G79: Sanyam Agrawal | H79: Ankith NVP | I79: Rishabh Dassani | K79: Alok Joshi | L79: Alok Joshi | M79: Satyavrat Mudgil | N79: Sangeetha Sharma | O79: {=IFERROR( INDEX('Scrum Teams'!B$2:B$1010, MATCH(1, (B79='Scrum Teams'!F$2:F$1010) + (B79='Scrum Teams'!G$2:G$1010) + (B79='Scrum Teams'!H$2:H$1010) + (B79='Scrum Teams'!I$2:I$1010) + (B79='Scrum Teams'!J$2:J$1010) + (B79='Scrum Teams'!K$2:K$1010) + (B79='Scrum Teams'!L$2:L$1010) + (B79='Scrum Teams'!M$2:M$1010) + (B79='Scrum Teams'!N$2:N$1010) + (B79='Scrum Teams'!O$2:O$1010) + (B79='Scrum Teams'!P$2:P$1010) + (B79='Scrum Teams'!Q$2:Q$1010), 0) ), "Not found" )} -> Platform | P79: SERV | Q79: Akanksha Jadli
A80: Service | B80: Service-Integrations | C80: Amit Parpiyani | D80: Amit Parpiyani | E80: Prashant Gupta, Vraj Solanki | G80: Sanyam Agrawal | H80: Ankith NVP | I80: Rishabh Dassani | K80: Alok Joshi | L80: Alok Joshi | M80: Satyavrat Mudgil | N80: Sangeetha Sharma | O80: {=IFERROR( INDEX('Scrum Teams'!B$2:B$1010, MATCH(1, (B80='Scrum Teams'!F$2:F$1010) + (B80='Scrum Teams'!G$2:G$1010) + (B80='Scrum Teams'!H$2:H$1010) + (B80='Scrum Teams'!I$2:I$1010) + (B80='Scrum Teams'!J$2:J$1010) + (B80='Scrum Teams'!K$2:K$1010) + (B80='Scrum Teams'!L$2:L$1010) + (B80='Scrum Teams'!M$2:M$1010) + (B80='Scrum Teams'!N$2:N$1010) + (B80='Scrum Teams'!O$2:O$1010) + (B80='Scrum Teams'!P$2:P$1010) + (B80='Scrum Teams'!Q$2:Q$1010), 0) ), "Not found" )} -> Platform | P80: SERV | Q80: Akanksha Jadli
A81: Service | B81: Service-Dealer_Apps | C81: Jyothish | E81: Prashant Gupta, Vraj Solanki | G81: Sanyam Agrawal | H81: Pranav Kothiwal | I81: Rishabh Dassani | K81: Alok Joshi | L81: Alok Joshi | M81: Satyavrat Mudgil | N81: Sangeetha Sharma | O81: {=IFERROR( INDEX('Scrum Teams'!B$2:B$1010, MATCH(1, (B81='Scrum Teams'!F$2:F$1010) + (B81='Scrum Teams'!G$2:G$1010) + (B81='Scrum Teams'!H$2:H$1010) + (B81='Scrum Teams'!I$2:I$1010) + (B81='Scrum Teams'!J$2:J$1010) + (B81='Scrum Teams'!K$2:K$1010) + (B81='Scrum Teams'!L$2:L$1010) + (B81='Scrum Teams'!M$2:M$1010) + (B81='Scrum Teams'!N$2:N$1010) + (B81='Scrum Teams'!O$2:O$1010) + (B81='Scrum Teams'!P$2:P$1010) + (B81='Scrum Teams'!Q$2:Q$1010), 0) ), "Not found" )} -> Dealer-Apps | P81: SERV | Q81: Akanksha Jadli
A82: Service | B82: Service-Consumer_Apps | C82: Faheem Ahmad | E82: Prashant Gupta, Vraj Solanki | G82: Sanyam Agrawal | H82: Rakshit Agnihotri | I82: Rishabh Dassani | K82: Alok Joshi | L82: Alok Joshi | M82: Satyavrat Mudgil | N82: Sangeetha Sharma | O82: {=IFERROR( INDEX('Scrum Teams'!B$2:B$1010, MATCH(1, (B82='Scrum Teams'!F$2:F$1010) + (B82='Scrum Teams'!G$2:G$1010) + (B82='Scrum Teams'!H$2:H$1010) + (B82='Scrum Teams'!I$2:I$1010) + (B82='Scrum Teams'!J$2:J$1010) + (B82='Scrum Teams'!K$2:K$1010) + (B82='Scrum Teams'!L$2:L$1010) + (B82='Scrum Teams'!M$2:M$1010) + (B82='Scrum Teams'!N$2:N$1010) + (B82='Scrum Teams'!O$2:O$1010) + (B82='Scrum Teams'!P$2:P$1010) + (B82='Scrum Teams'!Q$2:Q$1010), 0) ), "Not found" )} -> Consumer | P82: SERV | Q82: Akanksha Jadli
A83: Service | B83: Service-Core | C83: Syed Absar Ahmad | D83: Amit Parpiyani | E83: Prashant Gupta, Vraj Solanki | G83: Sanyam Agrawal | H83: Ayush Aditya | I83: Rishabh Dassani | K83: Alok Joshi | L83: Alok Joshi | M83: Satyavrat Mudgil | N83: Sangeetha Sharma | O83: {=IFERROR( INDEX('Scrum Teams'!B$2:B$1010, MATCH(1, (B83='Scrum Teams'!F$2:F$1010) + (B83='Scrum Teams'!G$2:G$1010) + (B83='Scrum Teams'!H$2:H$1010) + (B83='Scrum Teams'!I$2:I$1010) + (B83='Scrum Teams'!J$2:J$1010) + (B83='Scrum Teams'!K$2:K$1010) + (B83='Scrum Teams'!L$2:L$1010) + (B83='Scrum Teams'!M$2:M$1010) + (B83='Scrum Teams'!N$2:N$1010) + (B83='Scrum Teams'!O$2:O$1010) + (B83='Scrum Teams'!P$2:P$1010) + (B83='Scrum Teams'!Q$2:Q$1010), 0) ), "Not found" )} -> Platform | P83: SERV | Q83: Akanksha Jadli
A84: Service | B84: Service-Mobile | C84: Faheem Ahmad | E84: Prashant Gupta, Vraj Solanki | G84: Sanyam Agrawal | H84: Rakshit Agnihotri | I84: Rishabh Dassani | K84: Alok Joshi | L84: Alok Joshi | M84: Satyavrat Mudgil | N84: Sangeetha Sharma | O84: {=IFERROR( INDEX('Scrum Teams'!B$2:B$1010, MATCH(1, (B84='Scrum Teams'!F$2:F$1010) + (B84='Scrum Teams'!G$2:G$1010) + (B84='Scrum Teams'!H$2:H$1010) + (B84='Scrum Teams'!I$2:I$1010) + (B84='Scrum Teams'!J$2:J$1010) + (B84='Scrum Teams'!K$2:K$1010) + (B84='Scrum Teams'!L$2:L$1010) + (B84='Scrum Teams'!M$2:M$1010) + (B84='Scrum Teams'!N$2:N$1010) + (B84='Scrum Teams'!O$2:O$1010) + (B84='Scrum Teams'!P$2:P$1010) + (B84='Scrum Teams'!Q$2:Q$1010), 0) ), "Not found" )} -> ServiceMobile | P84: SERV | Q84: Akanksha Jadli
A85: Service | B85: Service-MobilePlatform_Android | C85: Faheem Ahmad | E85: Prashant Gupta, Vraj Solanki | G85: Sanyam Agrawal | H85: Rakshit Agnihotri | I85: Rishabh Dassani | K85: Alok Joshi | L85: Alok Joshi | M85: Satyavrat Mudgil | O85: {=IFERROR( INDEX('Scrum Teams'!B$2:B$1010, MATCH(1, (B85='Scrum Teams'!F$2:F$1010) + (B85='Scrum Teams'!G$2:G$1010) + (B85='Scrum Teams'!H$2:H$1010) + (B85='Scrum Teams'!I$2:I$1010) + (B85='Scrum Teams'!J$2:J$1010) + (B85='Scrum Teams'!K$2:K$1010) + (B85='Scrum Teams'!L$2:L$1010) + (B85='Scrum Teams'!M$2:M$1010) + (B85='Scrum Teams'!N$2:N$1010) + (B85='Scrum Teams'!O$2:O$1010) + (B85='Scrum Teams'!P$2:P$1010) + (B85='Scrum Teams'!Q$2:Q$1010), 0) ), "Not found" )} -> ServiceMobile | P85: SERV | Q85: Akanksha Jadli
A86: Service | B86: Service-MobilePlatform_iOS | C86: Faheem Ahmad | E86: Prashant Gupta, Vraj Solanki | G86: Sanyam Agrawal | H86: Jayshri Soundarajan | I86: Vamsee Krishna Mullapudi | J86: Vamsee Krishna Mullapudi | K86: Vijayakumar B | M86: Shiva Somasundaram | O86: {=IFERROR( INDEX('Scrum Teams'!B$2:B$1010, MATCH(1, (B86='Scrum Teams'!F$2:F$1010) + (B86='Scrum Teams'!G$2:G$1010) + (B86='Scrum Teams'!H$2:H$1010) + (B86='Scrum Teams'!I$2:I$1010) + (B86='Scrum Teams'!J$2:J$1010) + (B86='Scrum Teams'!K$2:K$1010) + (B86='Scrum Teams'!L$2:L$1010) + (B86='Scrum Teams'!M$2:M$1010) + (B86='Scrum Teams'!N$2:N$1010) + (B86='Scrum Teams'!O$2:O$1010) + (B86='Scrum Teams'!P$2:P$1010) + (B86='Scrum Teams'!Q$2:Q$1010), 0) ), "Not found" )} -> ServiceMobile | P86: SERV | Q86: Akanksha Jadli
A87: Service | B87: Service-MobilePlatform_RN | C87: Faheem Ahmad | E87: Prashant Gupta, Vraj Solanki | G87: Sanyam Agrawal | H87: Jayshri Soundarajan | I87: Vamsee Krishna Mullapudi | J87: Vamsee Krishna Mullapudi | K87: Vijayakumar B | M87: Shiva Somasundaram | O87: {=IFERROR( INDEX('Scrum Teams'!B$2:B$1010, MATCH(1, (B87='Scrum Teams'!F$2:F$1010) + (B87='Scrum Teams'!G$2:G$1010) + (B87='Scrum Teams'!H$2:H$1010) + (B87='Scrum Teams'!I$2:I$1010) + (B87='Scrum Teams'!J$2:J$1010) + (B87='Scrum Teams'!K$2:K$1010) + (B87='Scrum Teams'!L$2:L$1010) + (B87='Scrum Teams'!M$2:M$1010) + (B87='Scrum Teams'!N$2:N$1010) + (B87='Scrum Teams'!O$2:O$1010) + (B87='Scrum Teams'!P$2:P$1010) + (B87='Scrum Teams'!Q$2:Q$1010), 0) ), "Not found" )} -> ServiceMobile | P87: SERV | Q87: Akanksha Jadli
A88: Service | B88: Service-ServiceOutboundAI | E88: Prashant Gupta, Vraj Solanki | G88: Sanyam Agrawal | O88: {=IFERROR( INDEX('Scrum Teams'!B$2:B$1010, MATCH(1, (B88='Scrum Teams'!F$2:F$1010) + (B88='Scrum Teams'!G$2:G$1010) + (B88='Scrum Teams'!H$2:H$1010) + (B88='Scrum Teams'!I$2:I$1010) + (B88='Scrum Teams'!J$2:J$1010) + (B88='Scrum Teams'!K$2:K$1010) + (B88='Scrum Teams'!L$2:L$1010) + (B88='Scrum Teams'!M$2:M$1010) + (B88='Scrum Teams'!N$2:N$1010) + (B88='Scrum Teams'!O$2:O$1010) + (B88='Scrum Teams'!P$2:P$1010) + (B88='Scrum Teams'!Q$2:Q$1010), 0) ), "Not found" )} -> Not found | P88: SERV | Q88: Akanksha Jadli
A89: Parts | B89: Parts-Inventory | C89: Jay Doshi | D89: Akshay Nagpurkar | E89: Anirudh Agarwal | G89: Sanyam Agrawal | H89: Ritesh Batra | I89: Sarita Surapaneni | J89: Sarita Surapaneni | K89: Alok Joshi | L89: Alok Joshi | M89: Satyavrat Mudgil | N89: Venkateswara Rao Gudipati | O89: {=IFERROR( INDEX('Scrum Teams'!B$2:B$1010, MATCH(1, (B89='Scrum Teams'!F$2:F$1010) + (B89='Scrum Teams'!G$2:G$1010) + (B89='Scrum Teams'!H$2:H$1010) + (B89='Scrum Teams'!I$2:I$1010) + (B89='Scrum Teams'!J$2:J$1010) + (B89='Scrum Teams'!K$2:K$1010) + (B89='Scrum Teams'!L$2:L$1010) + (B89='Scrum Teams'!M$2:M$1010) + (B89='Scrum Teams'!N$2:N$1010) + (B89='Scrum Teams'!O$2:O$1010) + (B89='Scrum Teams'!P$2:P$1010) + (B89='Scrum Teams'!Q$2:Q$1010), 0) ), "Not found" )} -> Inventory Guardians | P89: PART | Q89: Akanksha Jadli
A90: Parts | B90: Parts-Physical_Inventory | C90: Jay Doshi | D90: Akshay Nagpurkar | E90: Anirudh Agarwal | G90: Sanyam Agrawal | H90: Nandu Battula | I90: Sarita Surapaneni | J90: Sarita Surapaneni | K90: Alok Joshi | L90: Alok Joshi | M90: Satyavrat Mudgil | N90: Venkateswara Rao Gudipati | O90: {=IFERROR( INDEX('Scrum Teams'!B$2:B$1010, MATCH(1, (B90='Scrum Teams'!F$2:F$1010) + (B90='Scrum Teams'!G$2:G$1010) + (B90='Scrum Teams'!H$2:H$1010) + (B90='Scrum Teams'!I$2:I$1010) + (B90='Scrum Teams'!J$2:J$1010) + (B90='Scrum Teams'!K$2:K$1010) + (B90='Scrum Teams'!L$2:L$1010) + (B90='Scrum Teams'!M$2:M$1010) + (B90='Scrum Teams'!N$2:N$1010) + (B90='Scrum Teams'!O$2:O$1010) + (B90='Scrum Teams'!P$2:P$1010) + (B90='Scrum Teams'!Q$2:Q$1010), 0) ), "Not found" )} -> Inventory Guardians | P90: PART | Q90: Akanksha Jadli
A91: Parts | B91: Parts-Purchase_Order | C91: Jay Doshi | D91: Akshay Nagpurkar | E91: Anirudh Agarwal | G91: Sanyam Agrawal | H91: Snigdha Sahoo | I91: Hemant Agarwal | J91: Sarita Surapaneni | K91: Alok Joshi | L91: Alok Joshi | M91: Satyavrat Mudgil | N91: Venkateswara Rao Gudipati | O91: {=IFERROR( INDEX('Scrum Teams'!B$2:B$1010, MATCH(1, (B91='Scrum Teams'!F$2:F$1010) + (B91='Scrum Teams'!G$2:G$1010) + (B91='Scrum Teams'!H$2:H$1010) + (B91='Scrum Teams'!I$2:I$1010) + (B91='Scrum Teams'!J$2:J$1010) + (B91='Scrum Teams'!K$2:K$1010) + (B91='Scrum Teams'!L$2:L$1010) + (B91='Scrum Teams'!M$2:M$1010) + (B91='Scrum Teams'!N$2:N$1010) + (B91='Scrum Teams'!O$2:O$1010) + (B91='Scrum Teams'!P$2:P$1010) + (B91='Scrum Teams'!Q$2:Q$1010), 0) ), "Not found" )} -> Ordering Operators | P91: PART | Q91: Akanksha Jadli
A92: Parts | B92: Parts-Receiving | C92: Jay Doshi | D92: Akshay Nagpurkar | E92: Anirudh Agarwal | G92: Sanyam Agrawal | H92: Rounak Das | I92: Hemant Agarwal | J92: Sarita Surapaneni | K92: Alok Joshi | L92: Alok Joshi | M92: Satyavrat Mudgil | N92: Venkateswara Rao Gudipati | O92: {=IFERROR( INDEX('Scrum Teams'!B$2:B$1010, MATCH(1, (B92='Scrum Teams'!F$2:F$1010) + (B92='Scrum Teams'!G$2:G$1010) + (B92='Scrum Teams'!H$2:H$1010) + (B92='Scrum Teams'!I$2:I$1010) + (B92='Scrum Teams'!J$2:J$1010) + (B92='Scrum Teams'!K$2:K$1010) + (B92='Scrum Teams'!L$2:L$1010) + (B92='Scrum Teams'!M$2:M$1010) + (B92='Scrum Teams'!N$2:N$1010) + (B92='Scrum Teams'!O$2:O$1010) + (B92='Scrum Teams'!P$2:P$1010) + (B92='Scrum Teams'!Q$2:Q$1010), 0) ), "Not found" )} -> Ordering Operators | P92: PART | Q92: Akanksha Jadli
A93: Parts | B93: Parts-Sales_Order | C93: Vidit Gupta | D93: Akshay Nagpurkar | E93: Anirudh Agarwal | G93: Sanyam Agrawal | H93: Prajjwal Khandelwal | I93: Sarita Surapaneni | J93: Sarita Surapaneni | K93: Alok Joshi | L93: Alok Joshi | M93: Satyavrat Mudgil | N93: Venkateswara Rao Gudipati | O93: {=IFERROR( INDEX('Scrum Teams'!B$2:B$1010, MATCH(1, (B93='Scrum Teams'!F$2:F$1010) + (B93='Scrum Teams'!G$2:G$1010) + (B93='Scrum Teams'!H$2:H$1010) + (B93='Scrum Teams'!I$2:I$1010) + (B93='Scrum Teams'!J$2:J$1010) + (B93='Scrum Teams'!K$2:K$1010) + (B93='Scrum Teams'!L$2:L$1010) + (B93='Scrum Teams'!M$2:M$1010) + (B93='Scrum Teams'!N$2:N$1010) + (B93='Scrum Teams'!O$2:O$1010) + (B93='Scrum Teams'!P$2:P$1010) + (B93='Scrum Teams'!Q$2:Q$1010), 0) ), "Not found" )} -> Sales Order Frontiers | P93: PART | Q93: Akanksha Jadli
A94: Parts | B94: Parts-Special_Order_Request | C94: Vidit Gupta | D94: Akshay Nagpurkar | E94: Anirudh Agarwal | G94: Sanyam Agrawal | H94: Sumedha Sagar | I94: Hemant Agarwal | J94: Sarita Surapaneni | K94: Alok Joshi | L94: Alok Joshi | M94: Satyavrat Mudgil | N94: Venkateswara Rao Gudipati | O94: {=IFERROR( INDEX('Scrum Teams'!B$2:B$1010, MATCH(1, (B94='Scrum Teams'!F$2:F$1010) + (B94='Scrum Teams'!G$2:G$1010) + (B94='Scrum Teams'!H$2:H$1010) + (B94='Scrum Teams'!I$2:I$1010) + (B94='Scrum Teams'!J$2:J$1010) + (B94='Scrum Teams'!K$2:K$1010) + (B94='Scrum Teams'!L$2:L$1010) + (B94='Scrum Teams'!M$2:M$1010) + (B94='Scrum Teams'!N$2:N$1010) + (B94='Scrum Teams'!O$2:O$1010) + (B94='Scrum Teams'!P$2:P$1010) + (B94='Scrum Teams'!Q$2:Q$1010), 0) ), "Not found" )} -> Sales Order Frontiers | P94: PART | Q94: Akanksha Jadli
A95: Parts | B95: Parts-Label_Configurator | C95: Jay Doshi | D95: Akshay Nagpurkar | E95: Anirudh Agarwal | G95: Sanyam Agrawal | H95: Nandu Battula | I95: Sarita Surapaneni | J95: Sarita Surapaneni | K95: Alok Joshi | L95: Alok Joshi | M95: Satyavrat Mudgil | N95: Venkateswara Rao Gudipati | O95: {=IFERROR( INDEX('Scrum Teams'!B$2:B$1010, MATCH(1, (B95='Scrum Teams'!F$2:F$1010) + (B95='Scrum Teams'!G$2:G$1010) + (B95='Scrum Teams'!H$2:H$1010) + (B95='Scrum Teams'!I$2:I$1010) + (B95='Scrum Teams'!J$2:J$1010) + (B95='Scrum Teams'!K$2:K$1010) + (B95='Scrum Teams'!L$2:L$1010) + (B95='Scrum Teams'!M$2:M$1010) + (B95='Scrum Teams'!N$2:N$1010) + (B95='Scrum Teams'!O$2:O$1010) + (B95='Scrum Teams'!P$2:P$1010) + (B95='Scrum Teams'!Q$2:Q$1010), 0) ), "Not found" )} -> Ordering Operators | P95: PART | Q95: Akanksha Jadli
A96: Parts | B96: Parts-Repair_Order_Sales | C96: Prajesh Sahoo | D96: Akshay Nagpurkar | E96: Anirudh Agarwal | G96: Sanyam Agrawal | H96: Snigdha Sahoo | I96: Hemant Agarwal | J96: Sarita Surapaneni | K96: Alok Joshi | L96: Alok Joshi | M96: Satyavrat Mudgil | N96: Venkateswara Rao Gudipati | O96: {=IFERROR( INDEX('Scrum Teams'!B$2:B$1010, MATCH(1, (B96='Scrum Teams'!F$2:F$1010) + (B96='Scrum Teams'!G$2:G$1010) + (B96='Scrum Teams'!H$2:H$1010) + (B96='Scrum Teams'!I$2:I$1010) + (B96='Scrum Teams'!J$2:J$1010) + (B96='Scrum Teams'!K$2:K$1010) + (B96='Scrum Teams'!L$2:L$1010) + (B96='Scrum Teams'!M$2:M$1010) + (B96='Scrum Teams'!N$2:N$1010) + (B96='Scrum Teams'!O$2:O$1010) + (B96='Scrum Teams'!P$2:P$1010) + (B96='Scrum Teams'!Q$2:Q$1010), 0) ), "Not found" )} -> Repair Order Fulfillers | P96: PART | Q96: Akanksha Jadli
A97: Parts | B97: Parts-Picklist | C97: Prajesh Sahoo | D97: Akshay Nagpurkar | E97: Anirudh Agarwal | G97: Sanyam Agrawal | H97: Prajjwal Khandelwal | I97: Sarita Surapaneni | J97: Sarita Surapaneni | K97: Alok Joshi | L97: Alok Joshi | M97: Satyavrat Mudgil | N97: Venkateswara Rao Gudipati | O97: {=IFERROR( INDEX('Scrum Teams'!B$2:B$1010, MATCH(1, (B97='Scrum Teams'!F$2:F$1010) + (B97='Scrum Teams'!G$2:G$1010) + (B97='Scrum Teams'!H$2:H$1010) + (B97='Scrum Teams'!I$2:I$1010) + (B97='Scrum Teams'!J$2:J$1010) + (B97='Scrum Teams'!K$2:K$1010) + (B97='Scrum Teams'!L$2:L$1010) + (B97='Scrum Teams'!M$2:M$1010) + (B97='Scrum Teams'!N$2:N$1010) + (B97='Scrum Teams'!O$2:O$1010) + (B97='Scrum Teams'!P$2:P$1010) + (B97='Scrum Teams'!Q$2:Q$1010), 0) ), "Not found" )} -> Repair Order Fulfillers | P97: PART | Q97: Akanksha Jadli
A98: Parts | B98: Parts-Dirty_Core_Inventory | C98: Jay Doshi | D98: Akshay Nagpurkar | E98: Anirudh Agarwal | G98: Sanyam Agrawal | H98: Rounak Das | I98: Hemant Agarwal | J98: Sarita Surapaneni | K98: Alok Joshi | L98: Alok Joshi | M98: Satyavrat Mudgil | N98: Venkateswara Rao Gudipati | O98: {=IFERROR( INDEX('Scrum Teams'!B$2:B$1010, MATCH(1, (B98='Scrum Teams'!F$2:F$1010) + (B98='Scrum Teams'!G$2:G$1010) + (B98='Scrum Teams'!H$2:H$1010) + (B98='Scrum Teams'!I$2:I$1010) + (B98='Scrum Teams'!J$2:J$1010) + (B98='Scrum Teams'!K$2:K$1010) + (B98='Scrum Teams'!L$2:L$1010) + (B98='Scrum Teams'!M$2:M$1010) + (B98='Scrum Teams'!N$2:N$1010) + (B98='Scrum Teams'!O$2:O$1010) + (B98='Scrum Teams'!P$2:P$1010) + (B98='Scrum Teams'!Q$2:Q$1010), 0) ), "Not found" )} -> Ordering Operators | P98: PART | Q98: Akanksha Jadli
A99: Parts | B99: Parts-Material_Return | C99: Jay Doshi | D99: Akshay Nagpurkar | E99: Anirudh Agarwal | G99: Sanyam Agrawal | H99: Rounak Das | I99: Hemant Agarwal | J99: Sarita Surapaneni | K99: Alok Joshi | L99: Alok Joshi | M99: Satyavrat Mudgil | N99: Venkateswara Rao Gudipati | O99: {=IFERROR( INDEX('Scrum Teams'!B$2:B$1010, MATCH(1, (B99='Scrum Teams'!F$2:F$1010) + (B99='Scrum Teams'!G$2:G$1010) + (B99='Scrum Teams'!H$2:H$1010) + (B99='Scrum Teams'!I$2:I$1010) + (B99='Scrum Teams'!J$2:J$1010) + (B99='Scrum Teams'!K$2:K$1010) + (B99='Scrum Teams'!L$2:L$1010) + (B99='Scrum Teams'!M$2:M$1010) + (B99='Scrum Teams'!N$2:N$1010) + (B99='Scrum Teams'!O$2:O$1010) + (B99='Scrum Teams'!P$2:P$1010) + (B99='Scrum Teams'!Q$2:Q$1010), 0) ), "Not found" )} -> Ordering Operators | P99: PART | Q99: Akanksha Jadli
A100: Parts | B100: Parts-Price_Tape | C100: Jay Doshi | D100: Akshay Nagpurkar | E100: Anirudh Agarwal | G100: Sanyam Agrawal | H100: Pranjal Pushp | I100: Hemant Agarwal | J100: Sarita Surapaneni | K100: Alok Joshi | L100: Alok Joshi | M100: Satyavrat Mudgil | N100: Venkateswara Rao Gudipati | O100: {=IFERROR( INDEX('Scrum Teams'!B$2:B$1010, MATCH(1, (B100='Scrum Teams'!F$2:F$1010) + (B100='Scrum Teams'!G$2:G$1010) + (B100='Scrum Teams'!H$2:H$1010) + (B100='Scrum Teams'!I$2:I$1010) + (B100='Scrum Teams'!J$2:J$1010) + (B100='Scrum Teams'!K$2:K$1010) + (B100='Scrum Teams'!L$2:L$1010) + (B100='Scrum Teams'!M$2:M$1010) + (B100='Scrum Teams'!N$2:N$1010) + (B100='Scrum Teams'!O$2:O$1010) + (B100='Scrum Teams'!P$2:P$1010) + (B100='Scrum Teams'!Q$2:Q$1010), 0) ), "Not found" )} -> Integrations Connectors | P100: PART | Q100: Akanksha Jadli
...

Sheet Capacity
A1: Project / Space | B1: Key | C1: Past Velocity | D1: Sprint Capacity | E1: Monthly Capacity for Calc | F1: Discrepancy? | G1: Component | H1: Key | I1: Sprint Capacity | J1: Monthly Capacity for Calc | K1: Discrepancy? | L1: Component | M1: Scrum Team | N1: Key | O1: Sprint Capacity | P1: Actual Monthly Capacity | Q1: Monthly Capacity for Calc | R1: VP | T1: Teams | U1: May-25 | V1: Jun-25 | W1: Jul-25 | X1: Velocity
A2: Accounting | B2: ACCT | D2: =IF(E2="","",E2/2) -> 285 | E2: =IF(B2="","",SUMIFS($J$2:$J$39,$H$2:$H$39,B2)) -> 570 | F2: {=IF(B2="","",_xlfn.LET( _xlpm.comp, TRIM(CLEAN(B2)), _xlpm.expected, E2, _xlpm.actual, SUMPRODUCT(--(TRIM(CLEAN($H$2:$H$140))=_xlpm.comp), $J$2:$J$140), IF(_xlpm.actual=_xlpm.expected, "No", "Mismatch by " & (_xlpm.actual-_xlpm.expected)) ))} -> No | G2: {=IFERROR(INDEX(_xlfn._xlws.SORT(_xlfn.UNIQUE(_xlfn._xlws.FILTER($L$2:$L$140,$L$2:$L$140<>""))),ROW()-1),"")} -> Accounting | H2: =IF(G2="", "", _xlfn.XLOOKUP(G2, 'Component Masterlist v2'!A:A, 'Component Masterlist v2'!P:P, "Not found")) -> ACCT | I2: =IF(J2="","",J2/2) -> 285 | J2: =IF(G2="","",SUMIFS($Q$2:$Q$140,$L$2:$L$140,G2)) -> 570 | K2: {=IF(G2="","",_xlfn.LET( _xlpm.comp, TRIM(CLEAN(G2)), _xlpm.expected, J2, _xlpm.actual, SUMPRODUCT(--(TRIM(CLEAN($L$2:$L$140))=_xlpm.comp), $Q$2:$Q$140), IF(_xlpm.actual=_xlpm.expected, "No", "Mismatch by " & (_xlpm.actual-_xlpm.expected)) ))} -> No | L2: =IF(M2="", "", _xlfn.XLOOKUP(M2,'Scrum Teams'!B:B,'Scrum Teams'!A:A,"")) -> Accounting | M2: {=IFERROR(INDEX(_xlfn.SORTBY(_xlfn.UNIQUE(_xlfn._xlws.FILTER('Scrum Teams'!$B$2:$B$1006,'Scrum Teams'!$B$2:$B$1006<>"")),_xlfn.XLOOKUP(_xlfn.UNIQUE(_xlfn._xlws.FILTER('Scrum Teams'!$B$2:$B$1006,'Scrum Teams'!$B$2:$B$1006<>"")),'Scrum Teams'!$B:$B,'Scrum Teams'!$A:$A,"")),ROW()-1),"")} -> Gold | N2: =IF(L2="", "", _xlfn.XLOOKUP(L2, 'Component Masterlist v2'!A:A, 'Component Masterlist v2'!P:P, "Not found")) -> ACCT | O2: =IF(P2="", "", P2/2) -> 86 | P2: =IF(M2="","",_xlfn.LET( _xlpm.pos, MATCH(M2,'Scrum Teams'!$B$2:$B$1006,0), _xlpm.val, INDEX('Scrum Teams'!$E$2:$E$1006,_xlpm.pos), IF(ISBLANK(INDEX('Scrum Teams'!$E$2:$E$1006,_xlpm.pos)),"",_xlpm.val) )) -> 172 | Q2: =IF(L2="","",IF(P2<>"", P2, 90)) -> 172 | R2: =IF(M2="","",IF(L2="", "Missing component", _xlfn.XLOOKUP(L2, Lookup!A:A, Lookup!D:D, "NA"))) -> Sanyam Agrawal | S2: Refresh? | T2: Platform | U2: 139.5 | V2: 124 | W2: 182.5 | X2: 148.66667
A3: AEPlatform | B3: AEP | D3: =IF(E3="","",E3/2) -> 765 | E3: =IF(B3="","",SUMIFS($J$2:$J$39,$H$2:$H$39,B3)) -> 1530 | F3: {=IF(B3="","",_xlfn.LET( _xlpm.comp, TRIM(CLEAN(B3)), _xlpm.expected, E3, _xlpm.actual, SUMPRODUCT(--(TRIM(CLEAN($H$2:$H$140))=_xlpm.comp), $J$2:$J$140), IF(_xlpm.actual=_xlpm.expected, "No", "Mismatch by " & (_xlpm.actual-_xlpm.expected)) ))} -> No | G3: {=IFERROR(INDEX(_xlfn._xlws.SORT(_xlfn.UNIQUE(_xlfn._xlws.FILTER($L$2:$L$140,$L$2:$L$140<>""))),ROW()-1),"")} -> AEPlatform | H3: =IF(G3="", "", _xlfn.XLOOKUP(G3, 'Component Masterlist v2'!A:A, 'Component Masterlist v2'!P:P, "Not found")) -> AEP | I3: =IF(J3="","",J3/2) -> 765 | J3: =IF(G3="","",SUMIFS($Q$2:$Q$140,$L$2:$L$140,G3)) -> 1530 | K3: {=IF(G3="","",_xlfn.LET( _xlpm.comp, TRIM(CLEAN(G3)), _xlpm.expected, J3, _xlpm.actual, SUMPRODUCT(--(TRIM(CLEAN($L$2:$L$140))=_xlpm.comp), $Q$2:$Q$140), IF(_xlpm.actual=_xlpm.expected, "No", "Mismatch by " & (_xlpm.actual-_xlpm.expected)) ))} -> No | L3: =IF(M3="", "", _xlfn.XLOOKUP(M3,'Scrum Teams'!B:B,'Scrum Teams'!A:A,"")) -> Accounting | M3: {=IFERROR(INDEX(_xlfn.SORTBY(_xlfn.UNIQUE(_xlfn._xlws.FILTER('Scrum Teams'!$B$2:$B$1006,'Scrum Teams'!$B$2:$B$1006<>"")),_xlfn.XLOOKUP(_xlfn.UNIQUE(_xlfn._xlws.FILTER('Scrum Teams'!$B$2:$B$1006,'Scrum Teams'!$B$2:$B$1006<>"")),'Scrum Teams'!$B:$B,'Scrum Teams'!$A:$A,"")),ROW()-1),"")} -> Helium | N3: =IF(L3="", "", _xlfn.XLOOKUP(L3, 'Component Masterlist v2'!A:A, 'Component Masterlist v2'!P:P, "Not found")) -> ACCT | O3: =IF(P3="", "", P3/2) -> 58 | P3: =IF(M3="","",_xlfn.LET( _xlpm.pos, MATCH(M3,'Scrum Teams'!$B$2:$B$1006,0), _xlpm.val, INDEX('Scrum Teams'!$E$2:$E$1006,_xlpm.pos), IF(ISBLANK(INDEX('Scrum Teams'!$E$2:$E$1006,_xlpm.pos)),"",_xlpm.val) )) -> 116 | Q3: =IF(L3="","",IF(P3<>"", P3, 90)) -> 116 | R3: =IF(M3="","",IF(L3="", "Missing component", _xlfn.XLOOKUP(L3, Lookup!A:A, Lookup!D:D, "NA"))) -> Sanyam Agrawal | S3: {=IF( SUM(--ISNA(MATCH( _xlfn.UNIQUE(_xlfn._xlws.FILTER('Scrum Teams'!B2:B1010, 'Scrum Teams'!B2:B1010<>"")), _xlfn.UNIQUE(_xlfn._xlws.FILTER(M2:M1010, M2:M1010<>"")), 0 ))) > 0, "Yes", IF( AND( COUNT(_xlfn.UNIQUE(_xlfn._xlws.FILTER(M2:M1010, M2:M1010<>""))) = COUNT(_xlfn.UNIQUE(_xlfn._xlws.FILTER('Scrum Teams'!B2:B1010, 'Scrum Teams'!B2:B1010<>""))), SUM(--ISNA(MATCH( _xlfn.UNIQUE(_xlfn._xlws.FILTER(M2:M1010, M2:M1010<>"")), _xlfn.UNIQUE(_xlfn._xlws.FILTER('Scrum Teams'!B2:B1010, 'Scrum Teams'!B2:B1010<>"")), 0 )))=0 ), "No", "Check" ) )} -> No | T3: Retail | U3: 709 | V3: 481 | W3: 399 | X3: 529.66667
A4: AI | B4: AI | D4: =IF(E4="","",E4/2) -> 150 | E4: =IF(B4="","",SUMIFS($J$2:$J$39,$H$2:$H$39,B4)) -> 300 | F4: {=IF(B4="","",_xlfn.LET( _xlpm.comp, TRIM(CLEAN(B4)), _xlpm.expected, E4, _xlpm.actual, SUMPRODUCT(--(TRIM(CLEAN($H$2:$H$140))=_xlpm.comp), $J$2:$J$140), IF(_xlpm.actual=_xlpm.expected, "No", "Mismatch by " & (_xlpm.actual-_xlpm.expected)) ))} -> No | G4: {=IFERROR(INDEX(_xlfn._xlws.SORT(_xlfn.UNIQUE(_xlfn._xlws.FILTER($L$2:$L$140,$L$2:$L$140<>""))),ROW()-1),"")} -> AI_Core | H4: =IF(G4="", "", _xlfn.XLOOKUP(G4, 'Component Masterlist v2'!A:A, 'Component Masterlist v2'!P:P, "Not found")) -> AI | I4: =IF(J4="","",J4/2) -> 150 | J4: =IF(G4="","",SUMIFS($Q$2:$Q$140,$L$2:$L$140,G4)) -> 300 | K4: {=IF(G4="","",_xlfn.LET( _xlpm.comp, TRIM(CLEAN(G4)), _xlpm.expected, J4, _xlpm.actual, SUMPRODUCT(--(TRIM(CLEAN($L$2:$L$140))=_xlpm.comp), $Q$2:$Q$140), IF(_xlpm.actual=_xlpm.expected, "No", "Mismatch by " & (_xlpm.actual-_xlpm.expected)) ))} -> No | L4: =IF(M4="", "", _xlfn.XLOOKUP(M4,'Scrum Teams'!B:B,'Scrum Teams'!A:A,"")) -> Accounting | M4: {=IFERROR(INDEX(_xlfn.SORTBY(_xlfn.UNIQUE(_xlfn._xlws.FILTER('Scrum Teams'!$B$2:$B$1006,'Scrum Teams'!$B$2:$B$1006<>"")),_xlfn.XLOOKUP(_xlfn.UNIQUE(_xlfn._xlws.FILTER('Scrum Teams'!$B$2:$B$1006,'Scrum Teams'!$B$2:$B$1006<>"")),'Scrum Teams'!$B:$B,'Scrum Teams'!$A:$A,"")),ROW()-1),"")} -> Hydrogen | N4: =IF(L4="", "", _xlfn.XLOOKUP(L4, 'Component Masterlist v2'!A:A, 'Component Masterlist v2'!P:P, "Not found")) -> ACCT | O4: =IF(P4="", "", P4/2) -> 51 | P4: =IF(M4="","",_xlfn.LET( _xlpm.pos, MATCH(M4,'Scrum Teams'!$B$2:$B$1006,0), _xlpm.val, INDEX('Scrum Teams'!$E$2:$E$1006,_xlpm.pos), IF(ISBLANK(INDEX('Scrum Teams'!$E$2:$E$1006,_xlpm.pos)),"",_xlpm.val) )) -> 102 | Q4: =IF(L4="","",IF(P4<>"", P4, 90)) -> 102 | R4: =IF(M4="","",IF(L4="", "Missing component", _xlfn.XLOOKUP(L4, Lookup!A:A, Lookup!D:D, "NA"))) -> Sanyam Agrawal
A5: AI Platform | B5: AIPL | D5: =IF(E5="","",E5/2) -> 112.5 | E5: =IF(B5="","",SUMIFS($J$2:$J$39,$H$2:$H$39,B5)) -> 225 | F5: {=IF(B5="","",_xlfn.LET( _xlpm.comp, TRIM(CLEAN(B5)), _xlpm.expected, E5, _xlpm.actual, SUMPRODUCT(--(TRIM(CLEAN($H$2:$H$140))=_xlpm.comp), $J$2:$J$140), IF(_xlpm.actual=_xlpm.expected, "No", "Mismatch by " & (_xlpm.actual-_xlpm.expected)) ))} -> No | G5: {=IFERROR(INDEX(_xlfn._xlws.SORT(_xlfn.UNIQUE(_xlfn._xlws.FILTER($L$2:$L$140,$L$2:$L$140<>""))),ROW()-1),"")} -> AIBDC | H5: =IF(G5="", "", _xlfn.XLOOKUP(G5, 'Component Masterlist v2'!A:A, 'Component Masterlist v2'!P:P, "Not found")) -> AIB | I5: =IF(J5="","",J5/2) -> 87.5 | J5: =IF(G5="","",SUMIFS($Q$2:$Q$140,$L$2:$L$140,G5)) -> 175 | K5: {=IF(G5="","",_xlfn.LET( _xlpm.comp, TRIM(CLEAN(G5)), _xlpm.expected, J5, _xlpm.actual, SUMPRODUCT(--(TRIM(CLEAN($L$2:$L$140))=_xlpm.comp), $Q$2:$Q$140), IF(_xlpm.actual=_xlpm.expected, "No", "Mismatch by " & (_xlpm.actual-_xlpm.expected)) ))} -> No | L5: =IF(M5="", "", _xlfn.XLOOKUP(M5,'Scrum Teams'!B:B,'Scrum Teams'!A:A,"")) -> Accounting | M5: {=IFERROR(INDEX(_xlfn.SORTBY(_xlfn.UNIQUE(_xlfn._xlws.FILTER('Scrum Teams'!$B$2:$B$1006,'Scrum Teams'!$B$2:$B$1006<>"")),_xlfn.XLOOKUP(_xlfn.UNIQUE(_xlfn._xlws.FILTER('Scrum Teams'!$B$2:$B$1006,'Scrum Teams'!$B$2:$B$1006<>"")),'Scrum Teams'!$B:$B,'Scrum Teams'!$A:$A,"")),ROW()-1),"")} -> Oxygen | N5: =IF(L5="", "", _xlfn.XLOOKUP(L5, 'Component Masterlist v2'!A:A, 'Component Masterlist v2'!P:P, "Not found")) -> ACCT | O5: =IF(P5="", "", P5/2) -> 18 | P5: =IF(M5="","",_xlfn.LET( _xlpm.pos, MATCH(M5,'Scrum Teams'!$B$2:$B$1006,0), _xlpm.val, INDEX('Scrum Teams'!$E$2:$E$1006,_xlpm.pos), IF(ISBLANK(INDEX('Scrum Teams'!$E$2:$E$1006,_xlpm.pos)),"",_xlpm.val) )) -> 36 | Q5: =IF(L5="","",IF(P5<>"", P5, 90)) -> 36 | R5: =IF(M5="","",IF(L5="", "Missing component", _xlfn.XLOOKUP(L5, Lookup!A:A, Lookup!D:D, "NA"))) -> Sanyam Agrawal
A6: AIBDC | B6: AIB | D6: =IF(E6="","",E6/2) -> 87.5 | E6: =IF(B6="","",SUMIFS($J$2:$J$39,$H$2:$H$39,B6)) -> 175 | F6: {=IF(B6="","",_xlfn.LET( _xlpm.comp, TRIM(CLEAN(B6)), _xlpm.expected, E6, _xlpm.actual, SUMPRODUCT(--(TRIM(CLEAN($H$2:$H$140))=_xlpm.comp), $J$2:$J$140), IF(_xlpm.actual=_xlpm.expected, "No", "Mismatch by " & (_xlpm.actual-_xlpm.expected)) ))} -> No | G6: {=IFERROR(INDEX(_xlfn._xlws.SORT(_xlfn.UNIQUE(_xlfn._xlws.FILTER($L$2:$L$140,$L$2:$L$140<>""))),ROW()-1),"")} -> AIE_Core | H6: =IF(G6="", "", _xlfn.XLOOKUP(G6, 'Component Masterlist v2'!A:A, 'Component Masterlist v2'!P:P, "Not found")) -> AIPL | I6: =IF(J6="","",J6/2) -> 67.5 | J6: =IF(G6="","",SUMIFS($Q$2:$Q$140,$L$2:$L$140,G6)) -> 135 | K6: {=IF(G6="","",_xlfn.LET( _xlpm.comp, TRIM(CLEAN(G6)), _xlpm.expected, J6, _xlpm.actual, SUMPRODUCT(--(TRIM(CLEAN($L$2:$L$140))=_xlpm.comp), $Q$2:$Q$140), IF(_xlpm.actual=_xlpm.expected, "No", "Mismatch by " & (_xlpm.actual-_xlpm.expected)) ))} -> No | L6: =IF(M6="", "", _xlfn.XLOOKUP(M6,'Scrum Teams'!B:B,'Scrum Teams'!A:A,"")) -> Accounting | M6: {=IFERROR(INDEX(_xlfn.SORTBY(_xlfn.UNIQUE(_xlfn._xlws.FILTER('Scrum Teams'!$B$2:$B$1006,'Scrum Teams'!$B$2:$B$1006<>"")),_xlfn.XLOOKUP(_xlfn.UNIQUE(_xlfn._xlws.FILTER('Scrum Teams'!$B$2:$B$1006,'Scrum Teams'!$B$2:$B$1006<>"")),'Scrum Teams'!$B:$B,'Scrum Teams'!$A:$A,"")),ROW()-1),"")} -> Platinum | N6: =IF(L6="", "", _xlfn.XLOOKUP(L6, 'Component Masterlist v2'!A:A, 'Component Masterlist v2'!P:P, "Not found")) -> ACCT | O6: =IF(P6="", "", P6/2) -> 54 | P6: =IF(M6="","",_xlfn.LET( _xlpm.pos, MATCH(M6,'Scrum Teams'!$B$2:$B$1006,0), _xlpm.val, INDEX('Scrum Teams'!$E$2:$E$1006,_xlpm.pos), IF(ISBLANK(INDEX('Scrum Teams'!$E$2:$E$1006,_xlpm.pos)),"",_xlpm.val) )) -> 108 | Q6: =IF(L6="","",IF(P6<>"", P6, 90)) -> 108 | R6: =IF(M6="","",IF(L6="", "Missing component", _xlfn.XLOOKUP(L6, Lookup!A:A, Lookup!D:D, "NA"))) -> Sanyam Agrawal
A7: Analytics | B7: ANLY | D7: =IF(E7="","",E7/2) -> 112.5 | E7: =IF(B7="","",SUMIFS($J$2:$J$39,$H$2:$H$39,B7)) -> 225 | F7: {=IF(B7="","",_xlfn.LET( _xlpm.comp, TRIM(CLEAN(B7)), _xlpm.expected, E7, _xlpm.actual, SUMPRODUCT(--(TRIM(CLEAN($H$2:$H$140))=_xlpm.comp), $J$2:$J$140), IF(_xlpm.actual=_xlpm.expected, "No", "Mismatch by " & (_xlpm.actual-_xlpm.expected)) ))} -> No | G7: {=IFERROR(INDEX(_xlfn._xlws.SORT(_xlfn.UNIQUE(_xlfn._xlws.FILTER($L$2:$L$140,$L$2:$L$140<>""))),ROW()-1),"")} -> AIE_Platform | H7: =IF(G7="", "", _xlfn.XLOOKUP(G7, 'Component Masterlist v2'!A:A, 'Component Masterlist v2'!P:P, "Not found")) -> AIPL | I7: =IF(J7="","",J7/2) -> 45 | J7: =IF(G7="","",SUMIFS($Q$2:$Q$140,$L$2:$L$140,G7)) -> 90 | K7: {=IF(G7="","",_xlfn.LET( _xlpm.comp, TRIM(CLEAN(G7)), _xlpm.expected, J7, _xlpm.actual, SUMPRODUCT(--(TRIM(CLEAN($L$2:$L$140))=_xlpm.comp), $Q$2:$Q$140), IF(_xlpm.actual=_xlpm.expected, "No", "Mismatch by " & (_xlpm.actual-_xlpm.expected)) ))} -> No | L7: =IF(M7="", "", _xlfn.XLOOKUP(M7,'Scrum Teams'!B:B,'Scrum Teams'!A:A,"")) -> Accounting | M7: {=IFERROR(INDEX(_xlfn.SORTBY(_xlfn.UNIQUE(_xlfn._xlws.FILTER('Scrum Teams'!$B$2:$B$1006,'Scrum Teams'!$B$2:$B$1006<>"")),_xlfn.XLOOKUP(_xlfn.UNIQUE(_xlfn._xlws.FILTER('Scrum Teams'!$B$2:$B$1006,'Scrum Teams'!$B$2:$B$1006<>"")),'Scrum Teams'!$B:$B,'Scrum Teams'!$A:$A,"")),ROW()-1),"")} -> Aurum | N7: =IF(L7="", "", _xlfn.XLOOKUP(L7, 'Component Masterlist v2'!A:A, 'Component Masterlist v2'!P:P, "Not found")) -> ACCT | O7: =IF(P7="", "", P7/2) -> 18 | P7: =IF(M7="","",_xlfn.LET( _xlpm.pos, MATCH(M7,'Scrum Teams'!$B$2:$B$1006,0), _xlpm.val, INDEX('Scrum Teams'!$E$2:$E$1006,_xlpm.pos), IF(ISBLANK(INDEX('Scrum Teams'!$E$2:$E$1006,_xlpm.pos)),"",_xlpm.val) )) -> 36 | Q7: =IF(L7="","",IF(P7<>"", P7, 90)) -> 36 | R7: =IF(M7="","",IF(L7="", "Missing component", _xlfn.XLOOKUP(L7, Lookup!A:A, Lookup!D:D, "NA"))) -> Sanyam Agrawal
A8: APC | B8: APC | D8: =IF(E8="","",E8/2) -> 175.5 | E8: =IF(B8="","",SUMIFS($J$2:$J$39,$H$2:$H$39,B8)) -> 351 | F8: {=IF(B8="","",_xlfn.LET( _xlpm.comp, TRIM(CLEAN(B8)), _xlpm.expected, E8, _xlpm.actual, SUMPRODUCT(--(TRIM(CLEAN($H$2:$H$140))=_xlpm.comp), $J$2:$J$140), IF(_xlpm.actual=_xlpm.expected, "No", "Mismatch by " & (_xlpm.actual-_xlpm.expected)) ))} -> No | G8: {=IFERROR(INDEX(_xlfn._xlws.SORT(_xlfn.UNIQUE(_xlfn._xlws.FILTER($L$2:$L$140,$L$2:$L$140<>""))),ROW()-1),"")} -> AMC | H8: =IF(G8="", "", _xlfn.XLOOKUP(G8, 'Component Masterlist v2'!A:A, 'Component Masterlist v2'!P:P, "Not found")) -> AMC | I8: =IF(J8="","",J8/2) -> 45 | J8: =IF(G8="","",SUMIFS($Q$2:$Q$140,$L$2:$L$140,G8)) -> 90 | K8: {=IF(G8="","",_xlfn.LET( _xlpm.comp, TRIM(CLEAN(G8)), _xlpm.expected, J8, _xlpm.actual, SUMPRODUCT(--(TRIM(CLEAN($L$2:$L$140))=_xlpm.comp), $Q$2:$Q$140), IF(_xlpm.actual=_xlpm.expected, "No", "Mismatch by " & (_xlpm.actual-_xlpm.expected)) ))} -> No | L8: =IF(M8="", "", _xlfn.XLOOKUP(M8,'Scrum Teams'!B:B,'Scrum Teams'!A:A,"")) -> AEPlatform | M8: {=IFERROR(INDEX(_xlfn.SORTBY(_xlfn.UNIQUE(_xlfn._xlws.FILTER('Scrum Teams'!$B$2:$B$1006,'Scrum Teams'!$B$2:$B$1006<>"")),_xlfn.XLOOKUP(_xlfn.UNIQUE(_xlfn._xlws.FILTER('Scrum Teams'!$B$2:$B$1006,'Scrum Teams'!$B$2:$B$1006<>"")),'Scrum Teams'!$B:$B,'Scrum Teams'!$A:$A,"")),ROW()-1),"")} -> AEP Chat | N8: =IF(L8="", "", _xlfn.XLOOKUP(L8, 'Component Masterlist v2'!A:A, 'Component Masterlist v2'!P:P, "Not found")) -> AEP | O8: =IF(P8="", "", P8/2) -> 30 | P8: =IF(M8="","",_xlfn.LET( _xlpm.pos, MATCH(M8,'Scrum Teams'!$B$2:$B$1006,0), _xlpm.val, INDEX('Scrum Teams'!$E$2:$E$1006,_xlpm.pos), IF(ISBLANK(INDEX('Scrum Teams'!$E$2:$E$1006,_xlpm.pos)),"",_xlpm.val) )) -> 60 | Q8: =IF(L8="","",IF(P8<>"", P8, 90)) -> 60 | R8: =IF(M8="","",IF(L8="", "Missing component", _xlfn.XLOOKUP(L8, Lookup!A:A, Lookup!D:D, "NA"))) -> Santosh Golecha
A9: APEX | B9: APEX | D9: =IF(E9="","",E9/2) -> 170 | E9: =IF(B9="","",SUMIFS($J$2:$J$39,$H$2:$H$39,B9)) -> 340 | F9: {=IF(B9="","",_xlfn.LET( _xlpm.comp, TRIM(CLEAN(B9)), _xlpm.expected, E9, _xlpm.actual, SUMPRODUCT(--(TRIM(CLEAN($H$2:$H$140))=_xlpm.comp), $J$2:$J$140), IF(_xlpm.actual=_xlpm.expected, "No", "Mismatch by " & (_xlpm.actual-_xlpm.expected)) ))} -> No | G9: {=IFERROR(INDEX(_xlfn._xlws.SORT(_xlfn.UNIQUE(_xlfn._xlws.FILTER($L$2:$L$140,$L$2:$L$140<>""))),ROW()-1),"")} -> Analytics | H9: =IF(G9="", "", _xlfn.XLOOKUP(G9, 'Component Masterlist v2'!A:A, 'Component Masterlist v2'!P:P, "Not found")) -> ANLY | I9: =IF(J9="","",J9/2) -> 112.5 | J9: =IF(G9="","",SUMIFS($Q$2:$Q$140,$L$2:$L$140,G9)) -> 225 | K9: {=IF(G9="","",_xlfn.LET( _xlpm.comp, TRIM(CLEAN(G9)), _xlpm.expected, J9, _xlpm.actual, SUMPRODUCT(--(TRIM(CLEAN($L$2:$L$140))=_xlpm.comp), $Q$2:$Q$140), IF(_xlpm.actual=_xlpm.expected, "No", "Mismatch by " & (_xlpm.actual-_xlpm.expected)) ))} -> No | L9: =IF(M9="", "", _xlfn.XLOOKUP(M9,'Scrum Teams'!B:B,'Scrum Teams'!A:A,"")) -> AEPlatform | M9: {=IFERROR(INDEX(_xlfn.SORTBY(_xlfn.UNIQUE(_xlfn._xlws.FILTER('Scrum Teams'!$B$2:$B$1006,'Scrum Teams'!$B$2:$B$1006<>"")),_xlfn.XLOOKUP(_xlfn.UNIQUE(_xlfn._xlws.FILTER('Scrum Teams'!$B$2:$B$1006,'Scrum Teams'!$B$2:$B$1006<>"")),'Scrum Teams'!$B:$B,'Scrum Teams'!$A:$A,"")),ROW()-1),"")} -> AEP Checkout | N9: =IF(L9="", "", _xlfn.XLOOKUP(L9, 'Component Masterlist v2'!A:A, 'Component Masterlist v2'!P:P, "Not found")) -> AEP | O9: =IF(P9="", "", P9/2) -> 180 | P9: =IF(M9="","",_xlfn.LET( _xlpm.pos, MATCH(M9,'Scrum Teams'!$B$2:$B$1006,0), _xlpm.val, INDEX('Scrum Teams'!$E$2:$E$1006,_xlpm.pos), IF(ISBLANK(INDEX('Scrum Teams'!$E$2:$E$1006,_xlpm.pos)),"",_xlpm.val) )) -> 360 | Q9: =IF(L9="","",IF(P9<>"", P9, 90)) -> 360 | R9: =IF(M9="","",IF(L9="", "Missing component", _xlfn.XLOOKUP(L9, Lookup!A:A, Lookup!D:D, "NA"))) -> Santosh Golecha
A10: ApplicationPlatforms | B10: APLT | D10: =IF(E10="","",E10/2) -> 352 | E10: =IF(B10="","",SUMIFS($J$2:$J$39,$H$2:$H$39,B10)) -> 704 | F10: {=IF(B10="","",_xlfn.LET( _xlpm.comp, TRIM(CLEAN(B10)), _xlpm.expected, E10, _xlpm.actual, SUMPRODUCT(--(TRIM(CLEAN($H$2:$H$140))=_xlpm.comp), $J$2:$J$140), IF(_xlpm.actual=_xlpm.expected, "No", "Mismatch by " & (_xlpm.actual-_xlpm.expected)) ))} -> No | G10: {=IFERROR(INDEX(_xlfn._xlws.SORT(_xlfn.UNIQUE(_xlfn._xlws.FILTER($L$2:$L$140,$L$2:$L$140<>""))),ROW()-1),"")} -> APC | H10: =IF(G10="", "", _xlfn.XLOOKUP(G10, 'Component Masterlist v2'!A:A, 'Component Masterlist v2'!P:P, "Not found")) -> APC | I10: =IF(J10="","",J10/2) -> 175.5 | J10: =IF(G10="","",SUMIFS($Q$2:$Q$140,$L$2:$L$140,G10)) -> 351 | K10: {=IF(G10="","",_xlfn.LET( _xlpm.comp, TRIM(CLEAN(G10)), _xlpm.expected, J10, _xlpm.actual, SUMPRODUCT(--(TRIM(CLEAN($L$2:$L$140))=_xlpm.comp), $Q$2:$Q$140), IF(_xlpm.actual=_xlpm.expected, "No", "Mismatch by " & (_xlpm.actual-_xlpm.expected)) ))} -> No | L10: =IF(M10="", "", _xlfn.XLOOKUP(M10,'Scrum Teams'!B:B,'Scrum Teams'!A:A,"")) -> AEPlatform | M10: {=IFERROR(INDEX(_xlfn.SORTBY(_xlfn.UNIQUE(_xlfn._xlws.FILTER('Scrum Teams'!$B$2:$B$1006,'Scrum Teams'!$B$2:$B$1006<>"")),_xlfn.XLOOKUP(_xlfn.UNIQUE(_xlfn._xlws.FILTER('Scrum Teams'!$B$2:$B$1006,'Scrum Teams'!$B$2:$B$1006<>"")),'Scrum Teams'!$B:$B,'Scrum Teams'!$A:$A,"")),ROW()-1),"")} -> AEP Core | N10: =IF(L10="", "", _xlfn.XLOOKUP(L10, 'Component Masterlist v2'!A:A, 'Component Masterlist v2'!P:P, "Not found")) -> AEP | O10: =IF(P10="", "", P10/2) -> 90 | P10: =IF(M10="","",_xlfn.LET( _xlpm.pos, MATCH(M10,'Scrum Teams'!$B$2:$B$1006,0), _xlpm.val, INDEX('Scrum Teams'!$E$2:$E$1006,_xlpm.pos), IF(ISBLANK(INDEX('Scrum Teams'!$E$2:$E$1006,_xlpm.pos)),"",_xlpm.val) )) -> 180 | Q10: =IF(L10="","",IF(P10<>"", P10, 90)) -> 180 | R10: =IF(M10="","",IF(L10="", "Missing component", _xlfn.XLOOKUP(L10, Lookup!A:A, Lookup!D:D, "NA"))) -> Santosh Golecha
A11: Cashiering | B11: CASH | D11: =IF(E11="","",E11/2) -> 34 | E11: =IF(B11="","",SUMIFS($J$2:$J$39,$H$2:$H$39,B11)) -> 68 | F11: {=IF(B11="","",_xlfn.LET( _xlpm.comp, TRIM(CLEAN(B11)), _xlpm.expected, E11, _xlpm.actual, SUMPRODUCT(--(TRIM(CLEAN($H$2:$H$140))=_xlpm.comp), $J$2:$J$140), IF(_xlpm.actual=_xlpm.expected, "No", "Mismatch by " & (_xlpm.actual-_xlpm.expected)) ))} -> No | G11: {=IFERROR(INDEX(_xlfn._xlws.SORT(_xlfn.UNIQUE(_xlfn._xlws.FILTER($L$2:$L$140,$L$2:$L$140<>""))),ROW()-1),"")} -> APEX | H11: =IF(G11="", "", _xlfn.XLOOKUP(G11, 'Component Masterlist v2'!A:A, 'Component Masterlist v2'!P:P, "Not found")) -> APEX | I11: =IF(J11="","",J11/2) -> 170 | J11: =IF(G11="","",SUMIFS($Q$2:$Q$140,$L$2:$L$140,G11)) -> 340 | K11: {=IF(G11="","",_xlfn.LET( _xlpm.comp, TRIM(CLEAN(G11)), _xlpm.expected, J11, _xlpm.actual, SUMPRODUCT(--(TRIM(CLEAN($L$2:$L$140))=_xlpm.comp), $Q$2:$Q$140), IF(_xlpm.actual=_xlpm.expected, "No", "Mismatch by " & (_xlpm.actual-_xlpm.expected)) ))} -> No | L11: =IF(M11="", "", _xlfn.XLOOKUP(M11,'Scrum Teams'!B:B,'Scrum Teams'!A:A,"")) -> AEPlatform | M11: {=IFERROR(INDEX(_xlfn.SORTBY(_xlfn.UNIQUE(_xlfn._xlws.FILTER('Scrum Teams'!$B$2:$B$1006,'Scrum Teams'!$B$2:$B$1006<>"")),_xlfn.XLOOKUP(_xlfn.UNIQUE(_xlfn._xlws.FILTER('Scrum Teams'!$B$2:$B$1006,'Scrum Teams'!$B$2:$B$1006<>"")),'Scrum Teams'!$B:$B,'Scrum Teams'!$A:$A,"")),ROW()-1),"")} -> AEP Retail | N11: =IF(L11="", "", _xlfn.XLOOKUP(L11, 'Component Masterlist v2'!A:A, 'Component Masterlist v2'!P:P, "Not found")) -> AEP | O11: =IF(P11="", "", P11/2) -> 120 | P11: =IF(M11="","",_xlfn.LET( _xlpm.pos, MATCH(M11,'Scrum Teams'!$B$2:$B$1006,0), _xlpm.val, INDEX('Scrum Teams'!$E$2:$E$1006,_xlpm.pos), IF(ISBLANK(INDEX('Scrum Teams'!$E$2:$E$1006,_xlpm.pos)),"",_xlpm.val) )) -> 240 | Q11: =IF(L11="","",IF(P11<>"", P11, 90)) -> 240 | R11: =IF(M11="","",IF(L11="", "Missing component", _xlfn.XLOOKUP(L11, Lookup!A:A, Lookup!D:D, "NA"))) -> Santosh Golecha
A12: Communication | B12: COMM | D12: =IF(E12="","",E12/2) -> 135 | E12: =IF(B12="","",SUMIFS($J$2:$J$39,$H$2:$H$39,B12)) -> 270 | F12: {=IF(B12="","",_xlfn.LET( _xlpm.comp, TRIM(CLEAN(B12)), _xlpm.expected, E12, _xlpm.actual, SUMPRODUCT(--(TRIM(CLEAN($H$2:$H$140))=_xlpm.comp), $J$2:$J$140), IF(_xlpm.actual=_xlpm.expected, "No", "Mismatch by " & (_xlpm.actual-_xlpm.expected)) ))} -> No | G12: {=IFERROR(INDEX(_xlfn._xlws.SORT(_xlfn.UNIQUE(_xlfn._xlws.FILTER($L$2:$L$140,$L$2:$L$140<>""))),ROW()-1),"")} -> ApplicationPlatforms | H12: =IF(G12="", "", _xlfn.XLOOKUP(G12, 'Component Masterlist v2'!A:A, 'Component Masterlist v2'!P:P, "Not found")) -> APLT | I12: =IF(J12="","",J12/2) -> 352 | J12: =IF(G12="","",SUMIFS($Q$2:$Q$140,$L$2:$L$140,G12)) -> 704 | K12: {=IF(G12="","",_xlfn.LET( _xlpm.comp, TRIM(CLEAN(G12)), _xlpm.expected, J12, _xlpm.actual, SUMPRODUCT(--(TRIM(CLEAN($L$2:$L$140))=_xlpm.comp), $Q$2:$Q$140), IF(_xlpm.actual=_xlpm.expected, "No", "Mismatch by " & (_xlpm.actual-_xlpm.expected)) ))} -> No | L12: =IF(M12="", "", _xlfn.XLOOKUP(M12,'Scrum Teams'!B:B,'Scrum Teams'!A:A,"")) -> AEPlatform | M12: {=IFERROR(INDEX(_xlfn.SORTBY(_xlfn.UNIQUE(_xlfn._xlws.FILTER('Scrum Teams'!$B$2:$B$1006,'Scrum Teams'!$B$2:$B$1006<>"")),_xlfn.XLOOKUP(_xlfn.UNIQUE(_xlfn._xlws.FILTER('Scrum Teams'!$B$2:$B$1006,'Scrum Teams'!$B$2:$B$1006<>"")),'Scrum Teams'!$B:$B,'Scrum Teams'!$A:$A,"")),ROW()-1),"")} -> AEP FnI | N12: =IF(L12="", "", _xlfn.XLOOKUP(L12, 'Component Masterlist v2'!A:A, 'Component Masterlist v2'!P:P, "Not found")) -> AEP | O12: =IF(P12="", "", P12/2) -> 120 | P12: =IF(M12="","",_xlfn.LET( _xlpm.pos, MATCH(M12,'Scrum Teams'!$B$2:$B$1006,0), _xlpm.val, INDEX('Scrum Teams'!$E$2:$E$1006,_xlpm.pos), IF(ISBLANK(INDEX('Scrum Teams'!$E$2:$E$1006,_xlpm.pos)),"",_xlpm.val) )) -> 240 | Q12: =IF(L12="","",IF(P12<>"", P12, 90)) -> 240 | R12: =IF(M12="","",IF(L12="", "Missing component", _xlfn.XLOOKUP(L12, Lookup!A:A, Lookup!D:D, "NA"))) -> Santosh Golecha
A13: CRM | B13: CRM | D13: =IF(E13="","",E13/2) -> 442.5 | E13: =IF(B13="","",SUMIFS($J$2:$J$39,$H$2:$H$39,B13)) -> 885 | F13: {=IF(B13="","",_xlfn.LET( _xlpm.comp, TRIM(CLEAN(B13)), _xlpm.expected, E13, _xlpm.actual, SUMPRODUCT(--(TRIM(CLEAN($H$2:$H$140))=_xlpm.comp), $J$2:$J$140), IF(_xlpm.actual=_xlpm.expected, "No", "Mismatch by " & (_xlpm.actual-_xlpm.expected)) ))} -> No | G13: {=IFERROR(INDEX(_xlfn._xlws.SORT(_xlfn.UNIQUE(_xlfn._xlws.FILTER($L$2:$L$140,$L$2:$L$140<>""))),ROW()-1),"")} -> ARCIntegration | H13: =IF(G13="", "", _xlfn.XLOOKUP(G13, 'Component Masterlist v2'!A:A, 'Component Masterlist v2'!P:P, "Not found")) -> INTG | I13: =IF(J13="","",J13/2) -> 285 | J13: =IF(G13="","",SUMIFS($Q$2:$Q$140,$L$2:$L$140,G13)) -> 570 | K13: {=IF(G13="","",_xlfn.LET( _xlpm.comp, TRIM(CLEAN(G13)), _xlpm.expected, J13, _xlpm.actual, SUMPRODUCT(--(TRIM(CLEAN($L$2:$L$140))=_xlpm.comp), $Q$2:$Q$140), IF(_xlpm.actual=_xlpm.expected, "No", "Mismatch by " & (_xlpm.actual-_xlpm.expected)) ))} -> No | L13: =IF(M13="", "", _xlfn.XLOOKUP(M13,'Scrum Teams'!B:B,'Scrum Teams'!A:A,"")) -> AEPlatform | M13: {=IFERROR(INDEX(_xlfn.SORTBY(_xlfn.UNIQUE(_xlfn._xlws.FILTER('Scrum Teams'!$B$2:$B$1006,'Scrum Teams'!$B$2:$B$1006<>"")),_xlfn.XLOOKUP(_xlfn.UNIQUE(_xlfn._xlws.FILTER('Scrum Teams'!$B$2:$B$1006,'Scrum Teams'!$B$2:$B$1006<>"")),'Scrum Teams'!$B:$B,'Scrum Teams'!$A:$A,"")),ROW()-1),"")} -> AEP Pricing | N13: =IF(L13="", "", _xlfn.XLOOKUP(L13, 'Component Masterlist v2'!A:A, 'Component Masterlist v2'!P:P, "Not found")) -> AEP | O13: =IF(P13="", "", P13/2) -> 105 | P13: =IF(M13="","",_xlfn.LET( _xlpm.pos, MATCH(M13,'Scrum Teams'!$B$2:$B$1006,0), _xlpm.val, INDEX('Scrum Teams'!$E$2:$E$1006,_xlpm.pos), IF(ISBLANK(INDEX('Scrum Teams'!$E$2:$E$1006,_xlpm.pos)),"",_xlpm.val) )) -> 210 | Q13: =IF(L13="","",IF(P13<>"", P13, 90)) -> 210 | R13: =IF(M13="","",IF(L13="", "Missing component", _xlfn.XLOOKUP(L13, Lookup!A:A, Lookup!D:D, "NA"))) -> Santosh Golecha
A14: Data Platform Engineering | B14: DPLT | D14: =IF(E14="","",E14/2) -> 142.5 | E14: =IF(B14="","",SUMIFS($J$2:$J$39,$H$2:$H$39,B14)) -> 285 | F14: {=IF(B14="","",_xlfn.LET( _xlpm.comp, TRIM(CLEAN(B14)), _xlpm.expected, E14, _xlpm.actual, SUMPRODUCT(--(TRIM(CLEAN($H$2:$H$140))=_xlpm.comp), $J$2:$J$140), IF(_xlpm.actual=_xlpm.expected, "No", "Mismatch by " & (_xlpm.actual-_xlpm.expected)) ))} -> No | G14: {=IFERROR(INDEX(_xlfn._xlws.SORT(_xlfn.UNIQUE(_xlfn._xlws.FILTER($L$2:$L$140,$L$2:$L$140<>""))),ROW()-1),"")} -> Campaign | H14: =IF(G14="", "", _xlfn.XLOOKUP(G14, 'Component Masterlist v2'!A:A, 'Component Masterlist v2'!P:P, "Not found")) -> CRM | I14: =IF(J14="","",J14/2) -> 77.5 | J14: =IF(G14="","",SUMIFS($Q$2:$Q$140,$L$2:$L$140,G14)) -> 155 | K14: {=IF(G14="","",_xlfn.LET( _xlpm.comp, TRIM(CLEAN(G14)), _xlpm.expected, J14, _xlpm.actual, SUMPRODUCT(--(TRIM(CLEAN($L$2:$L$140))=_xlpm.comp), $Q$2:$Q$140), IF(_xlpm.actual=_xlpm.expected, "No", "Mismatch by " & (_xlpm.actual-_xlpm.expected)) ))} -> No | L14: =IF(M14="", "", _xlfn.XLOOKUP(M14,'Scrum Teams'!B:B,'Scrum Teams'!A:A,"")) -> AEPlatform | M14: {=IFERROR(INDEX(_xlfn.SORTBY(_xlfn.UNIQUE(_xlfn._xlws.FILTER('Scrum Teams'!$B$2:$B$1006,'Scrum Teams'!$B$2:$B$1006<>"")),_xlfn.XLOOKUP(_xlfn.UNIQUE(_xlfn._xlws.FILTER('Scrum Teams'!$B$2:$B$1006,'Scrum Teams'!$B$2:$B$1006<>"")),'Scrum Teams'!$B:$B,'Scrum Teams'!$A:$A,"")),ROW()-1),"")} -> AEP VI | N14: =IF(L14="", "", _xlfn.XLOOKUP(L14, 'Component Masterlist v2'!A:A, 'Component Masterlist v2'!P:P, "Not found")) -> AEP | O14: =IF(P14="", "", P14/2) -> 120 | P14: =IF(M14="","",_xlfn.LET( _xlpm.pos, MATCH(M14,'Scrum Teams'!$B$2:$B$1006,0), _xlpm.val, INDEX('Scrum Teams'!$E$2:$E$1006,_xlpm.pos), IF(ISBLANK(INDEX('Scrum Teams'!$E$2:$E$1006,_xlpm.pos)),"",_xlpm.val) )) -> 240 | Q14: =IF(L14="","",IF(P14<>"", P14, 90)) -> 240 | R14: =IF(M14="","",IF(L14="", "Missing component", _xlfn.XLOOKUP(L14, Lookup!A:A, Lookup!D:D, "NA"))) -> Santosh Golecha
A15: Onboarding Platforms | B15: OPLT | D15: =IF(E15="","",E15/2) -> 313.5 | E15: =IF(B15="","",SUMIFS($J$2:$J$39,$H$2:$H$39,B15)) -> 627 | F15: {=IF(B15="","",_xlfn.LET( _xlpm.comp, TRIM(CLEAN(B15)), _xlpm.expected, E15, _xlpm.actual, SUMPRODUCT(--(TRIM(CLEAN($H$2:$H$140))=_xlpm.comp), $J$2:$J$140), IF(_xlpm.actual=_xlpm.expected, "No", "Mismatch by " & (_xlpm.actual-_xlpm.expected)) ))} -> No | G15: {=IFERROR(INDEX(_xlfn._xlws.SORT(_xlfn.UNIQUE(_xlfn._xlws.FILTER($L$2:$L$140,$L$2:$L$140<>""))),ROW()-1),"")} -> Cashiering | H15: =IF(G15="", "", _xlfn.XLOOKUP(G15, 'Component Masterlist v2'!A:A, 'Component Masterlist v2'!P:P, "Not found")) -> CASH | I15: =IF(J15="","",J15/2) -> 34 | J15: =IF(G15="","",SUMIFS($Q$2:$Q$140,$L$2:$L$140,G15)) -> 68 | K15: {=IF(G15="","",_xlfn.LET( _xlpm.comp, TRIM(CLEAN(G15)), _xlpm.expected, J15, _xlpm.actual, SUMPRODUCT(--(TRIM(CLEAN($L$2:$L$140))=_xlpm.comp), $Q$2:$Q$140), IF(_xlpm.actual=_xlpm.expected, "No", "Mismatch by " & (_xlpm.actual-_xlpm.expected)) ))} -> No | L15: =IF(M15="", "", _xlfn.XLOOKUP(M15,'Scrum Teams'!B:B,'Scrum Teams'!A:A,"")) -> AI_Core | M15: {=IFERROR(INDEX(_xlfn.SORTBY(_xlfn.UNIQUE(_xlfn._xlws.FILTER('Scrum Teams'!$B$2:$B$1006,'Scrum Teams'!$B$2:$B$1006<>"")),_xlfn.XLOOKUP(_xlfn.UNIQUE(_xlfn._xlws.FILTER('Scrum Teams'!$B$2:$B$1006,'Scrum Teams'!$B$2:$B$1006<>"")),'Scrum Teams'!$B:$B,'Scrum Teams'!$A:$A,"")),ROW()-1),"")} -> AI-Generic | N15: =IF(L15="", "", _xlfn.XLOOKUP(L15, 'Component Masterlist v2'!A:A, 'Component Masterlist v2'!P:P, "Not found")) -> AI | O15: =IF(P15="", "", P15/2) -> 0 | P15: =IF(M15="","",_xlfn.LET( _xlpm.pos, MATCH(M15,'Scrum Teams'!$B$2:$B$1006,0), _xlpm.val, INDEX('Scrum Teams'!$E$2:$E$1006,_xlpm.pos), IF(ISBLANK(INDEX('Scrum Teams'!$E$2:$E$1006,_xlpm.pos)),"",_xlpm.val) )) -> 0 | Q15: =IF(L15="","",IF(P15<>"", P15, 90)) -> 0 | R15: =IF(M15="","",IF(L15="", "Missing component", _xlfn.XLOOKUP(L15, Lookup!A:A, Lookup!D:D, "NA"))) -> Satish Sallakonda
... A19: Galaxy | B19: GAL | D19: =IF(E19="","",E19/2) -> 90 | E19: =IF(B19="","",SUMIFS($J$2:$J$39,$H$2:$H$39,B19)) -> 180 | F19: {=IF(B19="","",_xlfn.LET( _xlpm.comp, TRIM(CLEAN(B19)), _xlpm.expected, E19, _xlpm.actual, SUMPRODUCT(--(TRIM(CLEAN($H$2:$H$140))=_xlpm.comp), $J$2:$J$140), IF(_xlpm.actual=_xlpm.expected, "No", "Mismatch by " & (_xlpm.actual-_xlpm.expected)) ))} -> No | G19: {=IFERROR(INDEX(_xlfn._xlws.SORT(_xlfn.UNIQUE(_xlfn._xlws.FILTER($L$2:$L$140,$L$2:$L$140<>""))),ROW()-1),"")} -> DigitalRetailing | H19: =IF(G19="", "", _xlfn.XLOOKUP(G19, 'Component Masterlist v2'!A:A, 'Component Masterlist v2'!P:P, "Not found")) -> DGRT | I19: =IF(J19="","",J19/2) -> 238.5 | J19: =IF(G19="","",SUMIFS($Q$2:$Q$140,$L$2:$L$140,G19)) -> 477 | K19: {=IF(G19="","",_xlfn.LET( _xlpm.comp, TRIM(CLEAN(G19)), _xlpm.expected, J19, _xlpm.actual, SUMPRODUCT(--(TRIM(CLEAN($L$2:$L$140))=_xlpm.comp), $Q$2:$Q$140), IF(_xlpm.actual=_xlpm.expected, "No", "Mismatch by " & (_xlpm.actual-_xlpm.expected)) ))} -> No | L19: =IF(M19="", "", _xlfn.XLOOKUP(M19,'Scrum Teams'!B:B,'Scrum Teams'!A:A,"")) -> AIBDC | M19: {=IFERROR(INDEX(_xlfn.SORTBY(_xlfn.UNIQUE(_xlfn._xlws.FILTER('Scrum Teams'!$B$2:$B$1006,'Scrum Teams'!$B$2:$B$1006<>"")),_xlfn.XLOOKUP(_xlfn.UNIQUE(_xlfn._xlws.FILTER('Scrum Teams'!$B$2:$B$1006,'Scrum Teams'!$B$2:$B$1006<>"")),'Scrum Teams'!$B:$B,'Scrum Teams'!$A:$A,"")),ROW()-1),"")} -> AIBDC | N19: =IF(L19="", "", _xlfn.XLOOKUP(L19, 'Component Masterlist v2'!A:A, 'Component Masterlist v2'!P:P, "Not found")) -> AIB | O19: =IF(P19="", "", P19/2) -> 87.5 | P19: =IF(M19="","",_xlfn.LET( _xlpm.pos, MATCH(M19,'Scrum Teams'!$B$2:$B$1006,0), _xlpm.val, INDEX('Scrum Teams'!$E$2:$E$1006,_xlpm.pos), IF(ISBLANK(INDEX('Scrum Teams'!$E$2:$E$1006,_xlpm.pos)),"",_xlpm.val) )) -> 175 | Q19: =IF(L19="","",IF(P19<>"", P19, 90)) -> 175 | R19: =IF(M19="","",IF(L19="", "Missing component", _xlfn.XLOOKUP(L19, Lookup!A:A, Lookup!D:D, "NA"))) -> Ved Singh
A20: GM | B20: GM | D20: =IF(E20="","",E20/2) -> 1500 | E20: =IF(B20="","",SUMIFS($J$2:$J$39,$H$2:$H$39,B20)) -> 3000 | F20: {=IF(B20="","",_xlfn.LET( _xlpm.comp, TRIM(CLEAN(B20)), _xlpm.expected, E20, _xlpm.actual, SUMPRODUCT(--(TRIM(CLEAN($H$2:$H$140))=_xlpm.comp), $J$2:$J$140), IF(_xlpm.actual=_xlpm.expected, "No", "Mismatch by " & (_xlpm.actual-_xlpm.expected)) ))} -> No | G20: {=IFERROR(INDEX(_xlfn._xlws.SORT(_xlfn.UNIQUE(_xlfn._xlws.FILTER($L$2:$L$140,$L$2:$L$140<>""))),ROW()-1),"")} -> DR_GM | H20: =IF(G20="", "", _xlfn.XLOOKUP(G20, 'Component Masterlist v2'!A:A, 'Component Masterlist v2'!P:P, "Not found")) -> GM | I20: 1500 | J20: 3000 | K20: {=IF(G20="","",_xlfn.LET( _xlpm.comp, TRIM(CLEAN(G20)), _xlpm.expected, J20, _xlpm.actual, SUMPRODUCT(--(TRIM(CLEAN($L$2:$L$140))=_xlpm.comp), $Q$2:$Q$140), IF(_xlpm.actual=_xlpm.expected, "No", "Mismatch by " & (_xlpm.actual-_xlpm.expected)) ))} -> Mismatch by -1635 | L20: =IF(M20="", "", _xlfn.XLOOKUP(M20,'Scrum Teams'!B:B,'Scrum Teams'!A:A,"")) -> AIE_Core | M20: {=IFERROR(INDEX(_xlfn.SORTBY(_xlfn.UNIQUE(_xlfn._xlws.FILTER('Scrum Teams'!$B$2:$B$1006,'Scrum Teams'!$B$2:$B$1006<>"")),_xlfn.XLOOKUP(_xlfn.UNIQUE(_xlfn._xlws.FILTER('Scrum Teams'!$B$2:$B$1006,'Scrum Teams'!$B$2:$B$1006<>"")),'Scrum Teams'!$B:$B,'Scrum Teams'!$A:$A,"")),ROW()-1),"")} -> AIE-Generic | N20: =IF(L20="", "", _xlfn.XLOOKUP(L20, 'Component Masterlist v2'!A:A, 'Component Masterlist v2'!P:P, "Not found")) -> AIPL | O20: =IF(P20="", "", P20/2) -> 22.5 | P20: =IF(M20="","",_xlfn.LET( _xlpm.pos, MATCH(M20,'Scrum Teams'!$B$2:$B$1006,0), _xlpm.val, INDEX('Scrum Teams'!$E$2:$E$1006,_xlpm.pos), IF(ISBLANK(INDEX('Scrum Teams'!$E$2:$E$1006,_xlpm.pos)),"",_xlpm.val) )) -> 45 | Q20: =IF(L20="","",IF(P20<>"", P20, 90)) -> 45 | R20: =IF(M20="","",IF(L20="", "Missing component", _xlfn.XLOOKUP(L20, Lookup!A:A, Lookup!D:D, "NA"))) -> Satish Sallakonda
A21: Honda AHM | B21: AHM | D21: =IF(E21="","",E21/2) -> 670.5 | E21: =IF(B21="","",SUMIFS($J$2:$J$39,$H$2:$H$39,B21)) -> 1341 | F21: {=IF(B21="","",_xlfn.LET( _xlpm.comp, TRIM(CLEAN(B21)), _xlpm.expected, E21, _xlpm.actual, SUMPRODUCT(--(TRIM(CLEAN($H$2:$H$140))=_xlpm.comp), $J$2:$J$140), IF(_xlpm.actual=_xlpm.expected, "No", "Mismatch by " & (_xlpm.actual-_xlpm.expected)) ))} -> No | G21: {=IFERROR(INDEX(_xlfn._xlws.SORT(_xlfn.UNIQUE(_xlfn._xlws.FILTER($L$2:$L$140,$L$2:$L$140<>""))),ROW()-1),"")} -> DR_Honda | H21: =IF(G21="", "", _xlfn.XLOOKUP(G21, 'Component Masterlist v2'!A:A, 'Component Masterlist v2'!P:P, "Not found")) -> AHM | I21: 305.5 | J21: 611 | K21: {=IF(G21="","",_xlfn.LET( _xlpm.comp, TRIM(CLEAN(G21)), _xlpm.expected, J21, _xlpm.actual, SUMPRODUCT(--(TRIM(CLEAN($L$2:$L$140))=_xlpm.comp), $Q$2:$Q$140), IF(_xlpm.actual=_xlpm.expected, "No", "Mismatch by " & (_xlpm.actual-_xlpm.expected)) ))} -> Mismatch by -288 | L21: =IF(M21="", "", _xlfn.XLOOKUP(M21,'Scrum Teams'!B:B,'Scrum Teams'!A:A,"")) -> AIE_Core | M21: {=IFERROR(INDEX(_xlfn.SORTBY(_xlfn.UNIQUE(_xlfn._xlws.FILTER('Scrum Teams'!$B$2:$B$1006,'Scrum Teams'!$B$2:$B$1006<>"")),_xlfn.XLOOKUP(_xlfn.UNIQUE(_xlfn._xlws.FILTER('Scrum Teams'!$B$2:$B$1006,'Scrum Teams'!$B$2:$B$1006<>"")),'Scrum Teams'!$B:$B,'Scrum Teams'!$A:$A,"")),ROW()-1),"")} -> AIE-Retail | N21: =IF(L21="", "", _xlfn.XLOOKUP(L21, 'Component Masterlist v2'!A:A, 'Component Masterlist v2'!P:P, "Not found")) -> AIPL | O21: =IF(P21="", "", P21/2) -> 22.5 | P21: =IF(M21="","",_xlfn.LET( _xlpm.pos, MATCH(M21,'Scrum Teams'!$B$2:$B$1006,0), _xlpm.val, INDEX('Scrum Teams'!$E$2:$E$1006,_xlpm.pos), IF(ISBLANK(INDEX('Scrum Teams'!$E$2:$E$1006,_xlpm.pos)),"",_xlpm.val) )) -> 45 | Q21: =IF(L21="","",IF(P21<>"", P21, 90)) -> 45 | R21: =IF(M21="","",IF(L21="", "Missing component", _xlfn.XLOOKUP(L21, Lookup!A:A, Lookup!D:D, "NA"))) -> Satish Sallakonda
A22: Hyundai | B22: HYUN | D22: =IF(E22="","",E22/2) -> 45 | E22: =IF(B22="","",SUMIFS($J$2:$J$39,$H$2:$H$39,B22)) -> 90 | F22: {=IF(B22="","",_xlfn.LET( _xlpm.comp, TRIM(CLEAN(B22)), _xlpm.expected, E22, _xlpm.actual, SUMPRODUCT(--(TRIM(CLEAN($H$2:$H$140))=_xlpm.comp), $J$2:$J$140), IF(_xlpm.actual=_xlpm.expected, "No", "Mismatch by " & (_xlpm.actual-_xlpm.expected)) ))} -> No | G22: {=IFERROR(INDEX(_xlfn._xlws.SORT(_xlfn.UNIQUE(_xlfn._xlws.FILTER($L$2:$L$140,$L$2:$L$140<>""))),ROW()-1),"")} -> DR_Hyundai | H22: =IF(G22="", "", _xlfn.XLOOKUP(G22, 'Component Masterlist v2'!A:A, 'Component Masterlist v2'!P:P, "Not found")) -> HYUN | I22: =IF(J22="","",J22/2) -> 45 | J22: =IF(G22="","",SUMIFS($Q$2:$Q$140,$L$2:$L$140,G22)) -> 90 | K22: {=IF(G22="","",_xlfn.LET( _xlpm.comp, TRIM(CLEAN(G22)), _xlpm.expected, J22, _xlpm.actual, SUMPRODUCT(--(TRIM(CLEAN($L$2:$L$140))=_xlpm.comp), $Q$2:$Q$140), IF(_xlpm.actual=_xlpm.expected, "No", "Mismatch by " & (_xlpm.actual-_xlpm.expected)) ))} -> No | L22: =IF(M22="", "", _xlfn.XLOOKUP(M22,'Scrum Teams'!B:B,'Scrum Teams'!A:A,"")) -> AIE_Core | M22: {=IFERROR(INDEX(_xlfn.SORTBY(_xlfn.UNIQUE(_xlfn._xlws.FILTER('Scrum Teams'!$B$2:$B$1006,'Scrum Teams'!$B$2:$B$1006<>"")),_xlfn.XLOOKUP(_xlfn.UNIQUE(_xlfn._xlws.FILTER('Scrum Teams'!$B$2:$B$1006,'Scrum Teams'!$B$2:$B$1006<>"")),'Scrum Teams'!$B:$B,'Scrum Teams'!$A:$A,"")),ROW()-1),"")} -> AIE-Service | N22: =IF(L22="", "", _xlfn.XLOOKUP(L22, 'Component Masterlist v2'!A:A, 'Component Masterlist v2'!P:P, "Not found")) -> AIPL | O22: =IF(P22="", "", P22/2) -> 22.5 | P22: =IF(M22="","",_xlfn.LET( _xlpm.pos, MATCH(M22,'Scrum Teams'!$B$2:$B$1006,0), _xlpm.val, INDEX('Scrum Teams'!$E$2:$E$1006,_xlpm.pos), IF(ISBLANK(INDEX('Scrum Teams'!$E$2:$E$1006,_xlpm.pos)),"",_xlpm.val) )) -> 45 | Q22: =IF(L22="","",IF(P22<>"", P22, 90)) -> 45 | R22: =IF(M22="","",IF(L22="", "Missing component", _xlfn.XLOOKUP(L22, Lookup!A:A, Lookup!D:D, "NA"))) -> Satish Sallakonda
A23: Integration | B23: INTG | D23: =IF(E23="","",E23/2) -> 285 | E23: =IF(B23="","",SUMIFS($J$2:$J$39,$H$2:$H$39,B23)) -> 570 | F23: {=IF(B23="","",_xlfn.LET( _xlpm.comp, TRIM(CLEAN(B23)), _xlpm.expected, E23, _xlpm.actual, SUMPRODUCT(--(TRIM(CLEAN($H$2:$H$140))=_xlpm.comp), $J$2:$J$140), IF(_xlpm.actual=_xlpm.expected, "No", "Mismatch by " & (_xlpm.actual-_xlpm.expected)) ))} -> No | G23: {=IFERROR(INDEX(_xlfn._xlws.SORT(_xlfn.UNIQUE(_xlfn._xlws.FILTER($L$2:$L$140,$L$2:$L$140<>""))),ROW()-1),"")} -> eSign_Platform | H23: =IF(G23="", "", _xlfn.XLOOKUP(G23, 'Component Masterlist v2'!A:A, 'Component Masterlist v2'!P:P, "Not found")) -> ESGN | I23: =IF(J23="","",J23/2) -> 44 | J23: =IF(G23="","",SUMIFS($Q$2:$Q$140,$L$2:$L$140,G23)) -> 88 | K23: {=IF(G23="","",_xlfn.LET( _xlpm.comp, TRIM(CLEAN(G23)), _xlpm.expected, J23, _xlpm.actual, SUMPRODUCT(--(TRIM(CLEAN($L$2:$L$140))=_xlpm.comp), $Q$2:$Q$140), IF(_xlpm.actual=_xlpm.expected, "No", "Mismatch by " & (_xlpm.actual-_xlpm.expected)) ))} -> No | L23: =IF(M23="", "", _xlfn.XLOOKUP(M23,'Scrum Teams'!B:B,'Scrum Teams'!A:A,"")) -> AIE_Platform | M23: {=IFERROR(INDEX(_xlfn.SORTBY(_xlfn.UNIQUE(_xlfn._xlws.FILTER('Scrum Teams'!$B$2:$B$1006,'Scrum Teams'!$B$2:$B$1006<>"")),_xlfn.XLOOKUP(_xlfn.UNIQUE(_xlfn._xlws.FILTER('Scrum Teams'!$B$2:$B$1006,'Scrum Teams'!$B$2:$B$1006<>"")),'Scrum Teams'!$B:$B,'Scrum Teams'!$A:$A,"")),ROW()-1),"")} -> AIE_Platform | N23: =IF(L23="", "", _xlfn.XLOOKUP(L23, 'Component Masterlist v2'!A:A, 'Component Masterlist v2'!P:P, "Not found")) -> AIPL | O23: =IF(P23="", "", P23/2) -> 45 | P23: =IF(M23="","",_xlfn.LET( _xlpm.pos, MATCH(M23,'Scrum Teams'!$B$2:$B$1006,0), _xlpm.val, INDEX('Scrum Teams'!$E$2:$E$1006,_xlpm.pos), IF(ISBLANK(INDEX('Scrum Teams'!$E$2:$E$1006,_xlpm.pos)),"",_xlpm.val) )) -> 90 | Q23: =IF(L23="","",IF(P23<>"", P23, 90)) -> 90 | R23: =IF(M23="","",IF(L23="", "Missing component", _xlfn.XLOOKUP(L23, Lookup!A:A, Lookup!D:D, "NA"))) -> Satish Sallakonda
A24: IOT Engg | B24: IOT | D24: =IF(E24="","",E24/2) -> 45 | E24: =IF(B24="","",SUMIFS($J$2:$J$39,$H$2:$H$39,B24)) -> 90 | F24: {=IF(B24="","",_xlfn.LET( _xlpm.comp, TRIM(CLEAN(B24)), _xlpm.expected, E24, _xlpm.actual, SUMPRODUCT(--(TRIM(CLEAN($H$2:$H$140))=_xlpm.comp), $J$2:$J$140), IF(_xlpm.actual=_xlpm.expected, "No", "Mismatch by " & (_xlpm.actual-_xlpm.expected)) ))} -> No | G24: {=IFERROR(INDEX(_xlfn._xlws.SORT(_xlfn.UNIQUE(_xlfn._xlws.FILTER($L$2:$L$140,$L$2:$L$140<>""))),ROW()-1),"")} -> Fleet_Honda | H24: =IF(G24="", "", _xlfn.XLOOKUP(G24, 'Component Masterlist v2'!A:A, 'Component Masterlist v2'!P:P, "Not found")) -> AHM | I24: 365 | J24: 730 | K24: {=IF(G24="","",_xlfn.LET( _xlpm.comp, TRIM(CLEAN(G24)), _xlpm.expected, J24, _xlpm.actual, SUMPRODUCT(--(TRIM(CLEAN($L$2:$L$140))=_xlpm.comp), $Q$2:$Q$140), IF(_xlpm.actual=_xlpm.expected, "No", "Mismatch by " & (_xlpm.actual-_xlpm.expected)) ))} -> Mismatch by -488 | L24: =IF(M24="", "", _xlfn.XLOOKUP(M24,'Scrum Teams'!B:B,'Scrum Teams'!A:A,"")) -> AMC | M24: {=IFERROR(INDEX(_xlfn.SORTBY(_xlfn.UNIQUE(_xlfn._xlws.FILTER('Scrum Teams'!$B$2:$B$1006,'Scrum Teams'!$B$2:$B$1006<>"")),_xlfn.XLOOKUP(_xlfn.UNIQUE(_xlfn._xlws.FILTER('Scrum Teams'!$B$2:$B$1006,'Scrum Teams'!$B$2:$B$1006<>"")),'Scrum Teams'!$B:$B,'Scrum Teams'!$A:$A,"")),ROW()-1),"")} -> AMC | N24: =IF(L24="", "", _xlfn.XLOOKUP(L24, 'Component Masterlist v2'!A:A, 'Component Masterlist v2'!P:P, "Not found")) -> AMC | O24: =IF(P24="", "", P24/2) | P24: =IF(M24="","",_xlfn.LET( _xlpm.pos, MATCH(M24,'Scrum Teams'!$B$2:$B$1006,0), _xlpm.val, INDEX('Scrum Teams'!$E$2:$E$1006,_xlpm.pos), IF(ISBLANK(INDEX('Scrum Teams'!$E$2:$E$1006,_xlpm.pos)),"",_xlpm.val) )) | Q24: =IF(L24="","",IF(P24<>"", P24, 90)) -> 90 | R24: =IF(M24="","",IF(L24="", "Missing component", _xlfn.XLOOKUP(L24, Lookup!A:A, Lookup!D:D, "NA"))) -> Santosh Golecha
A25: Orbit | B25: ORBT | D25: =IF(E25="","",E25/2) -> 85 | E25: =IF(B25="","",SUMIFS($J$2:$J$39,$H$2:$H$39,B25)) -> 170 | F25: {=IF(B25="","",_xlfn.LET( _xlpm.comp, TRIM(CLEAN(B25)), _xlpm.expected, E25, _xlpm.actual, SUMPRODUCT(--(TRIM(CLEAN($H$2:$H$140))=_xlpm.comp), $J$2:$J$140), IF(_xlpm.actual=_xlpm.expected, "No", "Mismatch by " & (_xlpm.actual-_xlpm.expected)) ))} -> No | G25: {=IFERROR(INDEX(_xlfn._xlws.SORT(_xlfn.UNIQUE(_xlfn._xlws.FILTER($L$2:$L$140,$L$2:$L$140<>""))),ROW()-1),"")} -> FnI | H25: =IF(G25="", "", _xlfn.XLOOKUP(G25, 'Component Masterlist v2'!A:A, 'Component Masterlist v2'!P:P, "Not found")) -> FNI | I25: =IF(J25="","",J25/2) -> 368 | J25: =IF(G25="","",SUMIFS($Q$2:$Q$140,$L$2:$L$140,G25)) -> 736 | K25: {=IF(G25="","",_xlfn.LET( _xlpm.comp, TRIM(CLEAN(G25)), _xlpm.expected, J25, _xlpm.actual, SUMPRODUCT(--(TRIM(CLEAN($L$2:$L$140))=_xlpm.comp), $Q$2:$Q$140), IF(_xlpm.actual=_xlpm.expected, "No", "Mismatch by " & (_xlpm.actual-_xlpm.expected)) ))} -> No | L25: =IF(M25="", "", _xlfn.XLOOKUP(M25,'Scrum Teams'!B:B,'Scrum Teams'!A:A,"")) -> Analytics | M25: {=IFERROR(INDEX(_xlfn.SORTBY(_xlfn.UNIQUE(_xlfn._xlws.FILTER('Scrum Teams'!$B$2:$B$1006,'Scrum Teams'!$B$2:$B$1006<>"")),_xlfn.XLOOKUP(_xlfn.UNIQUE(_xlfn._xlws.FILTER('Scrum Teams'!$B$2:$B$1006,'Scrum Teams'!$B$2:$B$1006<>"")),'Scrum Teams'!$B:$B,'Scrum Teams'!$A:$A,"")),ROW()-1),"")} -> Analytics-Eng | N25: =IF(L25="", "", _xlfn.XLOOKUP(L25, 'Component Masterlist v2'!A:A, 'Component Masterlist v2'!P:P, "Not found")) -> ANLY | O25: =IF(P25="", "", P25/2) -> 112.5 | P25: =IF(M25="","",_xlfn.LET( _xlpm.pos, MATCH(M25,'Scrum Teams'!$B$2:$B$1006,0), _xlpm.val, INDEX('Scrum Teams'!$E$2:$E$1006,_xlpm.pos), IF(ISBLANK(INDEX('Scrum Teams'!$E$2:$E$1006,_xlpm.pos)),"",_xlpm.val) )) -> 225 | Q25: =IF(L25="","",IF(P25<>"", P25, 90)) -> 225 | R25: =IF(M25="","",IF(L25="", "Missing component", _xlfn.XLOOKUP(L25, Lookup!A:A, Lookup!D:D, "NA"))) -> Satish Sallakonda
A26: Parts | B26: PART | D26: =IF(E26="","",E26/2) -> 336 | E26: =IF(B26="","",SUMIFS($J$2:$J$39,$H$2:$H$39,B26)) -> 672 | F26: {=IF(B26="","",_xlfn.LET( _xlpm.comp, TRIM(CLEAN(B26)), _xlpm.expected, E26, _xlpm.actual, SUMPRODUCT(--(TRIM(CLEAN($H$2:$H$140))=_xlpm.comp), $J$2:$J$140), IF(_xlpm.actual=_xlpm.expected, "No", "Mismatch by " & (_xlpm.actual-_xlpm.expected)) ))} -> No | G26: {=IFERROR(INDEX(_xlfn._xlws.SORT(_xlfn.UNIQUE(_xlfn._xlws.FILTER($L$2:$L$140,$L$2:$L$140<>""))),ROW()-1),"")} -> Galaxy | H26: =IF(G26="", "", _xlfn.XLOOKUP(G26, 'Component Masterlist v2'!A:A, 'Component Masterlist v2'!P:P, "Not found")) -> GAL | I26: =IF(J26="","",J26/2) -> 90 | J26: =IF(G26="","",SUMIFS($Q$2:$Q$140,$L$2:$L$140,G26)) -> 180 | K26: {=IF(G26="","",_xlfn.LET( _xlpm.comp, TRIM(CLEAN(G26)), _xlpm.expected, J26, _xlpm.actual, SUMPRODUCT(--(TRIM(CLEAN($L$2:$L$140))=_xlpm.comp), $Q$2:$Q$140), IF(_xlpm.actual=_xlpm.expected, "No", "Mismatch by " & (_xlpm.actual-_xlpm.expected)) ))} -> No | L26: =IF(M26="", "", _xlfn.XLOOKUP(M26,'Scrum Teams'!B:B,'Scrum Teams'!A:A,"")) -> APC | M26: {=IFERROR(INDEX(_xlfn.SORTBY(_xlfn.UNIQUE(_xlfn._xlws.FILTER('Scrum Teams'!$B$2:$B$1006,'Scrum Teams'!$B$2:$B$1006<>"")),_xlfn.XLOOKUP(_xlfn.UNIQUE(_xlfn._xlws.FILTER('Scrum Teams'!$B$2:$B$1006,'Scrum Teams'!$B$2:$B$1006<>"")),'Scrum Teams'!$B:$B,'Scrum Teams'!$A:$A,"")),ROW()-1),"")} -> IEX | N26: =IF(L26="", "", _xlfn.XLOOKUP(L26, 'Component Masterlist v2'!A:A, 'Component Masterlist v2'!P:P, "Not found")) -> APC | O26: =IF(P26="", "", P26/2) -> 49.5 | P26: =IF(M26="","",_xlfn.LET( _xlpm.pos, MATCH(M26,'Scrum Teams'!$B$2:$B$1006,0), _xlpm.val, INDEX('Scrum Teams'!$E$2:$E$1006,_xlpm.pos), IF(ISBLANK(INDEX('Scrum Teams'!$E$2:$E$1006,_xlpm.pos)),"",_xlpm.val) )) -> 99 | Q26: =IF(L26="","",IF(P26<>"", P26, 90)) -> 99 | R26: =IF(M26="","",IF(L26="", "Missing component", _xlfn.XLOOKUP(L26, Lookup!A:A, Lookup!D:D, "NA"))) -> Keith Wiseman
A27: Payroll | B27: PYRL | D27: =IF(E27="","",E27/2) -> 70 | E27: =IF(B27="","",SUMIFS($J$2:$J$39,$H$2:$H$39,B27)) -> 140 | F27: {=IF(B27="","",_xlfn.LET( _xlpm.comp, TRIM(CLEAN(B27)), _xlpm.expected, E27, _xlpm.actual, SUMPRODUCT(--(TRIM(CLEAN($H$2:$H$140))=_xlpm.comp), $J$2:$J$140), IF(_xlpm.actual=_xlpm.expected, "No", "Mismatch by " & (_xlpm.actual-_xlpm.expected)) ))} -> No | G27: {=IFERROR(INDEX(_xlfn._xlws.SORT(_xlfn.UNIQUE(_xlfn._xlws.FILTER($L$2:$L$140,$L$2:$L$140<>""))),ROW()-1),"")} -> HorizontalPlatforms | H27: =IF(G27="", "", _xlfn.XLOOKUP(G27, 'Component Masterlist v2'!A:A, 'Component Masterlist v2'!P:P, "Not found")) -> HPLT | I27: =IF(J27="","",J27/2) -> 195 | J27: =IF(G27="","",SUMIFS($Q$2:$Q$140,$L$2:$L$140,G27)) -> 390 | K27: {=IF(G27="","",_xlfn.LET( _xlpm.comp, TRIM(CLEAN(G27)), _xlpm.expected, J27, _xlpm.actual, SUMPRODUCT(--(TRIM(CLEAN($L$2:$L$140))=_xlpm.comp), $Q$2:$Q$140), IF(_xlpm.actual=_xlpm.expected, "No", "Mismatch by " & (_xlpm.actual-_xlpm.expected)) ))} -> No | L27: =IF(M27="", "", _xlfn.XLOOKUP(M27,'Scrum Teams'!B:B,'Scrum Teams'!A:A,"")) -> APC | M27: {=IFERROR(INDEX(_xlfn.SORTBY(_xlfn.UNIQUE(_xlfn._xlws.FILTER('Scrum Teams'!$B$2:$B$1006,'Scrum Teams'!$B$2:$B$1006<>"")),_xlfn.XLOOKUP(_xlfn.UNIQUE(_xlfn._xlws.FILTER('Scrum Teams'!$B$2:$B$1006,'Scrum Teams'!$B$2:$B$1006<>"")),'Scrum Teams'!$B:$B,'Scrum Teams'!$A:$A,"")),ROW()-1),"")} -> PEX | N27: =IF(L27="", "", _xlfn.XLOOKUP(L27, 'Component Masterlist v2'!A:A, 'Component Masterlist v2'!P:P, "Not found")) -> APC | O27: =IF(P27="", "", P27/2) -> 58.5 | P27: =IF(M27="","",_xlfn.LET( _xlpm.pos, MATCH(M27,'Scrum Teams'!$B$2:$B$1006,0), _xlpm.val, INDEX('Scrum Teams'!$E$2:$E$1006,_xlpm.pos), IF(ISBLANK(INDEX('Scrum Teams'!$E$2:$E$1006,_xlpm.pos)),"",_xlpm.val) )) -> 117 | Q27: =IF(L27="","",IF(P27<>"", P27, 90)) -> 117 | R27: =IF(M27="","",IF(L27="", "Missing component", _xlfn.XLOOKUP(L27, Lookup!A:A, Lookup!D:D, "NA"))) -> Keith Wiseman
A28: PayTek | B28: PYTK | D28: =IF(E28="","",E28/2) -> 170 | E28: =IF(B28="","",SUMIFS($J$2:$J$39,$H$2:$H$39,B28)) -> 340 | F28: {=IF(B28="","",_xlfn.LET( _xlpm.comp, TRIM(CLEAN(B28)), _xlpm.expected, E28, _xlpm.actual, SUMPRODUCT(--(TRIM(CLEAN($H$2:$H$140))=_xlpm.comp), $J$2:$J$140), IF(_xlpm.actual=_xlpm.expected, "No", "Mismatch by " & (_xlpm.actual-_xlpm.expected)) ))} -> No | G28: {=IFERROR(INDEX(_xlfn._xlws.SORT(_xlfn.UNIQUE(_xlfn._xlws.FILTER($L$2:$L$140,$L$2:$L$140<>""))),ROW()-1),"")} -> IOT | H28: =IF(G28="", "", _xlfn.XLOOKUP(G28, 'Component Masterlist v2'!A:A, 'Component Masterlist v2'!P:P, "Not found")) -> IOT | I28: =IF(J28="","",J28/2) -> 45 | J28: =IF(G28="","",SUMIFS($Q$2:$Q$140,$L$2:$L$140,G28)) -> 90 | K28: {=IF(G28="","",_xlfn.LET( _xlpm.comp, TRIM(CLEAN(G28)), _xlpm.expected, J28, _xlpm.actual, SUMPRODUCT(--(TRIM(CLEAN($L$2:$L$140))=_xlpm.comp), $Q$2:$Q$140), IF(_xlpm.actual=_xlpm.expected, "No", "Mismatch by " & (_xlpm.actual-_xlpm.expected)) ))} -> No | L28: =IF(M28="", "", _xlfn.XLOOKUP(M28,'Scrum Teams'!B:B,'Scrum Teams'!A:A,"")) -> APC | M28: {=IFERROR(INDEX(_xlfn.SORTBY(_xlfn.UNIQUE(_xlfn._xlws.FILTER('Scrum Teams'!$B$2:$B$1006,'Scrum Teams'!$B$2:$B$1006<>"")),_xlfn.XLOOKUP(_xlfn.UNIQUE(_xlfn._xlws.FILTER('Scrum Teams'!$B$2:$B$1006,'Scrum Teams'!$B$2:$B$1006<>"")),'Scrum Teams'!$B:$B,'Scrum Teams'!$A:$A,"")),ROW()-1),"")} -> Cortex | N28: =IF(L28="", "", _xlfn.XLOOKUP(L28, 'Component Masterlist v2'!A:A, 'Component Masterlist v2'!P:P, "Not found")) -> APC | O28: =IF(P28="", "", P28/2) -> 67.5 | P28: =IF(M28="","",_xlfn.LET( _xlpm.pos, MATCH(M28,'Scrum Teams'!$B$2:$B$1006,0), _xlpm.val, INDEX('Scrum Teams'!$E$2:$E$1006,_xlpm.pos), IF(ISBLANK(INDEX('Scrum Teams'!$E$2:$E$1006,_xlpm.pos)),"",_xlpm.val) )) -> 135 | Q28: =IF(L28="","",IF(P28<>"", P28, 90)) -> 135 | R28: =IF(M28="","",IF(L28="", "Missing component", _xlfn.XLOOKUP(L28, Lookup!A:A, Lookup!D:D, "NA"))) -> Keith Wiseman
A29: Horizontal Platforms | B29: HPLT | D29: =IF(E29="","",E29/2) -> 195 | E29: =IF(B29="","",SUMIFS($J$2:$J$39,$H$2:$H$39,B29)) -> 390 | F29: {=IF(B29="","",_xlfn.LET( _xlpm.comp, TRIM(CLEAN(B29)), _xlpm.expected, E29, _xlpm.actual, SUMPRODUCT(--(TRIM(CLEAN($H$2:$H$140))=_xlpm.comp), $J$2:$J$140), IF(_xlpm.actual=_xlpm.expected, "No", "Mismatch by " & (_xlpm.actual-_xlpm.expected)) ))} -> No | G29: {=IFERROR(INDEX(_xlfn._xlws.SORT(_xlfn.UNIQUE(_xlfn._xlws.FILTER($L$2:$L$140,$L$2:$L$140<>""))),ROW()-1),"")} -> OnboardingPlatforms | H29: =IF(G29="", "", _xlfn.XLOOKUP(G29, 'Component Masterlist v2'!A:A, 'Component Masterlist v2'!P:P, "Not found")) -> OPLT | I29: =IF(J29="","",J29/2) -> 313.5 | J29: =IF(G29="","",SUMIFS($Q$2:$Q$140,$L$2:$L$140,G29)) -> 627 | K29: {=IF(G29="","",_xlfn.LET( _xlpm.comp, TRIM(CLEAN(G29)), _xlpm.expected, J29, _xlpm.actual, SUMPRODUCT(--(TRIM(CLEAN($L$2:$L$140))=_xlpm.comp), $Q$2:$Q$140), IF(_xlpm.actual=_xlpm.expected, "No", "Mismatch by " & (_xlpm.actual-_xlpm.expected)) ))} -> No | L29: =IF(M29="", "", _xlfn.XLOOKUP(M29,'Scrum Teams'!B:B,'Scrum Teams'!A:A,"")) -> APEX | M29: {=IFERROR(INDEX(_xlfn.SORTBY(_xlfn.UNIQUE(_xlfn._xlws.FILTER('Scrum Teams'!$B$2:$B$1006,'Scrum Teams'!$B$2:$B$1006<>"")),_xlfn.XLOOKUP(_xlfn.UNIQUE(_xlfn._xlws.FILTER('Scrum Teams'!$B$2:$B$1006,'Scrum Teams'!$B$2:$B$1006<>"")),'Scrum Teams'!$B:$B,'Scrum Teams'!$A:$A,"")),ROW()-1),"")} -> R3, LD & Automation | N29: =IF(L29="", "", _xlfn.XLOOKUP(L29, 'Component Masterlist v2'!A:A, 'Component Masterlist v2'!P:P, "Not found")) -> APEX | O29: =IF(P29="", "", P29/2) -> 50 | P29: =IF(M29="","",_xlfn.LET( _xlpm.pos, MATCH(M29,'Scrum Teams'!$B$2:$B$1006,0), _xlpm.val, INDEX('Scrum Teams'!$E$2:$E$1006,_xlpm.pos), IF(ISBLANK(INDEX('Scrum Teams'!$E$2:$E$1006,_xlpm.pos)),"",_xlpm.val) )) -> 100 | Q29: =IF(L29="","",IF(P29<>"", P29, 90)) -> 100 | R29: =IF(M29="","",IF(L29="", "Missing component", _xlfn.XLOOKUP(L29, Lookup!A:A, Lookup!D:D, "NA"))) -> Satish Sallakonda
A30: Retail | B30: RETL | D30: =IF(E30="","",E30/2) -> 505 | E30: =IF(B30="","",SUMIFS($J$2:$J$39,$H$2:$H$39,B30)) -> 1010 | F30: {=IF(B30="","",_xlfn.LET( _xlpm.comp, TRIM(CLEAN(B30)), _xlpm.expected, E30, _xlpm.actual, SUMPRODUCT(--(TRIM(CLEAN($H$2:$H$140))=_xlpm.comp), $J$2:$J$140), IF(_xlpm.actual=_xlpm.expected, "No", "Mismatch by " & (_xlpm.actual-_xlpm.expected)) ))} -> No | G30: {=IFERROR(INDEX(_xlfn._xlws.SORT(_xlfn.UNIQUE(_xlfn._xlws.FILTER($L$2:$L$140,$L$2:$L$140<>""))),ROW()-1),"")} -> ORBIT | H30: =IF(G30="", "", _xlfn.XLOOKUP(G30, 'Component Masterlist v2'!A:A, 'Component Masterlist v2'!P:P, "Not found")) -> ORBT | I30: =IF(J30="","",J30/2) -> 85 | J30: =IF(G30="","",SUMIFS($Q$2:$Q$140,$L$2:$L$140,G30)) -> 170 | K30: {=IF(G30="","",_xlfn.LET( _xlpm.comp, TRIM(CLEAN(G30)), _xlpm.expected, J30, _xlpm.actual, SUMPRODUCT(--(TRIM(CLEAN($L$2:$L$140))=_xlpm.comp), $Q$2:$Q$140), IF(_xlpm.actual=_xlpm.expected, "No", "Mismatch by " & (_xlpm.actual-_xlpm.expected)) ))} -> No | L30: =IF(M30="", "", _xlfn.XLOOKUP(M30,'Scrum Teams'!B:B,'Scrum Teams'!A:A,"")) -> APEX | M30: {=IFERROR(INDEX(_xlfn.SORTBY(_xlfn.UNIQUE(_xlfn._xlws.FILTER('Scrum Teams'!$B$2:$B$1006,'Scrum Teams'!$B$2:$B$1006<>"")),_xlfn.XLOOKUP(_xlfn.UNIQUE(_xlfn._xlws.FILTER('Scrum Teams'!$B$2:$B$1006,'Scrum Teams'!$B$2:$B$1006<>"")),'Scrum Teams'!$B:$B,'Scrum Teams'!$A:$A,"")),ROW()-1),"")} -> SCP | N30: =IF(L30="", "", _xlfn.XLOOKUP(L30, 'Component Masterlist v2'!A:A, 'Component Masterlist v2'!P:P, "Not found")) -> APEX | O30: =IF(P30="", "", P30/2) -> 30 | P30: =IF(M30="","",_xlfn.LET( _xlpm.pos, MATCH(M30,'Scrum Teams'!$B$2:$B$1006,0), _xlpm.val, INDEX('Scrum Teams'!$E$2:$E$1006,_xlpm.pos), IF(ISBLANK(INDEX('Scrum Teams'!$E$2:$E$1006,_xlpm.pos)),"",_xlpm.val) )) -> 60 | Q30: =IF(L30="","",IF(P30<>"", P30, 90)) -> 60 | R30: =IF(M30="","",IF(L30="", "Missing component", _xlfn.XLOOKUP(L30, Lookup!A:A, Lookup!D:D, "NA"))) -> Satish Sallakonda
A31: Service | B31: SERV | D31: =IF(E31="","",E31/2) -> 405 | E31: =IF(B31="","",SUMIFS($J$2:$J$39,$H$2:$H$39,B31)) -> 810 | F31: {=IF(B31="","",_xlfn.LET( _xlpm.comp, TRIM(CLEAN(B31)), _xlpm.expected, E31, _xlpm.actual, SUMPRODUCT(--(TRIM(CLEAN($H$2:$H$140))=_xlpm.comp), $J$2:$J$140), IF(_xlpm.actual=_xlpm.expected, "No", "Mismatch by " & (_xlpm.actual-_xlpm.expected)) ))} -> No | G31: {=IFERROR(INDEX(_xlfn._xlws.SORT(_xlfn.UNIQUE(_xlfn._xlws.FILTER($L$2:$L$140,$L$2:$L$140<>""))),ROW()-1),"")} -> Parts | H31: =IF(G31="", "", _xlfn.XLOOKUP(G31, 'Component Masterlist v2'!A:A, 'Component Masterlist v2'!P:P, "Not found")) -> PART | I31: =IF(J31="","",J31/2) -> 336 | J31: =IF(G31="","",SUMIFS($Q$2:$Q$140,$L$2:$L$140,G31)) -> 672 | K31: {=IF(G31="","",_xlfn.LET( _xlpm.comp, TRIM(CLEAN(G31)), _xlpm.expected, J31, _xlpm.actual, SUMPRODUCT(--(TRIM(CLEAN($L$2:$L$140))=_xlpm.comp), $Q$2:$Q$140), IF(_xlpm.actual=_xlpm.expected, "No", "Mismatch by " & (_xlpm.actual-_xlpm.expected)) ))} -> No | L31: =IF(M31="", "", _xlfn.XLOOKUP(M31,'Scrum Teams'!B:B,'Scrum Teams'!A:A,"")) -> APEX | M31: {=IFERROR(INDEX(_xlfn.SORTBY(_xlfn.UNIQUE(_xlfn._xlws.FILTER('Scrum Teams'!$B$2:$B$1006,'Scrum Teams'!$B$2:$B$1006<>"")),_xlfn.XLOOKUP(_xlfn.UNIQUE(_xlfn._xlws.FILTER('Scrum Teams'!$B$2:$B$1006,'Scrum Teams'!$B$2:$B$1006<>"")),'Scrum Teams'!$B:$B,'Scrum Teams'!$A:$A,"")),ROW()-1),"")} -> Tax & Fee | N31: =IF(L31="", "", _xlfn.XLOOKUP(L31, 'Component Masterlist v2'!A:A, 'Component Masterlist v2'!P:P, "Not found")) -> APEX | O31: =IF(P31="", "", P31/2) -> 30 | P31: =IF(M31="","",_xlfn.LET( _xlpm.pos, MATCH(M31,'Scrum Teams'!$B$2:$B$1006,0), _xlpm.val, INDEX('Scrum Teams'!$E$2:$E$1006,_xlpm.pos), IF(ISBLANK(INDEX('Scrum Teams'!$E$2:$E$1006,_xlpm.pos)),"",_xlpm.val) )) -> 60 | Q31: =IF(L31="","",IF(P31<>"", P31, 90)) -> 60 | R31: =IF(M31="","",IF(L31="", "Missing component", _xlfn.XLOOKUP(L31, Lookup!A:A, Lookup!D:D, "NA"))) -> Satish Sallakonda
A32: SI Platform | B32: SIP | D32: =IF(E32="","",E32/2) -> 79.5 | E32: =IF(B32="","",SUMIFS($J$2:$J$39,$H$2:$H$39,B32)) -> 159 | F32: {=IF(B32="","",_xlfn.LET( _xlpm.comp, TRIM(CLEAN(B32)), _xlpm.expected, E32, _xlpm.actual, SUMPRODUCT(--(TRIM(CLEAN($H$2:$H$140))=_xlpm.comp), $J$2:$J$140), IF(_xlpm.actual=_xlpm.expected, "No", "Mismatch by " & (_xlpm.actual-_xlpm.expected)) ))} -> No | G32: {=IFERROR(INDEX(_xlfn._xlws.SORT(_xlfn.UNIQUE(_xlfn._xlws.FILTER($L$2:$L$140,$L$2:$L$140<>""))),ROW()-1),"")} -> Payroll | H32: =IF(G32="", "", _xlfn.XLOOKUP(G32, 'Component Masterlist v2'!A:A, 'Component Masterlist v2'!P:P, "Not found")) -> PYRL | I32: =IF(J32="","",J32/2) -> 70 | J32: =IF(G32="","",SUMIFS($Q$2:$Q$140,$L$2:$L$140,G32)) -> 140 | K32: {=IF(G32="","",_xlfn.LET( _xlpm.comp, TRIM(CLEAN(G32)), _xlpm.expected, J32, _xlpm.actual, SUMPRODUCT(--(TRIM(CLEAN($L$2:$L$140))=_xlpm.comp), $Q$2:$Q$140), IF(_xlpm.actual=_xlpm.expected, "No", "Mismatch by " & (_xlpm.actual-_xlpm.expected)) ))} -> No | L32: =IF(M32="", "", _xlfn.XLOOKUP(M32,'Scrum Teams'!B:B,'Scrum Teams'!A:A,"")) -> APEX | M32: {=IFERROR(INDEX(_xlfn.SORTBY(_xlfn.UNIQUE(_xlfn._xlws.FILTER('Scrum Teams'!$B$2:$B$1006,'Scrum Teams'!$B$2:$B$1006<>"")),_xlfn.XLOOKUP(_xlfn.UNIQUE(_xlfn._xlws.FILTER('Scrum Teams'!$B$2:$B$1006,'Scrum Teams'!$B$2:$B$1006<>"")),'Scrum Teams'!$B:$B,'Scrum Teams'!$A:$A,"")),ROW()-1),"")} -> VDP & Rewrite | N32: =IF(L32="", "", _xlfn.XLOOKUP(L32, 'Component Masterlist v2'!A:A, 'Component Masterlist v2'!P:P, "Not found")) -> APEX | O32: =IF(P32="", "", P32/2) -> 60 | P32: =IF(M32="","",_xlfn.LET( _xlpm.pos, MATCH(M32,'Scrum Teams'!$B$2:$B$1006,0), _xlpm.val, INDEX('Scrum Teams'!$E$2:$E$1006,_xlpm.pos), IF(ISBLANK(INDEX('Scrum Teams'!$E$2:$E$1006,_xlpm.pos)),"",_xlpm.val) )) -> 120 | Q32: =IF(L32="","",IF(P32<>"", P32, 90)) -> 120 | R32: =IF(M32="","",IF(L32="", "Missing component", _xlfn.XLOOKUP(L32, Lookup!A:A, Lookup!D:D, "NA"))) -> Satish Sallakonda
A33: T1Platform | B33: T1PL | D33: =IF(E33="","",E33/2) -> 60 | E33: =IF(B33="","",SUMIFS($J$2:$J$39,$H$2:$H$39,B33)) -> 120 | F33: {=IF(B33="","",_xlfn.LET( _xlpm.comp, TRIM(CLEAN(B33)), _xlpm.expected, E33, _xlpm.actual, SUMPRODUCT(--(TRIM(CLEAN($H$2:$H$140))=_xlpm.comp), $J$2:$J$140), IF(_xlpm.actual=_xlpm.expected, "No", "Mismatch by " & (_xlpm.actual-_xlpm.expected)) ))} -> No | G33: {=IFERROR(INDEX(_xlfn._xlws.SORT(_xlfn.UNIQUE(_xlfn._xlws.FILTER($L$2:$L$140,$L$2:$L$140<>""))),ROW()-1),"")} -> PayTek | H33: =IF(G33="", "", _xlfn.XLOOKUP(G33, 'Component Masterlist v2'!A:A, 'Component Masterlist v2'!P:P, "Not found")) -> PYTK | I33: =IF(J33="","",J33/2) -> 170 | J33: =IF(G33="","",SUMIFS($Q$2:$Q$140,$L$2:$L$140,G33)) -> 340 | K33: {=IF(G33="","",_xlfn.LET( _xlpm.comp, TRIM(CLEAN(G33)), _xlpm.expected, J33, _xlpm.actual, SUMPRODUCT(--(TRIM(CLEAN($L$2:$L$140))=_xlpm.comp), $Q$2:$Q$140), IF(_xlpm.actual=_xlpm.expected, "No", "Mismatch by " & (_xlpm.actual-_xlpm.expected)) ))} -> No | L33: =IF(M33="", "", _xlfn.XLOOKUP(M33,'Scrum Teams'!B:B,'Scrum Teams'!A:A,"")) -> ApplicationPlatforms | M33: {=IFERROR(INDEX(_xlfn.SORTBY(_xlfn.UNIQUE(_xlfn._xlws.FILTER('Scrum Teams'!$B$2:$B$1006,'Scrum Teams'!$B$2:$B$1006<>"")),_xlfn.XLOOKUP(_xlfn.UNIQUE(_xlfn._xlws.FILTER('Scrum Teams'!$B$2:$B$1006,'Scrum Teams'!$B$2:$B$1006<>"")),'Scrum Teams'!$B:$B,'Scrum Teams'!$A:$A,"")),ROW()-1),"")} -> Audit & Approval | N33: =IF(L33="", "", _xlfn.XLOOKUP(L33, 'Component Masterlist v2'!A:A, 'Component Masterlist v2'!P:P, "Not found")) -> APLT | O33: =IF(P33="", "", P33/2) -> 44 | P33: =IF(M33="","",_xlfn.LET( _xlpm.pos, MATCH(M33,'Scrum Teams'!$B$2:$B$1006,0), _xlpm.val, INDEX('Scrum Teams'!$E$2:$E$1006,_xlpm.pos), IF(ISBLANK(INDEX('Scrum Teams'!$E$2:$E$1006,_xlpm.pos)),"",_xlpm.val) )) -> 88 | Q33: =IF(L33="","",IF(P33<>"", P33, 90)) -> 88 | R33: =IF(M33="","",IF(L33="", "Missing component", _xlfn.XLOOKUP(L33, Lookup!A:A, Lookup!D:D, "NA"))) -> Keith Wiseman
A34: ZEBRA | B34: ZEB | D34: =IF(E34="","",E34/2) -> 77 | E34: =IF(B34="","",SUMIFS($J$2:$J$39,$H$2:$H$39,B34)) -> 154 | F34: {=IF(B34="","",_xlfn.LET( _xlpm.comp, TRIM(CLEAN(B34)), _xlpm.expected, E34, _xlpm.actual, SUMPRODUCT(--(TRIM(CLEAN($H$2:$H$140))=_xlpm.comp), $J$2:$J$140), IF(_xlpm.actual=_xlpm.expected, "No", "Mismatch by " & (_xlpm.actual-_xlpm.expected)) ))} -> No | G34: {=IFERROR(INDEX(_xlfn._xlws.SORT(_xlfn.UNIQUE(_xlfn._xlws.FILTER($L$2:$L$140,$L$2:$L$140<>""))),ROW()-1),"")} -> Retail | H34: =IF(G34="", "", _xlfn.XLOOKUP(G34, 'Component Masterlist v2'!A:A, 'Component Masterlist v2'!P:P, "Not found")) -> RETL | I34: =IF(J34="","",J34/2) -> 505 | J34: =IF(G34="","",SUMIFS($Q$2:$Q$140,$L$2:$L$140,G34)) -> 1010 | K34: {=IF(G34="","",_xlfn.LET( _xlpm.comp, TRIM(CLEAN(G34)), _xlpm.expected, J34, _xlpm.actual, SUMPRODUCT(--(TRIM(CLEAN($L$2:$L$140))=_xlpm.comp), $Q$2:$Q$140), IF(_xlpm.actual=_xlpm.expected, "No", "Mismatch by " & (_xlpm.actual-_xlpm.expected)) ))} -> No | L34: =IF(M34="", "", _xlfn.XLOOKUP(M34,'Scrum Teams'!B:B,'Scrum Teams'!A:A,"")) -> ApplicationPlatforms | M34: {=IFERROR(INDEX(_xlfn.SORTBY(_xlfn.UNIQUE(_xlfn._xlws.FILTER('Scrum Teams'!$B$2:$B$1006,'Scrum Teams'!$B$2:$B$1006<>"")),_xlfn.XLOOKUP(_xlfn.UNIQUE(_xlfn._xlws.FILTER('Scrum Teams'!$B$2:$B$1006,'Scrum Teams'!$B$2:$B$1006<>"")),'Scrum Teams'!$B:$B,'Scrum Teams'!$A:$A,"")),ROW()-1),"")} -> Compliance | N34: =IF(L34="", "", _xlfn.XLOOKUP(L34, 'Component Masterlist v2'!A:A, 'Component Masterlist v2'!P:P, "Not found")) -> APLT | O34: =IF(P34="", "", P34/2) -> 33 | P34: =IF(M34="","",_xlfn.LET( _xlpm.pos, MATCH(M34,'Scrum Teams'!$B$2:$B$1006,0), _xlpm.val, INDEX('Scrum Teams'!$E$2:$E$1006,_xlpm.pos), IF(ISBLANK(INDEX('Scrum Teams'!$E$2:$E$1006,_xlpm.pos)),"",_xlpm.val) )) -> 66 | Q34: =IF(L34="","",IF(P34<>"", P34, 90)) -> 66 | R34: =IF(M34="","",IF(L34="", "Missing component", _xlfn.XLOOKUP(L34, Lookup!A:A, Lookup!D:D, "NA"))) -> Keith Wiseman
G35: {=IFERROR(INDEX(_xlfn._xlws.SORT(_xlfn.UNIQUE(_xlfn._xlws.FILTER($L$2:$L$140,$L$2:$L$140<>""))),ROW()-1),"")} -> Service | H35: =IF(G35="", "", _xlfn.XLOOKUP(G35, 'Component Masterlist v2'!A:A, 'Component Masterlist v2'!P:P, "Not found")) -> SERV | I35: =IF(J35="","",J35/2) -> 405 | J35: =IF(G35="","",SUMIFS($Q$2:$Q$140,$L$2:$L$140,G35)) -> 810 | K35: {=IF(G35="","",_xlfn.LET( _xlpm.comp, TRIM(CLEAN(G35)), _xlpm.expected, J35, _xlpm.actual, SUMPRODUCT(--(TRIM(CLEAN($L$2:$L$140))=_xlpm.comp), $Q$2:$Q$140), IF(_xlpm.actual=_xlpm.expected, "No", "Mismatch by " & (_xlpm.actual-_xlpm.expected)) ))} -> No | L35: =IF(M35="", "", _xlfn.XLOOKUP(M35,'Scrum Teams'!B:B,'Scrum Teams'!A:A,"")) -> ApplicationPlatforms | M35: {=IFERROR(INDEX(_xlfn.SORTBY(_xlfn.UNIQUE(_xlfn._xlws.FILTER('Scrum Teams'!$B$2:$B$1006,'Scrum Teams'!$B$2:$B$1006<>"")),_xlfn.XLOOKUP(_xlfn.UNIQUE(_xlfn._xlws.FILTER('Scrum Teams'!$B$2:$B$1006,'Scrum Teams'!$B$2:$B$1006<>"")),'Scrum Teams'!$B:$B,'Scrum Teams'!$A:$A,"")),ROW()-1),"")} -> Configuration Studio | N35: =IF(L35="", "", _xlfn.XLOOKUP(L35, 'Component Masterlist v2'!A:A, 'Component Masterlist v2'!P:P, "Not found")) -> APLT | O35: =IF(P35="", "", P35/2) -> 55 | P35: =IF(M35="","",_xlfn.LET( _xlpm.pos, MATCH(M35,'Scrum Teams'!$B$2:$B$1006,0), _xlpm.val, INDEX('Scrum Teams'!$E$2:$E$1006,_xlpm.pos), IF(ISBLANK(INDEX('Scrum Teams'!$E$2:$E$1006,_xlpm.pos)),"",_xlpm.val) )) -> 110 | Q35: =IF(L35="","",IF(P35<>"", P35, 90)) -> 110 | R35: =IF(M35="","",IF(L35="", "Missing component", _xlfn.XLOOKUP(L35, Lookup!A:A, Lookup!D:D, "NA"))) -> Keith Wiseman
A36: Grand Total | D36: =SUM(D2:D34) -> 8546 | E36: =SUM(E2:E34) -> 17092 | G36: {=IFERROR(INDEX(_xlfn._xlws.SORT(_xlfn.UNIQUE(_xlfn._xlws.FILTER($L$2:$L$140,$L$2:$L$140<>""))),ROW()-1),"")} -> SIPlatform | H36: =IF(G36="", "", _xlfn.XLOOKUP(G36, 'Component Masterlist v2'!A:A, 'Component Masterlist v2'!P:P, "Not found")) -> SIP | I36: =IF(J36="","",J36/2) -> 79.5 | J36: =IF(G36="","",SUMIFS($Q$2:$Q$140,$L$2:$L$140,G36)) -> 159 | K36: {=IF(G36="","",_xlfn.LET( _xlpm.comp, TRIM(CLEAN(G36)), _xlpm.expected, J36, _xlpm.actual, SUMPRODUCT(--(TRIM(CLEAN($L$2:$L$140))=_xlpm.comp), $Q$2:$Q$140), IF(_xlpm.actual=_xlpm.expected, "No", "Mismatch by " & (_xlpm.actual-_xlpm.expected)) ))} -> No | L36: =IF(M36="", "", _xlfn.XLOOKUP(M36,'Scrum Teams'!B:B,'Scrum Teams'!A:A,"")) -> ApplicationPlatforms | M36: {=IFERROR(INDEX(_xlfn.SORTBY(_xlfn.UNIQUE(_xlfn._xlws.FILTER('Scrum Teams'!$B$2:$B$1006,'Scrum Teams'!$B$2:$B$1006<>"")),_xlfn.XLOOKUP(_xlfn.UNIQUE(_xlfn._xlws.FILTER('Scrum Teams'!$B$2:$B$1006,'Scrum Teams'!$B$2:$B$1006<>"")),'Scrum Teams'!$B:$B,'Scrum Teams'!$A:$A,"")),ROW()-1),"")} -> Enterprise | N36: =IF(L36="", "", _xlfn.XLOOKUP(L36, 'Component Masterlist v2'!A:A, 'Component Masterlist v2'!P:P, "Not found")) -> APLT | O36: =IF(P36="", "", P36/2) -> 82.5 | P36: =IF(M36="","",_xlfn.LET( _xlpm.pos, MATCH(M36,'Scrum Teams'!$B$2:$B$1006,0), _xlpm.val, INDEX('Scrum Teams'!$E$2:$E$1006,_xlpm.pos), IF(ISBLANK(INDEX('Scrum Teams'!$E$2:$E$1006,_xlpm.pos)),"",_xlpm.val) )) -> 165 | Q36: =IF(L36="","",IF(P36<>"", P36, 90)) -> 165 | R36: =IF(M36="","",IF(L36="", "Missing component", _xlfn.XLOOKUP(L36, Lookup!A:A, Lookup!D:D, "NA"))) -> Keith Wiseman | T36: Campaign | U36: 38 | V36: 40 | W36: 0 | X36: 26
G37: {=IFERROR(INDEX(_xlfn._xlws.SORT(_xlfn.UNIQUE(_xlfn._xlws.FILTER($L$2:$L$140,$L$2:$L$140<>""))),ROW()-1),"")} -> T1Platform | H37: =IF(G37="", "", _xlfn.XLOOKUP(G37, 'Component Masterlist v2'!A:A, 'Component Masterlist v2'!P:P, "Not found")) -> T1PL | I37: =IF(J37="","",J37/2) -> 60 | J37: =IF(G37="","",SUMIFS($Q$2:$Q$140,$L$2:$L$140,G37)) -> 120 | K37: {=IF(G37="","",_xlfn.LET( _xlpm.comp, TRIM(CLEAN(G37)), _xlpm.expected, J37, _xlpm.actual, SUMPRODUCT(--(TRIM(CLEAN($L$2:$L$140))=_xlpm.comp), $Q$2:$Q$140), IF(_xlpm.actual=_xlpm.expected, "No", "Mismatch by " & (_xlpm.actual-_xlpm.expected)) ))} -> No | L37: =IF(M37="", "", _xlfn.XLOOKUP(M37,'Scrum Teams'!B:B,'Scrum Teams'!A:A,"")) -> ApplicationPlatforms | M37: {=IFERROR(INDEX(_xlfn.SORTBY(_xlfn.UNIQUE(_xlfn._xlws.FILTER('Scrum Teams'!$B$2:$B$1006,'Scrum Teams'!$B$2:$B$1006<>"")),_xlfn.XLOOKUP(_xlfn.UNIQUE(_xlfn._xlws.FILTER('Scrum Teams'!$B$2:$B$1006,'Scrum Teams'!$B$2:$B$1006<>"")),'Scrum Teams'!$B:$B,'Scrum Teams'!$A:$A,"")),ROW()-1),"")} -> Identity Management | N37: =IF(L37="", "", _xlfn.XLOOKUP(L37, 'Component Masterlist v2'!A:A, 'Component Masterlist v2'!P:P, "Not found")) -> APLT | O37: =IF(P37="", "", P37/2) -> 44 | P37: =IF(M37="","",_xlfn.LET( _xlpm.pos, MATCH(M37,'Scrum Teams'!$B$2:$B$1006,0), _xlpm.val, INDEX('Scrum Teams'!$E$2:$E$1006,_xlpm.pos), IF(ISBLANK(INDEX('Scrum Teams'!$E$2:$E$1006,_xlpm.pos)),"",_xlpm.val) )) -> 88 | Q37: =IF(L37="","",IF(P37<>"", P37, 90)) -> 88 | R37: =IF(M37="","",IF(L37="", "Missing component", _xlfn.XLOOKUP(L37, Lookup!A:A, Lookup!D:D, "NA"))) -> Keith Wiseman | T37: Cashiering | U37: 95 | V37: 0 | W37: 10 | X37: 35
G38: {=IFERROR(INDEX(_xlfn._xlws.SORT(_xlfn.UNIQUE(_xlfn._xlws.FILTER($L$2:$L$140,$L$2:$L$140<>""))),ROW()-1),"")} -> ZEBRA | H38: =IF(G38="", "", _xlfn.XLOOKUP(G38, 'Component Masterlist v2'!A:A, 'Component Masterlist v2'!P:P, "Not found")) -> ZEB | I38: =IF(J38="","",J38/2) -> 77 | J38: =IF(G38="","",SUMIFS($Q$2:$Q$140,$L$2:$L$140,G38)) -> 154 | K38: {=IF(G38="","",_xlfn.LET( _xlpm.comp, TRIM(CLEAN(G38)), _xlpm.expected, J38, _xlpm.actual, SUMPRODUCT(--(TRIM(CLEAN($L$2:$L$140))=_xlpm.comp), $Q$2:$Q$140), IF(_xlpm.actual=_xlpm.expected, "No", "Mismatch by " & (_xlpm.actual-_xlpm.expected)) ))} -> No | L38: =IF(M38="", "", _xlfn.XLOOKUP(M38,'Scrum Teams'!B:B,'Scrum Teams'!A:A,"")) -> ApplicationPlatforms | M38: {=IFERROR(INDEX(_xlfn.SORTBY(_xlfn.UNIQUE(_xlfn._xlws.FILTER('Scrum Teams'!$B$2:$B$1006,'Scrum Teams'!$B$2:$B$1006<>"")),_xlfn.XLOOKUP(_xlfn.UNIQUE(_xlfn._xlws.FILTER('Scrum Teams'!$B$2:$B$1006,'Scrum Teams'!$B$2:$B$1006<>"")),'Scrum Teams'!$B:$B,'Scrum Teams'!$A:$A,"")),ROW()-1),"")} -> Printers & Scanners | N38: =IF(L38="", "", _xlfn.XLOOKUP(L38, 'Component Masterlist v2'!A:A, 'Component Masterlist v2'!P:P, "Not found")) -> APLT | O38: =IF(P38="", "", P38/2) -> 38.5 | P38: =IF(M38="","",_xlfn.LET( _xlpm.pos, MATCH(M38,'Scrum Teams'!$B$2:$B$1006,0), _xlpm.val, INDEX('Scrum Teams'!$E$2:$E$1006,_xlpm.pos), IF(ISBLANK(INDEX('Scrum Teams'!$E$2:$E$1006,_xlpm.pos)),"",_xlpm.val) )) -> 77 | Q38: =IF(L38="","",IF(P38<>"", P38, 90)) -> 77 | R38: =IF(M38="","",IF(L38="", "Missing component", _xlfn.XLOOKUP(L38, Lookup!A:A, Lookup!D:D, "NA"))) -> Keith Wiseman | T38: CMS | U38: 14 | V38: 8 | W38: 0 | X38: 7.3333333
G39: {=IFERROR(INDEX(_xlfn._xlws.SORT(_xlfn.UNIQUE(_xlfn._xlws.FILTER($L$2:$L$140,$L$2:$L$140<>""))),ROW()-1),"")} | H39: =IF(G39="", "", _xlfn.XLOOKUP(G39, 'Component Masterlist v2'!A:A, 'Component Masterlist v2'!P:P, "Not found")) | I39: =IF(J39="","",J39/2) | J39: =IF(G39="","",SUMIFS($Q$2:$Q$140,$L$2:$L$140,G39)) | L39: =IF(M39="", "", _xlfn.XLOOKUP(M39,'Scrum Teams'!B:B,'Scrum Teams'!A:A,"")) -> ApplicationPlatforms | M39: {=IFERROR(INDEX(_xlfn.SORTBY(_xlfn.UNIQUE(_xlfn._xlws.FILTER('Scrum Teams'!$B$2:$B$1006,'Scrum Teams'!$B$2:$B$1006<>"")),_xlfn.XLOOKUP(_xlfn.UNIQUE(_xlfn._xlws.FILTER('Scrum Teams'!$B$2:$B$1006,'Scrum Teams'!$B$2:$B$1006<>"")),'Scrum Teams'!$B:$B,'Scrum Teams'!$A:$A,"")),ROW()-1),"")} -> Workflow Engine | N39: =IF(L39="", "", _xlfn.XLOOKUP(L39, 'Component Masterlist v2'!A:A, 'Component Masterlist v2'!P:P, "Not found")) -> APLT | O39: =IF(P39="", "", P39/2) -> 55 | P39: =IF(M39="","",_xlfn.LET( _xlpm.pos, MATCH(M39,'Scrum Teams'!$B$2:$B$1006,0), _xlpm.val, INDEX('Scrum Teams'!$E$2:$E$1006,_xlpm.pos), IF(ISBLANK(INDEX('Scrum Teams'!$E$2:$E$1006,_xlpm.pos)),"",_xlpm.val) )) -> 110 | Q39: =IF(L39="","",IF(P39<>"", P39, 90)) -> 110 | R39: =IF(M39="","",IF(L39="", "Missing component", _xlfn.XLOOKUP(L39, Lookup!A:A, Lookup!D:D, "NA"))) -> Keith Wiseman
G40: Grand Total | I40: =SUM($I$2:$I$38) -> 8591 | J40: =SUM($J$2:$J$38) -> 17182 | K40: {=IF(G40="","",_xlfn.LET( _xlpm.comp, TRIM(CLEAN(G40)), _xlpm.expected, J40, _xlpm.actual, SUMPRODUCT(--(TRIM(CLEAN($L$2:$L$152))=_xlpm.comp), $Q$2:$Q$152), IF(_xlpm.actual=_xlpm.expected, "No", "Mismatch by " & (_xlpm.actual-_xlpm.expected)) ))} -> Mismatch by -2411 | L40: =IF(M40="", "", _xlfn.XLOOKUP(M40,'Scrum Teams'!B:B,'Scrum Teams'!A:A,"")) -> ARCIntegration | M40: {=IFERROR(INDEX(_xlfn.SORTBY(_xlfn.UNIQUE(_xlfn._xlws.FILTER('Scrum Teams'!$B$2:$B$1006,'Scrum Teams'!$B$2:$B$1006<>"")),_xlfn.XLOOKUP(_xlfn.UNIQUE(_xlfn._xlws.FILTER('Scrum Teams'!$B$2:$B$1006,'Scrum Teams'!$B$2:$B$1006<>"")),'Scrum Teams'!$B:$B,'Scrum Teams'!$A:$A,"")),ROW()-1),"")} -> Credit & FNI Integrations | N40: =IF(L40="", "", _xlfn.XLOOKUP(L40, 'Component Masterlist v2'!A:A, 'Component Masterlist v2'!P:P, "Not found")) -> INTG | O40: =IF(P40="", "", P40/2) -> 45 | P40: =IF(M40="","",_xlfn.LET( _xlpm.pos, MATCH(M40,'Scrum Teams'!$B$2:$B$1006,0), _xlpm.val, INDEX('Scrum Teams'!$E$2:$E$1006,_xlpm.pos), IF(ISBLANK(INDEX('Scrum Teams'!$E$2:$E$1006,_xlpm.pos)),"",_xlpm.val) )) -> 90 | Q40: =IF(L40="","",IF(P40<>"", P40, 90)) -> 90 | R40: =IF(M40="","",IF(L40="", "Missing component", _xlfn.XLOOKUP(L40, Lookup!A:A, Lookup!D:D, "NA"))) -> Turker Coskun
K41: {=IF(G41="","",_xlfn.LET( _xlpm.comp, TRIM(CLEAN(G41)), _xlpm.expected, J41, _xlpm.actual, SUMPRODUCT(--(TRIM(CLEAN($L$2:$L$140))=_xlpm.comp), $Q$2:$Q$140), IF(_xlpm.actual=_xlpm.expected, "No", "Mismatch by " & (_xlpm.actual-_xlpm.expected)) ))} | L41: =IF(M41="", "", _xlfn.XLOOKUP(M41,'Scrum Teams'!B:B,'Scrum Teams'!A:A,"")) -> ARCIntegration | M41: {=IFERROR(INDEX(_xlfn.SORTBY(_xlfn.UNIQUE(_xlfn._xlws.FILTER('Scrum Teams'!$B$2:$B$1006,'Scrum Teams'!$B$2:$B$1006<>"")),_xlfn.XLOOKUP(_xlfn.UNIQUE(_xlfn._xlws.FILTER('Scrum Teams'!$B$2:$B$1006,'Scrum Teams'!$B$2:$B$1006<>"")),'Scrum Teams'!$B:$B,'Scrum Teams'!$A:$A,"")),ROW()-1),"")} -> FixedOps Integration 1 | N41: =IF(L41="", "", _xlfn.XLOOKUP(L41, 'Component Masterlist v2'!A:A, 'Component Masterlist v2'!P:P, "Not found")) -> INTG | O41: =IF(P41="", "", P41/2) -> 45 | P41: =IF(M41="","",_xlfn.LET( _xlpm.pos, MATCH(M41,'Scrum Teams'!$B$2:$B$1006,0), _xlpm.val, INDEX('Scrum Teams'!$E$2:$E$1006,_xlpm.pos), IF(ISBLANK(INDEX('Scrum Teams'!$E$2:$E$1006,_xlpm.pos)),"",_xlpm.val) )) -> 90 | Q41: =IF(L41="","",IF(P41<>"", P41, 90)) -> 90 | R41: =IF(M41="","",IF(L41="", "Missing component", _xlfn.XLOOKUP(L41, Lookup!A:A, Lookup!D:D, "NA"))) -> Turker Coskun
K42: {=IF(G42="","",_xlfn.LET( _xlpm.comp, TRIM(CLEAN(G42)), _xlpm.expected, J42, _xlpm.actual, SUMPRODUCT(--(TRIM(CLEAN($L$2:$L$140))=_xlpm.comp), $Q$2:$Q$140), IF(_xlpm.actual=_xlpm.expected, "No", "Mismatch by " & (_xlpm.actual-_xlpm.expected)) ))} | L42: =IF(M42="", "", _xlfn.XLOOKUP(M42,'Scrum Teams'!B:B,'Scrum Teams'!A:A,"")) -> ARCIntegration | M42: {=IFERROR(INDEX(_xlfn.SORTBY(_xlfn.UNIQUE(_xlfn._xlws.FILTER('Scrum Teams'!$B$2:$B$1006,'Scrum Teams'!$B$2:$B$1006<>"")),_xlfn.XLOOKUP(_xlfn.UNIQUE(_xlfn._xlws.FILTER('Scrum Teams'!$B$2:$B$1006,'Scrum Teams'!$B$2:$B$1006<>"")),'Scrum Teams'!$B:$B,'Scrum Teams'!$A:$A,"")),ROW()-1),"")} -> FixedOps Integration 2 | N42: =IF(L42="", "", _xlfn.XLOOKUP(L42, 'Component Masterlist v2'!A:A, 'Component Masterlist v2'!P:P, "Not found")) -> INTG | O42: =IF(P42="", "", P42/2) -> 30 | P42: =IF(M42="","",_xlfn.LET( _xlpm.pos, MATCH(M42,'Scrum Teams'!$B$2:$B$1006,0), _xlpm.val, INDEX('Scrum Teams'!$E$2:$E$1006,_xlpm.pos), IF(ISBLANK(INDEX('Scrum Teams'!$E$2:$E$1006,_xlpm.pos)),"",_xlpm.val) )) -> 60 | Q42: =IF(L42="","",IF(P42<>"", P42, 90)) -> 60 | R42: =IF(M42="","",IF(L42="", "Missing component", _xlfn.XLOOKUP(L42, Lookup!A:A, Lookup!D:D, "NA"))) -> Turker Coskun
K43: {=IF(G43="","",_xlfn.LET( _xlpm.comp, TRIM(CLEAN(G43)), _xlpm.expected, J43, _xlpm.actual, SUMPRODUCT(--(TRIM(CLEAN($L$2:$L$140))=_xlpm.comp), $Q$2:$Q$140), IF(_xlpm.actual=_xlpm.expected, "No", "Mismatch by " & (_xlpm.actual-_xlpm.expected)) ))} | L43: =IF(M43="", "", _xlfn.XLOOKUP(M43,'Scrum Teams'!B:B,'Scrum Teams'!A:A,"")) -> ARCIntegration | M43: {=IFERROR(INDEX(_xlfn.SORTBY(_xlfn.UNIQUE(_xlfn._xlws.FILTER('Scrum Teams'!$B$2:$B$1006,'Scrum Teams'!$B$2:$B$1006<>"")),_xlfn.XLOOKUP(_xlfn.UNIQUE(_xlfn._xlws.FILTER('Scrum Teams'!$B$2:$B$1006,'Scrum Teams'!$B$2:$B$1006<>"")),'Scrum Teams'!$B:$B,'Scrum Teams'!$A:$A,"")),ROW()-1),"")} -> FixedOps Integration 3 | N43: =IF(L43="", "", _xlfn.XLOOKUP(L43, 'Component Masterlist v2'!A:A, 'Component Masterlist v2'!P:P, "Not found")) -> INTG | O43: =IF(P43="", "", P43/2) -> 30 | P43: =IF(M43="","",_xlfn.LET( _xlpm.pos, MATCH(M43,'Scrum Teams'!$B$2:$B$1006,0), _xlpm.val, INDEX('Scrum Teams'!$E$2:$E$1006,_xlpm.pos), IF(ISBLANK(INDEX('Scrum Teams'!$E$2:$E$1006,_xlpm.pos)),"",_xlpm.val) )) -> 60 | Q43: =IF(L43="","",IF(P43<>"", P43, 90)) -> 60 | R43: =IF(M43="","",IF(L43="", "Missing component", _xlfn.XLOOKUP(L43, Lookup!A:A, Lookup!D:D, "NA"))) -> Turker Coskun
K44: {=IF(G44="","",_xlfn.LET( _xlpm.comp, TRIM(CLEAN(G44)), _xlpm.expected, J44, _xlpm.actual, SUMPRODUCT(--(TRIM(CLEAN($L$2:$L$140))=_xlpm.comp), $Q$2:$Q$140), IF(_xlpm.actual=_xlpm.expected, "No", "Mismatch by " & (_xlpm.actual-_xlpm.expected)) ))} | L44: =IF(M44="", "", _xlfn.XLOOKUP(M44,'Scrum Teams'!B:B,'Scrum Teams'!A:A,"")) -> ARCIntegration | M44: {=IFERROR(INDEX(_xlfn.SORTBY(_xlfn.UNIQUE(_xlfn._xlws.FILTER('Scrum Teams'!$B$2:$B$1006,'Scrum Teams'!$B$2:$B$1006<>"")),_xlfn.XLOOKUP(_xlfn.UNIQUE(_xlfn._xlws.FILTER('Scrum Teams'!$B$2:$B$1006,'Scrum Teams'!$B$2:$B$1006<>"")),'Scrum Teams'!$B:$B,'Scrum Teams'!$A:$A,"")),ROW()-1),"")} -> Platform Integrations | N44: =IF(L44="", "", _xlfn.XLOOKUP(L44, 'Component Masterlist v2'!A:A, 'Component Masterlist v2'!P:P, "Not found")) -> INTG | O44: =IF(P44="", "", P44/2) -> 60 | P44: =IF(M44="","",_xlfn.LET( _xlpm.pos, MATCH(M44,'Scrum Teams'!$B$2:$B$1006,0), _xlpm.val, INDEX('Scrum Teams'!$E$2:$E$1006,_xlpm.pos), IF(ISBLANK(INDEX('Scrum Teams'!$E$2:$E$1006,_xlpm.pos)),"",_xlpm.val) )) -> 120 | Q44: =IF(L44="","",IF(P44<>"", P44, 90)) -> 120 | R44: =IF(M44="","",IF(L44="", "Missing component", _xlfn.XLOOKUP(L44, Lookup!A:A, Lookup!D:D, "NA"))) -> Turker Coskun
K45: {=IF(G45="","",_xlfn.LET( _xlpm.comp, TRIM(CLEAN(G45)), _xlpm.expected, J45, _xlpm.actual, SUMPRODUCT(--(TRIM(CLEAN($L$2:$L$140))=_xlpm.comp), $Q$2:$Q$140), IF(_xlpm.actual=_xlpm.expected, "No", "Mismatch by " & (_xlpm.actual-_xlpm.expected)) ))} | L45: =IF(M45="", "", _xlfn.XLOOKUP(M45,'Scrum Teams'!B:B,'Scrum Teams'!A:A,"")) -> ARCIntegration | M45: {=IFERROR(INDEX(_xlfn.SORTBY(_xlfn.UNIQUE(_xlfn._xlws.FILTER('Scrum Teams'!$B$2:$B$1006,'Scrum Teams'!$B$2:$B$1006<>"")),_xlfn.XLOOKUP(_xlfn.UNIQUE(_xlfn._xlws.FILTER('Scrum Teams'!$B$2:$B$1006,'Scrum Teams'!$B$2:$B$1006<>"")),'Scrum Teams'!$B:$B,'Scrum Teams'!$A:$A,"")),ROW()-1),"")} -> Retail Integration 1 | N45: =IF(L45="", "", _xlfn.XLOOKUP(L45, 'Component Masterlist v2'!A:A, 'Component Masterlist v2'!P:P, "Not found")) -> INTG | O45: =IF(P45="", "", P45/2) -> 45 | P45: =IF(M45="","",_xlfn.LET( _xlpm.pos, MATCH(M45,'Scrum Teams'!$B$2:$B$1006,0), _xlpm.val, INDEX('Scrum Teams'!$E$2:$E$1006,_xlpm.pos), IF(ISBLANK(INDEX('Scrum Teams'!$E$2:$E$1006,_xlpm.pos)),"",_xlpm.val) )) -> 90 | Q45: =IF(L45="","",IF(P45<>"", P45, 90)) -> 90 | R45: =IF(M45="","",IF(L45="", "Missing component", _xlfn.XLOOKUP(L45, Lookup!A:A, Lookup!D:D, "NA"))) -> Turker Coskun
K46: {=IF(G46="","",_xlfn.LET( _xlpm.comp, TRIM(CLEAN(G46)), _xlpm.expected, J46, _xlpm.actual, SUMPRODUCT(--(TRIM(CLEAN($L$2:$L$140))=_xlpm.comp), $Q$2:$Q$140), IF(_xlpm.actual=_xlpm.expected, "No", "Mismatch by " & (_xlpm.actual-_xlpm.expected)) ))} | L46: =IF(M46="", "", _xlfn.XLOOKUP(M46,'Scrum Teams'!B:B,'Scrum Teams'!A:A,"")) -> ARCIntegration | M46: {=IFERROR(INDEX(_xlfn.SORTBY(_xlfn.UNIQUE(_xlfn._xlws.FILTER('Scrum Teams'!$B$2:$B$1006,'Scrum Teams'!$B$2:$B$1006<>"")),_xlfn.XLOOKUP(_xlfn.UNIQUE(_xlfn._xlws.FILTER('Scrum Teams'!$B$2:$B$1006,'Scrum Teams'!$B$2:$B$1006<>"")),'Scrum Teams'!$B:$B,'Scrum Teams'!$A:$A,"")),ROW()-1),"")} -> Retail Integration 2 | N46: =IF(L46="", "", _xlfn.XLOOKUP(L46, 'Component Masterlist v2'!A:A, 'Component Masterlist v2'!P:P, "Not found")) -> INTG | O46: =IF(P46="", "", P46/2) -> 30 | P46: =IF(M46="","",_xlfn.LET( _xlpm.pos, MATCH(M46,'Scrum Teams'!$B$2:$B$1006,0), _xlpm.val, INDEX('Scrum Teams'!$E$2:$E$1006,_xlpm.pos), IF(ISBLANK(INDEX('Scrum Teams'!$E$2:$E$1006,_xlpm.pos)),"",_xlpm.val) )) -> 60 | Q46: =IF(L46="","",IF(P46<>"", P46, 90)) -> 60 | R46: =IF(M46="","",IF(L46="", "Missing component", _xlfn.XLOOKUP(L46, Lookup!A:A, Lookup!D:D, "NA"))) -> Turker Coskun
K47: {=IF(G47="","",_xlfn.LET( _xlpm.comp, TRIM(CLEAN(G47)), _xlpm.expected, J47, _xlpm.actual, SUMPRODUCT(--(TRIM(CLEAN($L$2:$L$140))=_xlpm.comp), $Q$2:$Q$140), IF(_xlpm.actual=_xlpm.expected, "No", "Mismatch by " & (_xlpm.actual-_xlpm.expected)) ))} | L47: =IF(M47="", "", _xlfn.XLOOKUP(M47,'Scrum Teams'!B:B,'Scrum Teams'!A:A,"")) -> Campaign | M47: {=IFERROR(INDEX(_xlfn.SORTBY(_xlfn.UNIQUE(_xlfn._xlws.FILTER('Scrum Teams'!$B$2:$B$1006,'Scrum Teams'!$B$2:$B$1006<>"")),_xlfn.XLOOKUP(_xlfn.UNIQUE(_xlfn._xlws.FILTER('Scrum Teams'!$B$2:$B$1006,'Scrum Teams'!$B$2:$B$1006<>"")),'Scrum Teams'!$B:$B,'Scrum Teams'!$A:$A,"")),ROW()-1),"")} -> Bishop | N47: =IF(L47="", "", _xlfn.XLOOKUP(L47, 'Component Masterlist v2'!A:A, 'Component Masterlist v2'!P:P, "Not found")) -> CRM | O47: =IF(P47="", "", P47/2) -> 77.5 | P47: =IF(M47="","",_xlfn.LET( _xlpm.pos, MATCH(M47,'Scrum Teams'!$B$2:$B$1006,0), _xlpm.val, INDEX('Scrum Teams'!$E$2:$E$1006,_xlpm.pos), IF(ISBLANK(INDEX('Scrum Teams'!$E$2:$E$1006,_xlpm.pos)),"",_xlpm.val) )) -> 155 | Q47: =IF(L47="","",IF(P47<>"", P47, 90)) -> 155 | R47: =IF(M47="","",IF(L47="", "Missing component", _xlfn.XLOOKUP(L47, Lookup!A:A, Lookup!D:D, "NA"))) -> Ved Singh
K48: {=IF(G48="","",_xlfn.LET( _xlpm.comp, TRIM(CLEAN(G48)), _xlpm.expected, J48, _xlpm.actual, SUMPRODUCT(--(TRIM(CLEAN($L$2:$L$140))=_xlpm.comp), $Q$2:$Q$140), IF(_xlpm.actual=_xlpm.expected, "No", "Mismatch by " & (_xlpm.actual-_xlpm.expected)) ))} | L48: =IF(M48="", "", _xlfn.XLOOKUP(M48,'Scrum Teams'!B:B,'Scrum Teams'!A:A,"")) -> Cashiering | M48: {=IFERROR(INDEX(_xlfn.SORTBY(_xlfn.UNIQUE(_xlfn._xlws.FILTER('Scrum Teams'!$B$2:$B$1006,'Scrum Teams'!$B$2:$B$1006<>"")),_xlfn.XLOOKUP(_xlfn.UNIQUE(_xlfn._xlws.FILTER('Scrum Teams'!$B$2:$B$1006,'Scrum Teams'!$B$2:$B$1006<>"")),'Scrum Teams'!$B:$B,'Scrum Teams'!$A:$A,"")),ROW()-1),"")} -> Cashiering | N48: =IF(L48="", "", _xlfn.XLOOKUP(L48, 'Component Masterlist v2'!A:A, 'Component Masterlist v2'!P:P, "Not found")) -> CASH | O48: =IF(P48="", "", P48/2) -> 34 | P48: =IF(M48="","",_xlfn.LET( _xlpm.pos, MATCH(M48,'Scrum Teams'!$B$2:$B$1006,0), _xlpm.val, INDEX('Scrum Teams'!$E$2:$E$1006,_xlpm.pos), IF(ISBLANK(INDEX('Scrum Teams'!$E$2:$E$1006,_xlpm.pos)),"",_xlpm.val) )) -> 68 | Q48: =IF(L48="","",IF(P48<>"", P48, 90)) -> 68 | R48: =IF(M48="","",IF(L48="", "Missing component", _xlfn.XLOOKUP(L48, Lookup!A:A, Lookup!D:D, "NA"))) -> Sanyam Agrawal
K49: {=IF(G49="","",_xlfn.LET( _xlpm.comp, TRIM(CLEAN(G49)), _xlpm.expected, J49, _xlpm.actual, SUMPRODUCT(--(TRIM(CLEAN($L$2:$L$140))=_xlpm.comp), $Q$2:$Q$140), IF(_xlpm.actual=_xlpm.expected, "No", "Mismatch by " & (_xlpm.actual-_xlpm.expected)) ))} | L49: =IF(M49="", "", _xlfn.XLOOKUP(M49,'Scrum Teams'!B:B,'Scrum Teams'!A:A,"")) -> Communication | M49: {=IFERROR(INDEX(_xlfn.SORTBY(_xlfn.UNIQUE(_xlfn._xlws.FILTER('Scrum Teams'!$B$2:$B$1006,'Scrum Teams'!$B$2:$B$1006<>"")),_xlfn.XLOOKUP(_xlfn.UNIQUE(_xlfn._xlws.FILTER('Scrum Teams'!$B$2:$B$1006,'Scrum Teams'!$B$2:$B$1006<>"")),'Scrum Teams'!$B:$B,'Scrum Teams'!$A:$A,"")),ROW()-1),"")} -> Communication | N49: =IF(L49="", "", _xlfn.XLOOKUP(L49, 'Component Masterlist v2'!A:A, 'Component Masterlist v2'!P:P, "Not found")) -> COMM | O49: =IF(P49="", "", P49/2) -> 135 | P49: =IF(M49="","",_xlfn.LET( _xlpm.pos, MATCH(M49,'Scrum Teams'!$B$2:$B$1006,0), _xlpm.val, INDEX('Scrum Teams'!$E$2:$E$1006,_xlpm.pos), IF(ISBLANK(INDEX('Scrum Teams'!$E$2:$E$1006,_xlpm.pos)),"",_xlpm.val) )) -> 270 | Q49: =IF(L49="","",IF(P49<>"", P49, 90)) -> 270 | R49: =IF(M49="","",IF(L49="", "Missing component", _xlfn.XLOOKUP(L49, Lookup!A:A, Lookup!D:D, "NA"))) -> Ved Singh
K50: {=IF(G50="","",_xlfn.LET( _xlpm.comp, TRIM(CLEAN(G50)), _xlpm.expected, J50, _xlpm.actual, SUMPRODUCT(--(TRIM(CLEAN($L$2:$L$140))=_xlpm.comp), $Q$2:$Q$140), IF(_xlpm.actual=_xlpm.expected, "No", "Mismatch by " & (_xlpm.actual-_xlpm.expected)) ))} | L50: =IF(M50="", "", _xlfn.XLOOKUP(M50,'Scrum Teams'!B:B,'Scrum Teams'!A:A,"")) -> CRM | M50: {=IFERROR(INDEX(_xlfn.SORTBY(_xlfn.UNIQUE(_xlfn._xlws.FILTER('Scrum Teams'!$B$2:$B$1006,'Scrum Teams'!$B$2:$B$1006<>"")),_xlfn.XLOOKUP(_xlfn.UNIQUE(_xlfn._xlws.FILTER('Scrum Teams'!$B$2:$B$1006,'Scrum Teams'!$B$2:$B$1006<>"")),'Scrum Teams'!$B:$B,'Scrum Teams'!$A:$A,"")),ROW()-1),"")} -> Gambit | N50: =IF(L50="", "", _xlfn.XLOOKUP(L50, 'Component Masterlist v2'!A:A, 'Component Masterlist v2'!P:P, "Not found")) -> CRM | O50: =IF(P50="", "", P50/2) -> 40 | P50: =IF(M50="","",_xlfn.LET( _xlpm.pos, MATCH(M50,'Scrum Teams'!$B$2:$B$1006,0), _xlpm.val, INDEX('Scrum Teams'!$E$2:$E$1006,_xlpm.pos), IF(ISBLANK(INDEX('Scrum Teams'!$E$2:$E$1006,_xlpm.pos)),"",_xlpm.val) )) -> 80 | Q50: =IF(L50="","",IF(P50<>"", P50, 90)) -> 80 | R50: =IF(M50="","",IF(L50="", "Missing component", _xlfn.XLOOKUP(L50, Lookup!A:A, Lookup!D:D, "NA"))) -> Ved Singh
K51: {=IF(G51="","",_xlfn.LET( _xlpm.comp, TRIM(CLEAN(G51)), _xlpm.expected, J51, _xlpm.actual, SUMPRODUCT(--(TRIM(CLEAN($L$2:$L$140))=_xlpm.comp), $Q$2:$Q$140), IF(_xlpm.actual=_xlpm.expected, "No", "Mismatch by " & (_xlpm.actual-_xlpm.expected)) ))} | L51: =IF(M51="", "", _xlfn.XLOOKUP(M51,'Scrum Teams'!B:B,'Scrum Teams'!A:A,"")) -> CRM | M51: {=IFERROR(INDEX(_xlfn.SORTBY(_xlfn.UNIQUE(_xlfn._xlws.FILTER('Scrum Teams'!$B$2:$B$1006,'Scrum Teams'!$B$2:$B$1006<>"")),_xlfn.XLOOKUP(_xlfn.UNIQUE(_xlfn._xlws.FILTER('Scrum Teams'!$B$2:$B$1006,'Scrum Teams'!$B$2:$B$1006<>"")),'Scrum Teams'!$B:$B,'Scrum Teams'!$A:$A,"")),ROW()-1),"")} -> Mystique | N51: =IF(L51="", "", _xlfn.XLOOKUP(L51, 'Component Masterlist v2'!A:A, 'Component Masterlist v2'!P:P, "Not found")) -> CRM | O51: =IF(P51="", "", P51/2) -> 95 | P51: =IF(M51="","",_xlfn.LET( _xlpm.pos, MATCH(M51,'Scrum Teams'!$B$2:$B$1006,0), _xlpm.val, INDEX('Scrum Teams'!$E$2:$E$1006,_xlpm.pos), IF(ISBLANK(INDEX('Scrum Teams'!$E$2:$E$1006,_xlpm.pos)),"",_xlpm.val) )) -> 190 | Q51: =IF(L51="","",IF(P51<>"", P51, 90)) -> 190 | R51: =IF(M51="","",IF(L51="", "Missing component", _xlfn.XLOOKUP(L51, Lookup!A:A, Lookup!D:D, "NA"))) -> Ved Singh
K52: {=IF(G52="","",_xlfn.LET( _xlpm.comp, TRIM(CLEAN(G52)), _xlpm.expected, J52, _xlpm.actual, SUMPRODUCT(--(TRIM(CLEAN($L$2:$L$140))=_xlpm.comp), $Q$2:$Q$140), IF(_xlpm.actual=_xlpm.expected, "No", "Mismatch by " & (_xlpm.actual-_xlpm.expected)) ))} | L52: =IF(M52="", "", _xlfn.XLOOKUP(M52,'Scrum Teams'!B:B,'Scrum Teams'!A:A,"")) -> CRM | M52: {=IFERROR(INDEX(_xlfn.SORTBY(_xlfn.UNIQUE(_xlfn._xlws.FILTER('Scrum Teams'!$B$2:$B$1006,'Scrum Teams'!$B$2:$B$1006<>"")),_xlfn.XLOOKUP(_xlfn.UNIQUE(_xlfn._xlws.FILTER('Scrum Teams'!$B$2:$B$1006,'Scrum Teams'!$B$2:$B$1006<>"")),'Scrum Teams'!$B:$B,'Scrum Teams'!$A:$A,"")),ROW()-1),"")} -> Storm | N52: =IF(L52="", "", _xlfn.XLOOKUP(L52, 'Component Masterlist v2'!A:A, 'Component Masterlist v2'!P:P, "Not found")) -> CRM | O52: =IF(P52="", "", P52/2) -> 87.5 | P52: =IF(M52="","",_xlfn.LET( _xlpm.pos, MATCH(M52,'Scrum Teams'!$B$2:$B$1006,0), _xlpm.val, INDEX('Scrum Teams'!$E$2:$E$1006,_xlpm.pos), IF(ISBLANK(INDEX('Scrum Teams'!$E$2:$E$1006,_xlpm.pos)),"",_xlpm.val) )) -> 175 | Q52: =IF(L52="","",IF(P52<>"", P52, 90)) -> 175 | R52: =IF(M52="","",IF(L52="", "Missing component", _xlfn.XLOOKUP(L52, Lookup!A:A, Lookup!D:D, "NA"))) -> Ved Singh
... K58: {=IF(G58="","",_xlfn.LET( _xlpm.comp, TRIM(CLEAN(G58)), _xlpm.expected, J58, _xlpm.actual, SUMPRODUCT(--(TRIM(CLEAN($L$2:$L$140))=_xlpm.comp), $Q$2:$Q$140), IF(_xlpm.actual=_xlpm.expected, "No", "Mismatch by " & (_xlpm.actual-_xlpm.expected)) ))} | L58: =IF(M58="", "", _xlfn.XLOOKUP(M58,'Scrum Teams'!B:B,'Scrum Teams'!A:A,"")) -> DataPlatform | M58: {=IFERROR(INDEX(_xlfn.SORTBY(_xlfn.UNIQUE(_xlfn._xlws.FILTER('Scrum Teams'!$B$2:$B$1006,'Scrum Teams'!$B$2:$B$1006<>"")),_xlfn.XLOOKUP(_xlfn.UNIQUE(_xlfn._xlws.FILTER('Scrum Teams'!$B$2:$B$1006,'Scrum Teams'!$B$2:$B$1006<>"")),'Scrum Teams'!$B:$B,'Scrum Teams'!$A:$A,"")),ROW()-1),"")} -> Data Platform | N58: =IF(L58="", "", _xlfn.XLOOKUP(L58, 'Component Masterlist v2'!A:A, 'Component Masterlist v2'!P:P, "Not found")) -> DPLT | O58: =IF(P58="", "", P58/2) -> 75 | P58: =IF(M58="","",_xlfn.LET( _xlpm.pos, MATCH(M58,'Scrum Teams'!$B$2:$B$1006,0), _xlpm.val, INDEX('Scrum Teams'!$E$2:$E$1006,_xlpm.pos), IF(ISBLANK(INDEX('Scrum Teams'!$E$2:$E$1006,_xlpm.pos)),"",_xlpm.val) )) -> 150 | Q58: =IF(L58="","",IF(P58<>"", P58, 90)) -> 150 | R58: =IF(M58="","",IF(L58="", "Missing component", _xlfn.XLOOKUP(L58, Lookup!A:A, Lookup!D:D, "NA"))) -> Satish Sallakonda
K59: {=IF(G59="","",_xlfn.LET( _xlpm.comp, TRIM(CLEAN(G59)), _xlpm.expected, J59, _xlpm.actual, SUMPRODUCT(--(TRIM(CLEAN($L$2:$L$140))=_xlpm.comp), $Q$2:$Q$140), IF(_xlpm.actual=_xlpm.expected, "No", "Mismatch by " & (_xlpm.actual-_xlpm.expected)) ))} | L59: =IF(M59="", "", _xlfn.XLOOKUP(M59,'Scrum Teams'!B:B,'Scrum Teams'!A:A,"")) -> DigitalRetailing | M59: {=IFERROR(INDEX(_xlfn.SORTBY(_xlfn.UNIQUE(_xlfn._xlws.FILTER('Scrum Teams'!$B$2:$B$1006,'Scrum Teams'!$B$2:$B$1006<>"")),_xlfn.XLOOKUP(_xlfn.UNIQUE(_xlfn._xlws.FILTER('Scrum Teams'!$B$2:$B$1006,'Scrum Teams'!$B$2:$B$1006<>"")),'Scrum Teams'!$B:$B,'Scrum Teams'!$A:$A,"")),ROW()-1),"")} -> DR_Checkout | N59: =IF(L59="", "", _xlfn.XLOOKUP(L59, 'Component Masterlist v2'!A:A, 'Component Masterlist v2'!P:P, "Not found")) -> DGRT | O59: =IF(P59="", "", P59/2) -> 171 | P59: =IF(M59="","",_xlfn.LET( _xlpm.pos, MATCH(M59,'Scrum Teams'!$B$2:$B$1006,0), _xlpm.val, INDEX('Scrum Teams'!$E$2:$E$1006,_xlpm.pos), IF(ISBLANK(INDEX('Scrum Teams'!$E$2:$E$1006,_xlpm.pos)),"",_xlpm.val) )) -> 342 | Q59: =IF(L59="","",IF(P59<>"", P59, 90)) -> 342 | R59: =IF(M59="","",IF(L59="", "Missing component", _xlfn.XLOOKUP(L59, Lookup!A:A, Lookup!D:D, "NA"))) -> Ved Singh | T59: Accounting | U59: 287 | V59: 297 | W59: 424.5 | X59: 336.16667
K60: {=IF(G60="","",_xlfn.LET( _xlpm.comp, TRIM(CLEAN(G60)), _xlpm.expected, J60, _xlpm.actual, SUMPRODUCT(--(TRIM(CLEAN($L$2:$L$140))=_xlpm.comp), $Q$2:$Q$140), IF(_xlpm.actual=_xlpm.expected, "No", "Mismatch by " & (_xlpm.actual-_xlpm.expected)) ))} | L60: =IF(M60="", "", _xlfn.XLOOKUP(M60,'Scrum Teams'!B:B,'Scrum Teams'!A:A,"")) -> DigitalRetailing | M60: {=IFERROR(INDEX(_xlfn.SORTBY(_xlfn.UNIQUE(_xlfn._xlws.FILTER('Scrum Teams'!$B$2:$B$1006,'Scrum Teams'!$B$2:$B$1006<>"")),_xlfn.XLOOKUP(_xlfn.UNIQUE(_xlfn._xlws.FILTER('Scrum Teams'!$B$2:$B$1006,'Scrum Teams'!$B$2:$B$1006<>"")),'Scrum Teams'!$B:$B,'Scrum Teams'!$A:$A,"")),ROW()-1),"")} -> DR_SRCHAT | N60: =IF(L60="", "", _xlfn.XLOOKUP(L60, 'Component Masterlist v2'!A:A, 'Component Masterlist v2'!P:P, "Not found")) -> DGRT | O60: =IF(P60="", "", P60/2) -> 67.5 | P60: =IF(M60="","",_xlfn.LET( _xlpm.pos, MATCH(M60,'Scrum Teams'!$B$2:$B$1006,0), _xlpm.val, INDEX('Scrum Teams'!$E$2:$E$1006,_xlpm.pos), IF(ISBLANK(INDEX('Scrum Teams'!$E$2:$E$1006,_xlpm.pos)),"",_xlpm.val) )) -> 135 | Q60: =IF(L60="","",IF(P60<>"", P60, 90)) -> 135 | R60: =IF(M60="","",IF(L60="", "Missing component", _xlfn.XLOOKUP(L60, Lookup!A:A, Lookup!D:D, "NA"))) -> Ved Singh | T60: AECPlatform / DGRT | U60: 381 | V60: 322 | W60: 311 | X60: 338
K61: {=IF(G61="","",_xlfn.LET( _xlpm.comp, TRIM(CLEAN(G61)), _xlpm.expected, J61, _xlpm.actual, SUMPRODUCT(--(TRIM(CLEAN($L$2:$L$140))=_xlpm.comp), $Q$2:$Q$140), IF(_xlpm.actual=_xlpm.expected, "No", "Mismatch by " & (_xlpm.actual-_xlpm.expected)) ))} | L61: =IF(M61="", "", _xlfn.XLOOKUP(M61,'Scrum Teams'!B:B,'Scrum Teams'!A:A,"")) -> DigitalRetailing | M61: {=IFERROR(INDEX(_xlfn.SORTBY(_xlfn.UNIQUE(_xlfn._xlws.FILTER('Scrum Teams'!$B$2:$B$1006,'Scrum Teams'!$B$2:$B$1006<>"")),_xlfn.XLOOKUP(_xlfn.UNIQUE(_xlfn._xlws.FILTER('Scrum Teams'!$B$2:$B$1006,'Scrum Teams'!$B$2:$B$1006<>"")),'Scrum Teams'!$B:$B,'Scrum Teams'!$A:$A,"")),ROW()-1),"")} -> DR_Studio | N61: =IF(L61="", "", _xlfn.XLOOKUP(L61, 'Component Masterlist v2'!A:A, 'Component Masterlist v2'!P:P, "Not found")) -> DGRT | O61: =IF(P61="", "", P61/2) -> 0 | P61: =IF(M61="","",_xlfn.LET( _xlpm.pos, MATCH(M61,'Scrum Teams'!$B$2:$B$1006,0), _xlpm.val, INDEX('Scrum Teams'!$E$2:$E$1006,_xlpm.pos), IF(ISBLANK(INDEX('Scrum Teams'!$E$2:$E$1006,_xlpm.pos)),"",_xlpm.val) )) -> 0 | Q61: =IF(L61="","",IF(P61<>"", P61, 90)) -> 0 | R61: =IF(M61="","",IF(L61="", "Missing component", _xlfn.XLOOKUP(L61, Lookup!A:A, Lookup!D:D, "NA"))) -> Ved Singh | T61: Analytics | U61: 53 | V61: 49.5 | W61: 60 | X61: 54.166667
K62: {=IF(G62="","",_xlfn.LET( _xlpm.comp, TRIM(CLEAN(G62)), _xlpm.expected, J62, _xlpm.actual, SUMPRODUCT(--(TRIM(CLEAN($L$2:$L$140))=_xlpm.comp), $Q$2:$Q$140), IF(_xlpm.actual=_xlpm.expected, "No", "Mismatch by " & (_xlpm.actual-_xlpm.expected)) ))} | L62: =IF(M62="", "", _xlfn.XLOOKUP(M62,'Scrum Teams'!B:B,'Scrum Teams'!A:A,"")) -> DR_GM | M62: {=IFERROR(INDEX(_xlfn.SORTBY(_xlfn.UNIQUE(_xlfn._xlws.FILTER('Scrum Teams'!$B$2:$B$1006,'Scrum Teams'!$B$2:$B$1006<>"")),_xlfn.XLOOKUP(_xlfn.UNIQUE(_xlfn._xlws.FILTER('Scrum Teams'!$B$2:$B$1006,'Scrum Teams'!$B$2:$B$1006<>"")),'Scrum Teams'!$B:$B,'Scrum Teams'!$A:$A,"")),ROW()-1),"")} -> 3rd Party Chat Integrations | N62: =IF(L62="", "", _xlfn.XLOOKUP(L62, 'Component Masterlist v2'!A:A, 'Component Masterlist v2'!P:P, "Not found")) -> GM | O62: =IF(P62="", "", P62/2) -> 52.5 | P62: =IF(M62="","",_xlfn.LET( _xlpm.pos, MATCH(M62,'Scrum Teams'!$B$2:$B$1006,0), _xlpm.val, INDEX('Scrum Teams'!$E$2:$E$1006,_xlpm.pos), IF(ISBLANK(INDEX('Scrum Teams'!$E$2:$E$1006,_xlpm.pos)),"",_xlpm.val) )) -> 105 | Q62: =IF(L62="","",IF(P62<>"", P62, 90)) -> 105 | R62: =IF(M62="","",IF(L62="", "Missing component", _xlfn.XLOOKUP(L62, Lookup!A:A, Lookup!D:D, "NA"))) -> Santosh Golecha | T62: APC | U62: 147.5 | V62: 146 | W62: 279 | X62: 190.83333
K63: {=IF(G63="","",_xlfn.LET( _xlpm.comp, TRIM(CLEAN(G63)), _xlpm.expected, J63, _xlpm.actual, SUMPRODUCT(--(TRIM(CLEAN($L$2:$L$140))=_xlpm.comp), $Q$2:$Q$140), IF(_xlpm.actual=_xlpm.expected, "No", "Mismatch by " & (_xlpm.actual-_xlpm.expected)) ))} | L63: =IF(M63="", "", _xlfn.XLOOKUP(M63,'Scrum Teams'!B:B,'Scrum Teams'!A:A,"")) -> DR_GM | M63: {=IFERROR(INDEX(_xlfn.SORTBY(_xlfn.UNIQUE(_xlfn._xlws.FILTER('Scrum Teams'!$B$2:$B$1006,'Scrum Teams'!$B$2:$B$1006<>"")),_xlfn.XLOOKUP(_xlfn.UNIQUE(_xlfn._xlws.FILTER('Scrum Teams'!$B$2:$B$1006,'Scrum Teams'!$B$2:$B$1006<>"")),'Scrum Teams'!$B:$B,'Scrum Teams'!$A:$A,"")),ROW()-1),"")} -> AEO-GEO | N63: =IF(L63="", "", _xlfn.XLOOKUP(L63, 'Component Masterlist v2'!A:A, 'Component Masterlist v2'!P:P, "Not found")) -> GM | O63: =IF(P63="", "", P63/2) -> 52.5 | P63: =IF(M63="","",_xlfn.LET( _xlpm.pos, MATCH(M63,'Scrum Teams'!$B$2:$B$1006,0), _xlpm.val, INDEX('Scrum Teams'!$E$2:$E$1006,_xlpm.pos), IF(ISBLANK(INDEX('Scrum Teams'!$E$2:$E$1006,_xlpm.pos)),"",_xlpm.val) )) -> 105 | Q63: =IF(L63="","",IF(P63<>"", P63, 90)) -> 105 | R63: =IF(M63="","",IF(L63="", "Missing component", _xlfn.XLOOKUP(L63, Lookup!A:A, Lookup!D:D, "NA"))) -> Santosh Golecha | T63: ARCIntegration | U63: 142 | V63: 133 | W63: 276 | X63: 183.66667
K64: {=IF(G64="","",_xlfn.LET( _xlpm.comp, TRIM(CLEAN(G64)), _xlpm.expected, J64, _xlpm.actual, SUMPRODUCT(--(TRIM(CLEAN($L$2:$L$140))=_xlpm.comp), $Q$2:$Q$140), IF(_xlpm.actual=_xlpm.expected, "No", "Mismatch by " & (_xlpm.actual-_xlpm.expected)) ))} | L64: =IF(M64="", "", _xlfn.XLOOKUP(M64,'Scrum Teams'!B:B,'Scrum Teams'!A:A,"")) -> DR_GM | M64: {=IFERROR(INDEX(_xlfn.SORTBY(_xlfn.UNIQUE(_xlfn._xlws.FILTER('Scrum Teams'!$B$2:$B$1006,'Scrum Teams'!$B$2:$B$1006<>"")),_xlfn.XLOOKUP(_xlfn.UNIQUE(_xlfn._xlws.FILTER('Scrum Teams'!$B$2:$B$1006,'Scrum Teams'!$B$2:$B$1006<>"")),'Scrum Teams'!$B:$B,'Scrum Teams'!$A:$A,"")),ROW()-1),"")} -> Configurator | N64: =IF(L64="", "", _xlfn.XLOOKUP(L64, 'Component Masterlist v2'!A:A, 'Component Masterlist v2'!P:P, "Not found")) -> GM | O64: =IF(P64="", "", P64/2) -> 60 | P64: =IF(M64="","",_xlfn.LET( _xlpm.pos, MATCH(M64,'Scrum Teams'!$B$2:$B$1006,0), _xlpm.val, INDEX('Scrum Teams'!$E$2:$E$1006,_xlpm.pos), IF(ISBLANK(INDEX('Scrum Teams'!$E$2:$E$1006,_xlpm.pos)),"",_xlpm.val) )) -> 120 | Q64: =IF(L64="","",IF(P64<>"", P64, 90)) -> 120 | R64: =IF(M64="","",IF(L64="", "Missing component", _xlfn.XLOOKUP(L64, Lookup!A:A, Lookup!D:D, "NA"))) -> Santosh Golecha
K65: {=IF(G65="","",_xlfn.LET( _xlpm.comp, TRIM(CLEAN(G65)), _xlpm.expected, J65, _xlpm.actual, SUMPRODUCT(--(TRIM(CLEAN($L$2:$L$140))=_xlpm.comp), $Q$2:$Q$140), IF(_xlpm.actual=_xlpm.expected, "No", "Mismatch by " & (_xlpm.actual-_xlpm.expected)) ))} | L65: =IF(M65="", "", _xlfn.XLOOKUP(M65,'Scrum Teams'!B:B,'Scrum Teams'!A:A,"")) -> DR_GM | M65: {=IFERROR(INDEX(_xlfn.SORTBY(_xlfn.UNIQUE(_xlfn._xlws.FILTER('Scrum Teams'!$B$2:$B$1006,'Scrum Teams'!$B$2:$B$1006<>"")),_xlfn.XLOOKUP(_xlfn.UNIQUE(_xlfn._xlws.FILTER('Scrum Teams'!$B$2:$B$1006,'Scrum Teams'!$B$2:$B$1006<>"")),'Scrum Teams'!$B:$B,'Scrum Teams'!$A:$A,"")),ROW()-1),"")} -> Discovery & Ingestion | N65: =IF(L65="", "", _xlfn.XLOOKUP(L65, 'Component Masterlist v2'!A:A, 'Component Masterlist v2'!P:P, "Not found")) -> GM | O65: =IF(P65="", "", P65/2) -> 37.5 | P65: =IF(M65="","",_xlfn.LET( _xlpm.pos, MATCH(M65,'Scrum Teams'!$B$2:$B$1006,0), _xlpm.val, INDEX('Scrum Teams'!$E$2:$E$1006,_xlpm.pos), IF(ISBLANK(INDEX('Scrum Teams'!$E$2:$E$1006,_xlpm.pos)),"",_xlpm.val) )) -> 75 | Q65: =IF(L65="","",IF(P65<>"", P65, 90)) -> 75 | R65: =IF(M65="","",IF(L65="", "Missing component", _xlfn.XLOOKUP(L65, Lookup!A:A, Lookup!D:D, "NA"))) -> Santosh Golecha
K66: {=IF(G66="","",_xlfn.LET( _xlpm.comp, TRIM(CLEAN(G66)), _xlpm.expected, J66, _xlpm.actual, SUMPRODUCT(--(TRIM(CLEAN($L$2:$L$140))=_xlpm.comp), $Q$2:$Q$140), IF(_xlpm.actual=_xlpm.expected, "No", "Mismatch by " & (_xlpm.actual-_xlpm.expected)) ))} | L66: =IF(M66="", "", _xlfn.XLOOKUP(M66,'Scrum Teams'!B:B,'Scrum Teams'!A:A,"")) -> DR_GM | M66: {=IFERROR(INDEX(_xlfn.SORTBY(_xlfn.UNIQUE(_xlfn._xlws.FILTER('Scrum Teams'!$B$2:$B$1006,'Scrum Teams'!$B$2:$B$1006<>"")),_xlfn.XLOOKUP(_xlfn.UNIQUE(_xlfn._xlws.FILTER('Scrum Teams'!$B$2:$B$1006,'Scrum Teams'!$B$2:$B$1006<>"")),'Scrum Teams'!$B:$B,'Scrum Teams'!$A:$A,"")),ROW()-1),"")} -> DX (1.0 Salescloud and 2.0 Custom Apps) | N66: =IF(L66="", "", _xlfn.XLOOKUP(L66, 'Component Masterlist v2'!A:A, 'Component Masterlist v2'!P:P, "Not found")) -> GM | O66: =IF(P66="", "", P66/2) -> 52.5 | P66: =IF(M66="","",_xlfn.LET( _xlpm.pos, MATCH(M66,'Scrum Teams'!$B$2:$B$1006,0), _xlpm.val, INDEX('Scrum Teams'!$E$2:$E$1006,_xlpm.pos), IF(ISBLANK(INDEX('Scrum Teams'!$E$2:$E$1006,_xlpm.pos)),"",_xlpm.val) )) -> 105 | Q66: =IF(L66="","",IF(P66<>"", P66, 90)) -> 105 | R66: =IF(M66="","",IF(L66="", "Missing component", _xlfn.XLOOKUP(L66, Lookup!A:A, Lookup!D:D, "NA"))) -> Santosh Golecha
K67: {=IF(G67="","",_xlfn.LET( _xlpm.comp, TRIM(CLEAN(G67)), _xlpm.expected, J67, _xlpm.actual, SUMPRODUCT(--(TRIM(CLEAN($L$2:$L$140))=_xlpm.comp), $Q$2:$Q$140), IF(_xlpm.actual=_xlpm.expected, "No", "Mismatch by " & (_xlpm.actual-_xlpm.expected)) ))} | L67: =IF(M67="", "", _xlfn.XLOOKUP(M67,'Scrum Teams'!B:B,'Scrum Teams'!A:A,"")) -> DR_GM | M67: {=IFERROR(INDEX(_xlfn.SORTBY(_xlfn.UNIQUE(_xlfn._xlws.FILTER('Scrum Teams'!$B$2:$B$1006,'Scrum Teams'!$B$2:$B$1006<>"")),_xlfn.XLOOKUP(_xlfn.UNIQUE(_xlfn._xlws.FILTER('Scrum Teams'!$B$2:$B$1006,'Scrum Teams'!$B$2:$B$1006<>"")),'Scrum Teams'!$B:$B,'Scrum Teams'!$A:$A,"")),ROW()-1),"")} -> GM Integrations (1.0 and 2.0) | N67: =IF(L67="", "", _xlfn.XLOOKUP(L67, 'Component Masterlist v2'!A:A, 'Component Masterlist v2'!P:P, "Not found")) -> GM | O67: =IF(P67="", "", P67/2) -> 75 | P67: =IF(M67="","",_xlfn.LET( _xlpm.pos, MATCH(M67,'Scrum Teams'!$B$2:$B$1006,0), _xlpm.val, INDEX('Scrum Teams'!$E$2:$E$1006,_xlpm.pos), IF(ISBLANK(INDEX('Scrum Teams'!$E$2:$E$1006,_xlpm.pos)),"",_xlpm.val) )) -> 150 | Q67: =IF(L67="","",IF(P67<>"", P67, 90)) -> 150 | R67: =IF(M67="","",IF(L67="", "Missing component", _xlfn.XLOOKUP(L67, Lookup!A:A, Lookup!D:D, "NA"))) -> Santosh Golecha
K68: {=IF(G68="","",_xlfn.LET( _xlpm.comp, TRIM(CLEAN(G68)), _xlpm.expected, J68, _xlpm.actual, SUMPRODUCT(--(TRIM(CLEAN($L$2:$L$140))=_xlpm.comp), $Q$2:$Q$140), IF(_xlpm.actual=_xlpm.expected, "No", "Mismatch by " & (_xlpm.actual-_xlpm.expected)) ))} | L68: =IF(M68="", "", _xlfn.XLOOKUP(M68,'Scrum Teams'!B:B,'Scrum Teams'!A:A,"")) -> DR_GM | M68: {=IFERROR(INDEX(_xlfn.SORTBY(_xlfn.UNIQUE(_xlfn._xlws.FILTER('Scrum Teams'!$B$2:$B$1006,'Scrum Teams'!$B$2:$B$1006<>"")),_xlfn.XLOOKUP(_xlfn.UNIQUE(_xlfn._xlws.FILTER('Scrum Teams'!$B$2:$B$1006,'Scrum Teams'!$B$2:$B$1006<>"")),'Scrum Teams'!$B:$B,'Scrum Teams'!$A:$A,"")),ROW()-1),"")} -> My Accounts | N68: =IF(L68="", "", _xlfn.XLOOKUP(L68, 'Component Masterlist v2'!A:A, 'Component Masterlist v2'!P:P, "Not found")) -> GM | O68: =IF(P68="", "", P68/2) -> 52.5 | P68: =IF(M68="","",_xlfn.LET( _xlpm.pos, MATCH(M68,'Scrum Teams'!$B$2:$B$1006,0), _xlpm.val, INDEX('Scrum Teams'!$E$2:$E$1006,_xlpm.pos), IF(ISBLANK(INDEX('Scrum Teams'!$E$2:$E$1006,_xlpm.pos)),"",_xlpm.val) )) -> 105 | Q68: =IF(L68="","",IF(P68<>"", P68, 90)) -> 105 | R68: =IF(M68="","",IF(L68="", "Missing component", _xlfn.XLOOKUP(L68, Lookup!A:A, Lookup!D:D, "NA"))) -> Santosh Golecha
K69: {=IF(G69="","",_xlfn.LET( _xlpm.comp, TRIM(CLEAN(G69)), _xlpm.expected, J69, _xlpm.actual, SUMPRODUCT(--(TRIM(CLEAN($L$2:$L$140))=_xlpm.comp), $Q$2:$Q$140), IF(_xlpm.actual=_xlpm.expected, "No", "Mismatch by " & (_xlpm.actual-_xlpm.expected)) ))} | L69: =IF(M69="", "", _xlfn.XLOOKUP(M69,'Scrum Teams'!B:B,'Scrum Teams'!A:A,"")) -> DR_GM | M69: {=IFERROR(INDEX(_xlfn.SORTBY(_xlfn.UNIQUE(_xlfn._xlws.FILTER('Scrum Teams'!$B$2:$B$1006,'Scrum Teams'!$B$2:$B$1006<>"")),_xlfn.XLOOKUP(_xlfn.UNIQUE(_xlfn._xlws.FILTER('Scrum Teams'!$B$2:$B$1006,'Scrum Teams'!$B$2:$B$1006<>"")),'Scrum Teams'!$B:$B,'Scrum Teams'!$A:$A,"")),ROW()-1),"")} -> OEM - D360 + Analytics | N69: =IF(L69="", "", _xlfn.XLOOKUP(L69, 'Component Masterlist v2'!A:A, 'Component Masterlist v2'!P:P, "Not found")) -> GM | O69: =IF(P69="", "", P69/2) -> 75 | P69: =IF(M69="","",_xlfn.LET( _xlpm.pos, MATCH(M69,'Scrum Teams'!$B$2:$B$1006,0), _xlpm.val, INDEX('Scrum Teams'!$E$2:$E$1006,_xlpm.pos), IF(ISBLANK(INDEX('Scrum Teams'!$E$2:$E$1006,_xlpm.pos)),"",_xlpm.val) )) -> 150 | Q69: =IF(L69="","",IF(P69<>"", P69, 90)) -> 150 | R69: =IF(M69="","",IF(L69="", "Missing component", _xlfn.XLOOKUP(L69, Lookup!A:A, Lookup!D:D, "NA"))) -> Santosh Golecha
K70: {=IF(G70="","",_xlfn.LET( _xlpm.comp, TRIM(CLEAN(G70)), _xlpm.expected, J70, _xlpm.actual, SUMPRODUCT(--(TRIM(CLEAN($L$2:$L$140))=_xlpm.comp), $Q$2:$Q$140), IF(_xlpm.actual=_xlpm.expected, "No", "Mismatch by " & (_xlpm.actual-_xlpm.expected)) ))} | L70: =IF(M70="", "", _xlfn.XLOOKUP(M70,'Scrum Teams'!B:B,'Scrum Teams'!A:A,"")) -> DR_GM | M70: {=IFERROR(INDEX(_xlfn.SORTBY(_xlfn.UNIQUE(_xlfn._xlws.FILTER('Scrum Teams'!$B$2:$B$1006,'Scrum Teams'!$B$2:$B$1006<>"")),_xlfn.XLOOKUP(_xlfn.UNIQUE(_xlfn._xlws.FILTER('Scrum Teams'!$B$2:$B$1006,'Scrum Teams'!$B$2:$B$1006<>"")),'Scrum Teams'!$B:$B,'Scrum Teams'!$A:$A,"")),ROW()-1),"")} -> OEM Agentic AI | N70: =IF(L70="", "", _xlfn.XLOOKUP(L70, 'Component Masterlist v2'!A:A, 'Component Masterlist v2'!P:P, "Not found")) -> GM | O70: =IF(P70="", "", P70/2) -> 75 | P70: =IF(M70="","",_xlfn.LET( _xlpm.pos, MATCH(M70,'Scrum Teams'!$B$2:$B$1006,0), _xlpm.val, INDEX('Scrum Teams'!$E$2:$E$1006,_xlpm.pos), IF(ISBLANK(INDEX('Scrum Teams'!$E$2:$E$1006,_xlpm.pos)),"",_xlpm.val) )) -> 150 | Q70: =IF(L70="","",IF(P70<>"", P70, 90)) -> 150 | R70: =IF(M70="","",IF(L70="", "Missing component", _xlfn.XLOOKUP(L70, Lookup!A:A, Lookup!D:D, "NA"))) -> Santosh Golecha
K71: {=IF(G71="","",_xlfn.LET( _xlpm.comp, TRIM(CLEAN(G71)), _xlpm.expected, J71, _xlpm.actual, SUMPRODUCT(--(TRIM(CLEAN($L$2:$L$140))=_xlpm.comp), $Q$2:$Q$140), IF(_xlpm.actual=_xlpm.expected, "No", "Mismatch by " & (_xlpm.actual-_xlpm.expected)) ))} | L71: =IF(M71="", "", _xlfn.XLOOKUP(M71,'Scrum Teams'!B:B,'Scrum Teams'!A:A,"")) -> DR_GM | M71: {=IFERROR(INDEX(_xlfn.SORTBY(_xlfn.UNIQUE(_xlfn._xlws.FILTER('Scrum Teams'!$B$2:$B$1006,'Scrum Teams'!$B$2:$B$1006<>"")),_xlfn.XLOOKUP(_xlfn.UNIQUE(_xlfn._xlws.FILTER('Scrum Teams'!$B$2:$B$1006,'Scrum Teams'!$B$2:$B$1006<>"")),'Scrum Teams'!$B:$B,'Scrum Teams'!$A:$A,"")),ROW()-1),"")} -> OMS & Pricing | N71: =IF(L71="", "", _xlfn.XLOOKUP(L71, 'Component Masterlist v2'!A:A, 'Component Masterlist v2'!P:P, "Not found")) -> GM | O71: =IF(P71="", "", P71/2) -> 15 | P71: =IF(M71="","",_xlfn.LET( _xlpm.pos, MATCH(M71,'Scrum Teams'!$B$2:$B$1006,0), _xlpm.val, INDEX('Scrum Teams'!$E$2:$E$1006,_xlpm.pos), IF(ISBLANK(INDEX('Scrum Teams'!$E$2:$E$1006,_xlpm.pos)),"",_xlpm.val) )) -> 30 | Q71: =IF(L71="","",IF(P71<>"", P71, 90)) -> 30 | R71: =IF(M71="","",IF(L71="", "Missing component", _xlfn.XLOOKUP(L71, Lookup!A:A, Lookup!D:D, "NA"))) -> Santosh Golecha
K72: {=IF(G72="","",_xlfn.LET( _xlpm.comp, TRIM(CLEAN(G72)), _xlpm.expected, J72, _xlpm.actual, SUMPRODUCT(--(TRIM(CLEAN($L$2:$L$140))=_xlpm.comp), $Q$2:$Q$140), IF(_xlpm.actual=_xlpm.expected, "No", "Mismatch by " & (_xlpm.actual-_xlpm.expected)) ))} | L72: =IF(M72="", "", _xlfn.XLOOKUP(M72,'Scrum Teams'!B:B,'Scrum Teams'!A:A,"")) -> DR_GM | M72: {=IFERROR(INDEX(_xlfn.SORTBY(_xlfn.UNIQUE(_xlfn._xlws.FILTER('Scrum Teams'!$B$2:$B$1006,'Scrum Teams'!$B$2:$B$1006<>"")),_xlfn.XLOOKUP(_xlfn.UNIQUE(_xlfn._xlws.FILTER('Scrum Teams'!$B$2:$B$1006,'Scrum Teams'!$B$2:$B$1006<>"")),'Scrum Teams'!$B:$B,'Scrum Teams'!$A:$A,"")),ROW()-1),"")} -> SCX (1.0 and 2.0) | N72: =IF(L72="", "", _xlfn.XLOOKUP(L72, 'Component Masterlist v2'!A:A, 'Component Masterlist v2'!P:P, "Not found")) -> GM | O72: =IF(P72="", "", P72/2) -> 60 | P72: =IF(M72="","",_xlfn.LET( _xlpm.pos, MATCH(M72,'Scrum Teams'!$B$2:$B$1006,0), _xlpm.val, INDEX('Scrum Teams'!$E$2:$E$1006,_xlpm.pos), IF(ISBLANK(INDEX('Scrum Teams'!$E$2:$E$1006,_xlpm.pos)),"",_xlpm.val) )) -> 120 | Q72: =IF(L72="","",IF(P72<>"", P72, 90)) -> 120 | R72: =IF(M72="","",IF(L72="", "Missing component", _xlfn.XLOOKUP(L72, Lookup!A:A, Lookup!D:D, "NA"))) -> Santosh Golecha
K73: {=IF(G73="","",_xlfn.LET( _xlpm.comp, TRIM(CLEAN(G73)), _xlpm.expected, J73, _xlpm.actual, SUMPRODUCT(--(TRIM(CLEAN($L$2:$L$140))=_xlpm.comp), $Q$2:$Q$140), IF(_xlpm.actual=_xlpm.expected, "No", "Mismatch by " & (_xlpm.actual-_xlpm.expected)) ))} | L73: =IF(M73="", "", _xlfn.XLOOKUP(M73,'Scrum Teams'!B:B,'Scrum Teams'!A:A,"")) -> DR_GM | M73: {=IFERROR(INDEX(_xlfn.SORTBY(_xlfn.UNIQUE(_xlfn._xlws.FILTER('Scrum Teams'!$B$2:$B$1006,'Scrum Teams'!$B$2:$B$1006<>"")),_xlfn.XLOOKUP(_xlfn.UNIQUE(_xlfn._xlws.FILTER('Scrum Teams'!$B$2:$B$1006,'Scrum Teams'!$B$2:$B$1006<>"")),'Scrum Teams'!$B:$B,'Scrum Teams'!$A:$A,"")),ROW()-1),"")} -> VDP | N73: =IF(L73="", "", _xlfn.XLOOKUP(L73, 'Component Masterlist v2'!A:A, 'Component Masterlist v2'!P:P, "Not found")) -> GM | O73: =IF(P73="", "", P73/2) -> 30 | P73: =IF(M73="","",_xlfn.LET( _xlpm.pos, MATCH(M73,'Scrum Teams'!$B$2:$B$1006,0), _xlpm.val, INDEX('Scrum Teams'!$E$2:$E$1006,_xlpm.pos), IF(ISBLANK(INDEX('Scrum Teams'!$E$2:$E$1006,_xlpm.pos)),"",_xlpm.val) )) -> 60 | Q73: =IF(L73="","",IF(P73<>"", P73, 90)) -> 60 | R73: =IF(M73="","",IF(L73="", "Missing component", _xlfn.XLOOKUP(L73, Lookup!A:A, Lookup!D:D, "NA"))) -> Santosh Golecha
K74: {=IF(G74="","",_xlfn.LET( _xlpm.comp, TRIM(CLEAN(G74)), _xlpm.expected, J74, _xlpm.actual, SUMPRODUCT(--(TRIM(CLEAN($L$2:$L$140))=_xlpm.comp), $Q$2:$Q$140), IF(_xlpm.actual=_xlpm.expected, "No", "Mismatch by " & (_xlpm.actual-_xlpm.expected)) ))} | L74: =IF(M74="", "", _xlfn.XLOOKUP(M74,'Scrum Teams'!B:B,'Scrum Teams'!A:A,"")) -> DR_GM | M74: {=IFERROR(INDEX(_xlfn.SORTBY(_xlfn.UNIQUE(_xlfn._xlws.FILTER('Scrum Teams'!$B$2:$B$1006,'Scrum Teams'!$B$2:$B$1006<>"")),_xlfn.XLOOKUP(_xlfn.UNIQUE(_xlfn._xlws.FILTER('Scrum Teams'!$B$2:$B$1006,'Scrum Teams'!$B$2:$B$1006<>"")),'Scrum Teams'!$B:$B,'Scrum Teams'!$A:$A,"")),ROW()-1),"")} -> VSR, FE Platform | N74: =IF(L74="", "", _xlfn.XLOOKUP(L74, 'Component Masterlist v2'!A:A, 'Component Masterlist v2'!P:P, "Not found")) -> GM | O74: =IF(P74="", "", P74/2) -> 45 | P74: =IF(M74="","",_xlfn.LET( _xlpm.pos, MATCH(M74,'Scrum Teams'!$B$2:$B$1006,0), _xlpm.val, INDEX('Scrum Teams'!$E$2:$E$1006,_xlpm.pos), IF(ISBLANK(INDEX('Scrum Teams'!$E$2:$E$1006,_xlpm.pos)),"",_xlpm.val) )) -> 90 | Q74: =IF(L74="","",IF(P74<>"", P74, 90)) -> 90 | R74: =IF(M74="","",IF(L74="", "Missing component", _xlfn.XLOOKUP(L74, Lookup!A:A, Lookup!D:D, "NA"))) -> Santosh Golecha
K75: {=IF(G75="","",_xlfn.LET( _xlpm.comp, TRIM(CLEAN(G75)), _xlpm.expected, J75, _xlpm.actual, SUMPRODUCT(--(TRIM(CLEAN($L$2:$L$140))=_xlpm.comp), $Q$2:$Q$140), IF(_xlpm.actual=_xlpm.expected, "No", "Mismatch by " & (_xlpm.actual-_xlpm.expected)) ))} | L75: =IF(M75="", "", _xlfn.XLOOKUP(M75,'Scrum Teams'!B:B,'Scrum Teams'!A:A,"")) -> DR_Honda | M75: {=IFERROR(INDEX(_xlfn.SORTBY(_xlfn.UNIQUE(_xlfn._xlws.FILTER('Scrum Teams'!$B$2:$B$1006,'Scrum Teams'!$B$2:$B$1006<>"")),_xlfn.XLOOKUP(_xlfn.UNIQUE(_xlfn._xlws.FILTER('Scrum Teams'!$B$2:$B$1006,'Scrum Teams'!$B$2:$B$1006<>"")),'Scrum Teams'!$B:$B,'Scrum Teams'!$A:$A,"")),ROW()-1),"")} -> Honda DX | N75: =IF(L75="", "", _xlfn.XLOOKUP(L75, 'Component Masterlist v2'!A:A, 'Component Masterlist v2'!P:P, "Not found")) -> AHM | O75: =IF(P75="", "", P75/2) -> 34 | P75: =IF(M75="","",_xlfn.LET( _xlpm.pos, MATCH(M75,'Scrum Teams'!$B$2:$B$1006,0), _xlpm.val, INDEX('Scrum Teams'!$E$2:$E$1006,_xlpm.pos), IF(ISBLANK(INDEX('Scrum Teams'!$E$2:$E$1006,_xlpm.pos)),"",_xlpm.val) )) -> 68 | Q75: =IF(L75="","",IF(P75<>"", P75, 90)) -> 68 | R75: =IF(M75="","",IF(L75="", "Missing component", _xlfn.XLOOKUP(L75, Lookup!A:A, Lookup!D:D, "NA"))) -> Santosh Golecha
... K82: {=IF(G82="","",_xlfn.LET( _xlpm.comp, TRIM(CLEAN(G82)), _xlpm.expected, J82, _xlpm.actual, SUMPRODUCT(--(TRIM(CLEAN($L$2:$L$140))=_xlpm.comp), $Q$2:$Q$140), IF(_xlpm.actual=_xlpm.expected, "No", "Mismatch by " & (_xlpm.actual-_xlpm.expected)) ))} | L82: =IF(M82="", "", _xlfn.XLOOKUP(M82,'Scrum Teams'!B:B,'Scrum Teams'!A:A,"")) -> FnI | M82: {=IFERROR(INDEX(_xlfn.SORTBY(_xlfn.UNIQUE(_xlfn._xlws.FILTER('Scrum Teams'!$B$2:$B$1006,'Scrum Teams'!$B$2:$B$1006<>"")),_xlfn.XLOOKUP(_xlfn.UNIQUE(_xlfn._xlws.FILTER('Scrum Teams'!$B$2:$B$1006,'Scrum Teams'!$B$2:$B$1006<>"")),'Scrum Teams'!$B:$B,'Scrum Teams'!$A:$A,"")),ROW()-1),"")} -> Ganga | N82: =IF(L82="", "", _xlfn.XLOOKUP(L82, 'Component Masterlist v2'!A:A, 'Component Masterlist v2'!P:P, "Not found")) -> FNI | O82: =IF(P82="", "", P82/2) -> 81 | P82: =IF(M82="","",_xlfn.LET( _xlpm.pos, MATCH(M82,'Scrum Teams'!$B$2:$B$1006,0), _xlpm.val, INDEX('Scrum Teams'!$E$2:$E$1006,_xlpm.pos), IF(ISBLANK(INDEX('Scrum Teams'!$E$2:$E$1006,_xlpm.pos)),"",_xlpm.val) )) -> 162 | Q82: =IF(L82="","",IF(P82<>"", P82, 90)) -> 162 | R82: =IF(M82="","",IF(L82="", "Missing component", _xlfn.XLOOKUP(L82, Lookup!A:A, Lookup!D:D, "NA"))) -> Ved Singh
K83: {=IF(G83="","",_xlfn.LET( _xlpm.comp, TRIM(CLEAN(G83)), _xlpm.expected, J83, _xlpm.actual, SUMPRODUCT(--(TRIM(CLEAN($L$2:$L$140))=_xlpm.comp), $Q$2:$Q$140), IF(_xlpm.actual=_xlpm.expected, "No", "Mismatch by " & (_xlpm.actual-_xlpm.expected)) ))} | L83: =IF(M83="", "", _xlfn.XLOOKUP(M83,'Scrum Teams'!B:B,'Scrum Teams'!A:A,"")) -> FnI | M83: {=IFERROR(INDEX(_xlfn.SORTBY(_xlfn.UNIQUE(_xlfn._xlws.FILTER('Scrum Teams'!$B$2:$B$1006,'Scrum Teams'!$B$2:$B$1006<>"")),_xlfn.XLOOKUP(_xlfn.UNIQUE(_xlfn._xlws.FILTER('Scrum Teams'!$B$2:$B$1006,'Scrum Teams'!$B$2:$B$1006<>"")),'Scrum Teams'!$B:$B,'Scrum Teams'!$A:$A,"")),ROW()-1),"")} -> Godavari | N83: =IF(L83="", "", _xlfn.XLOOKUP(L83, 'Component Masterlist v2'!A:A, 'Component Masterlist v2'!P:P, "Not found")) -> FNI | O83: =IF(P83="", "", P83/2) -> 61 | P83: =IF(M83="","",_xlfn.LET( _xlpm.pos, MATCH(M83,'Scrum Teams'!$B$2:$B$1006,0), _xlpm.val, INDEX('Scrum Teams'!$E$2:$E$1006,_xlpm.pos), IF(ISBLANK(INDEX('Scrum Teams'!$E$2:$E$1006,_xlpm.pos)),"",_xlpm.val) )) -> 122 | Q83: =IF(L83="","",IF(P83<>"", P83, 90)) -> 122 | R83: =IF(M83="","",IF(L83="", "Missing component", _xlfn.XLOOKUP(L83, Lookup!A:A, Lookup!D:D, "NA"))) -> Ved Singh | T83: Core | U83: 402.5 | V83: 358 | W83: 656.5 | X83: 472.33333
K84: {=IF(G84="","",_xlfn.LET( _xlpm.comp, TRIM(CLEAN(G84)), _xlpm.expected, J84, _xlpm.actual, SUMPRODUCT(--(TRIM(CLEAN($L$2:$L$140))=_xlpm.comp), $Q$2:$Q$140), IF(_xlpm.actual=_xlpm.expected, "No", "Mismatch by " & (_xlpm.actual-_xlpm.expected)) ))} | L84: =IF(M84="", "", _xlfn.XLOOKUP(M84,'Scrum Teams'!B:B,'Scrum Teams'!A:A,"")) -> FnI | M84: {=IFERROR(INDEX(_xlfn.SORTBY(_xlfn.UNIQUE(_xlfn._xlws.FILTER('Scrum Teams'!$B$2:$B$1006,'Scrum Teams'!$B$2:$B$1006<>"")),_xlfn.XLOOKUP(_xlfn.UNIQUE(_xlfn._xlws.FILTER('Scrum Teams'!$B$2:$B$1006,'Scrum Teams'!$B$2:$B$1006<>"")),'Scrum Teams'!$B:$B,'Scrum Teams'!$A:$A,"")),ROW()-1),"")} -> Krishna | N84: =IF(L84="", "", _xlfn.XLOOKUP(L84, 'Component Masterlist v2'!A:A, 'Component Masterlist v2'!P:P, "Not found")) -> FNI | O84: =IF(P84="", "", P84/2) -> 70 | P84: =IF(M84="","",_xlfn.LET( _xlpm.pos, MATCH(M84,'Scrum Teams'!$B$2:$B$1006,0), _xlpm.val, INDEX('Scrum Teams'!$E$2:$E$1006,_xlpm.pos), IF(ISBLANK(INDEX('Scrum Teams'!$E$2:$E$1006,_xlpm.pos)),"",_xlpm.val) )) -> 140 | Q84: =IF(L84="","",IF(P84<>"", P84, 90)) -> 140 | R84: =IF(M84="","",IF(L84="", "Missing component", _xlfn.XLOOKUP(L84, Lookup!A:A, Lookup!D:D, "NA"))) -> Ved Singh | T84: DataPlatform | U84: 16 | V84: 62 | W84: 22 | X84: 33.333333
K85: {=IF(G85="","",_xlfn.LET( _xlpm.comp, TRIM(CLEAN(G85)), _xlpm.expected, J85, _xlpm.actual, SUMPRODUCT(--(TRIM(CLEAN($L$2:$L$140))=_xlpm.comp), $Q$2:$Q$140), IF(_xlpm.actual=_xlpm.expected, "No", "Mismatch by " & (_xlpm.actual-_xlpm.expected)) ))} | L85: =IF(M85="", "", _xlfn.XLOOKUP(M85,'Scrum Teams'!B:B,'Scrum Teams'!A:A,"")) -> FnI | M85: {=IFERROR(INDEX(_xlfn.SORTBY(_xlfn.UNIQUE(_xlfn._xlws.FILTER('Scrum Teams'!$B$2:$B$1006,'Scrum Teams'!$B$2:$B$1006<>"")),_xlfn.XLOOKUP(_xlfn.UNIQUE(_xlfn._xlws.FILTER('Scrum Teams'!$B$2:$B$1006,'Scrum Teams'!$B$2:$B$1006<>"")),'Scrum Teams'!$B:$B,'Scrum Teams'!$A:$A,"")),ROW()-1),"")} -> Saryu | N85: =IF(L85="", "", _xlfn.XLOOKUP(L85, 'Component Masterlist v2'!A:A, 'Component Masterlist v2'!P:P, "Not found")) -> FNI | O85: =IF(P85="", "", P85/2) -> 80 | P85: =IF(M85="","",_xlfn.LET( _xlpm.pos, MATCH(M85,'Scrum Teams'!$B$2:$B$1006,0), _xlpm.val, INDEX('Scrum Teams'!$E$2:$E$1006,_xlpm.pos), IF(ISBLANK(INDEX('Scrum Teams'!$E$2:$E$1006,_xlpm.pos)),"",_xlpm.val) )) -> 160 | Q85: =IF(L85="","",IF(P85<>"", P85, 90)) -> 160 | R85: =IF(M85="","",IF(L85="", "Missing component", _xlfn.XLOOKUP(L85, Lookup!A:A, Lookup!D:D, "NA"))) -> Ved Singh | T85: eSign Platform | U85: 0 | V85: 101 | W85: 25 | X85: 42
K86: {=IF(G86="","",_xlfn.LET( _xlpm.comp, TRIM(CLEAN(G86)), _xlpm.expected, J86, _xlpm.actual, SUMPRODUCT(--(TRIM(CLEAN($L$2:$L$140))=_xlpm.comp), $Q$2:$Q$140), IF(_xlpm.actual=_xlpm.expected, "No", "Mismatch by " & (_xlpm.actual-_xlpm.expected)) ))} | L86: =IF(M86="", "", _xlfn.XLOOKUP(M86,'Scrum Teams'!B:B,'Scrum Teams'!A:A,"")) -> FnI | M86: {=IFERROR(INDEX(_xlfn.SORTBY(_xlfn.UNIQUE(_xlfn._xlws.FILTER('Scrum Teams'!$B$2:$B$1006,'Scrum Teams'!$B$2:$B$1006<>"")),_xlfn.XLOOKUP(_xlfn.UNIQUE(_xlfn._xlws.FILTER('Scrum Teams'!$B$2:$B$1006,'Scrum Teams'!$B$2:$B$1006<>"")),'Scrum Teams'!$B:$B,'Scrum Teams'!$A:$A,"")),ROW()-1),"")} -> Yamuna | N86: =IF(L86="", "", _xlfn.XLOOKUP(L86, 'Component Masterlist v2'!A:A, 'Component Masterlist v2'!P:P, "Not found")) -> FNI | O86: =IF(P86="", "", P86/2) -> 76 | P86: =IF(M86="","",_xlfn.LET( _xlpm.pos, MATCH(M86,'Scrum Teams'!$B$2:$B$1006,0), _xlpm.val, INDEX('Scrum Teams'!$E$2:$E$1006,_xlpm.pos), IF(ISBLANK(INDEX('Scrum Teams'!$E$2:$E$1006,_xlpm.pos)),"",_xlpm.val) )) -> 152 | Q86: =IF(L86="","",IF(P86<>"", P86, 90)) -> 152 | R86: =IF(M86="","",IF(L86="", "Missing component", _xlfn.XLOOKUP(L86, Lookup!A:A, Lookup!D:D, "NA"))) -> Ved Singh | T86: FnI | U86: 0 | V86: 0 | W86: 70 | X86: 23.333333
K87: {=IF(G87="","",_xlfn.LET( _xlpm.comp, TRIM(CLEAN(G87)), _xlpm.expected, J87, _xlpm.actual, SUMPRODUCT(--(TRIM(CLEAN($L$2:$L$140))=_xlpm.comp), $Q$2:$Q$140), IF(_xlpm.actual=_xlpm.expected, "No", "Mismatch by " & (_xlpm.actual-_xlpm.expected)) ))} | L87: =IF(M87="", "", _xlfn.XLOOKUP(M87,'Scrum Teams'!B:B,'Scrum Teams'!A:A,"")) -> Galaxy | M87: {=IFERROR(INDEX(_xlfn.SORTBY(_xlfn.UNIQUE(_xlfn._xlws.FILTER('Scrum Teams'!$B$2:$B$1006,'Scrum Teams'!$B$2:$B$1006<>"")),_xlfn.XLOOKUP(_xlfn.UNIQUE(_xlfn._xlws.FILTER('Scrum Teams'!$B$2:$B$1006,'Scrum Teams'!$B$2:$B$1006<>"")),'Scrum Teams'!$B:$B,'Scrum Teams'!$A:$A,"")),ROW()-1),"")} -> Kaveri | N87: =IF(L87="", "", _xlfn.XLOOKUP(L87, 'Component Masterlist v2'!A:A, 'Component Masterlist v2'!P:P, "Not found")) -> GAL | O87: =IF(P87="", "", P87/2) -> 90 | P87: =IF(M87="","",_xlfn.LET( _xlpm.pos, MATCH(M87,'Scrum Teams'!$B$2:$B$1006,0), _xlpm.val, INDEX('Scrum Teams'!$E$2:$E$1006,_xlpm.pos), IF(ISBLANK(INDEX('Scrum Teams'!$E$2:$E$1006,_xlpm.pos)),"",_xlpm.val) )) -> 180 | Q87: =IF(L87="","",IF(P87<>"", P87, 90)) -> 180 | R87: =IF(M87="","",IF(L87="", "Missing component", _xlfn.XLOOKUP(L87, Lookup!A:A, Lookup!D:D, "NA"))) -> Ved Singh | T87: Galaxy | U87: 135.5 | V87: 74 | W87: 101 | X87: 103.5
K88: {=IF(G88="","",_xlfn.LET( _xlpm.comp, TRIM(CLEAN(G88)), _xlpm.expected, J88, _xlpm.actual, SUMPRODUCT(--(TRIM(CLEAN($L$2:$L$140))=_xlpm.comp), $Q$2:$Q$140), IF(_xlpm.actual=_xlpm.expected, "No", "Mismatch by " & (_xlpm.actual-_xlpm.expected)) ))} | L88: =IF(M88="", "", _xlfn.XLOOKUP(M88,'Scrum Teams'!B:B,'Scrum Teams'!A:A,"")) -> HorizontalPlatforms | M88: {=IFERROR(INDEX(_xlfn.SORTBY(_xlfn.UNIQUE(_xlfn._xlws.FILTER('Scrum Teams'!$B$2:$B$1006,'Scrum Teams'!$B$2:$B$1006<>"")),_xlfn.XLOOKUP(_xlfn.UNIQUE(_xlfn._xlws.FILTER('Scrum Teams'!$B$2:$B$1006,'Scrum Teams'!$B$2:$B$1006<>"")),'Scrum Teams'!$B:$B,'Scrum Teams'!$A:$A,"")),ROW()-1),"")} -> HP-AI_Native | N88: =IF(L88="", "", _xlfn.XLOOKUP(L88, 'Component Masterlist v2'!A:A, 'Component Masterlist v2'!P:P, "Not found")) -> HPLT | O88: =IF(P88="", "", P88/2) -> 15 | P88: =IF(M88="","",_xlfn.LET( _xlpm.pos, MATCH(M88,'Scrum Teams'!$B$2:$B$1006,0), _xlpm.val, INDEX('Scrum Teams'!$E$2:$E$1006,_xlpm.pos), IF(ISBLANK(INDEX('Scrum Teams'!$E$2:$E$1006,_xlpm.pos)),"",_xlpm.val) )) -> 30 | Q88: =IF(L88="","",IF(P88<>"", P88, 90)) -> 30 | R88: =IF(M88="","",IF(L88="", "Missing component", _xlfn.XLOOKUP(L88, Lookup!A:A, Lookup!D:D, "NA"))) -> Raghu Edalur | T88: MobilePlatform | U88: 0 | V88: 0 | W88: 27 | X88: 9
K89: {=IF(G89="","",_xlfn.LET( _xlpm.comp, TRIM(CLEAN(G89)), _xlpm.expected, J89, _xlpm.actual, SUMPRODUCT(--(TRIM(CLEAN($L$2:$L$140))=_xlpm.comp), $Q$2:$Q$140), IF(_xlpm.actual=_xlpm.expected, "No", "Mismatch by " & (_xlpm.actual-_xlpm.expected)) ))} | L89: =IF(M89="", "", _xlfn.XLOOKUP(M89,'Scrum Teams'!B:B,'Scrum Teams'!A:A,"")) -> HorizontalPlatforms | M89: {=IFERROR(INDEX(_xlfn.SORTBY(_xlfn.UNIQUE(_xlfn._xlws.FILTER('Scrum Teams'!$B$2:$B$1006,'Scrum Teams'!$B$2:$B$1006<>"")),_xlfn.XLOOKUP(_xlfn.UNIQUE(_xlfn._xlws.FILTER('Scrum Teams'!$B$2:$B$1006,'Scrum Teams'!$B$2:$B$1006<>"")),'Scrum Teams'!$B:$B,'Scrum Teams'!$A:$A,"")),ROW()-1),"")} -> HP-Caching_and_Messaging | N89: =IF(L89="", "", _xlfn.XLOOKUP(L89, 'Component Masterlist v2'!A:A, 'Component Masterlist v2'!P:P, "Not found")) -> HPLT | O89: =IF(P89="", "", P89/2) -> 15 | P89: =IF(M89="","",_xlfn.LET( _xlpm.pos, MATCH(M89,'Scrum Teams'!$B$2:$B$1006,0), _xlpm.val, INDEX('Scrum Teams'!$E$2:$E$1006,_xlpm.pos), IF(ISBLANK(INDEX('Scrum Teams'!$E$2:$E$1006,_xlpm.pos)),"",_xlpm.val) )) -> 30 | Q89: =IF(L89="","",IF(P89<>"", P89, 90)) -> 30 | R89: =IF(M89="","",IF(L89="", "Missing component", _xlfn.XLOOKUP(L89, Lookup!A:A, Lookup!D:D, "NA"))) -> Raghu Edalur | T89: Parts | U89: 492.5 | V89: 175.2 | W89: 284 | X89: 317.23333
